Workbook

Sheet README
A1: NIST CSF 2.0 Document Framework: Document Register and Traceability
A2: Purpose: one list of every controlled document, its classification, ownership, and mapping to NIST CSF 2.0, ISO/IEC 27001:2022, NIST SP 800-53 Rev. 5, and Thai law.
A3: Sheets: Summary (counts by formula), Document Register (one row per document), Implementation Roadmap (recommended build order), Prerequisite Activities (meetings and workshops with agendas), Process Flows (operating chains), CSF Traceability (one row per CSF 2.0 subcategory), Hierarchy (parent to child links), Verify List (items to confirm with current Thai regulations).
A4: ISO 27002 Theme: the theme of the first ISO/IEC 27001:2022 Annex A control mapped to the document (A.5 Organizational, A.6 People, A.7 Physical, A.8 Technological); documents mapped only to management system clauses count as Organizational. NIST does not publish a theme grouping.
A5: Build Order, Wave, Track: practitioner guidance for an organization starting from scratch. Track A builds governance in overlapping waves (W0 Mandate to W5 Optimize). Track B runs threat-driven quick wins in parallel from day one.
A6: Capability: IT-ready = in-house IT can produce it from the template; Specialist-guided = IT drafts, a cybersecurity specialist facilitates or reviews; Specialist-required = needs a security FTE, consultant, or managed service.
A7: Level: Required = mandated by law or a certifiable standard when the Trigger applies; Expected = auditors, regulators, or customers expect it; Optional = adds value at higher maturity.
A8: Trigger: All, PDPA, ISO 27001 (certification), CII (Critical Information Infrastructure), CCA (service provider under the Computer Crime Act B.E. 2550 s.26).
A9: Package (cumulative): Essential = the smallest self-contained starter set every organization should have; Core = the rest of the full baseline, built on Essential (every Core document sits under an Essential document); Extended = higher maturity or specific contexts. Level answers whether a document is mandated; Package answers how much to adopt for the organization's size. A Required document applies whenever its trigger applies, whatever its package.
A10: Edit cells in the Document Register to track your own status; the Summary sheet recalculates.
A11: References as of October 2026. Items marked [VERIFY] must be confirmed against current Thai regulations before use. This pack is a sample and is not legal advice.

Sheet Summary
A1: Summary (formulas reference the Document Register sheet)
A3: By Function | B3: Count
A4: Govern | B4: =COUNTIF('Document Register'!$D$2:$D$143,"Govern*") -> 47
A5: Identify | B5: =COUNTIF('Document Register'!$D$2:$D$143,"Identify*") -> 23
A6: Protect | B6: =COUNTIF('Document Register'!$D$2:$D$143,"Protect*") -> 41
A7: Detect | B7: =COUNTIF('Document Register'!$D$2:$D$143,"Detect*") -> 8
A8: Respond | B8: =COUNTIF('Document Register'!$D$2:$D$143,"Respond*") -> 14
A9: Recover | B9: =COUNTIF('Document Register'!$D$2:$D$143,"Recover*") -> 9
A10: Total | B10: =SUM(B4:B9) -> 142
A12: By Tier | B12: Count
A13: T0 | B13: =COUNTIF('Document Register'!$F$2:$F$143,"T0*") -> 4
A14: T1 | B14: =COUNTIF('Document Register'!$F$2:$F$143,"T1*") -> 10
A15: T2 | B15: =COUNTIF('Document Register'!$F$2:$F$143,"T2*") -> 24
A16: T3 | B16: =COUNTIF('Document Register'!$F$2:$F$143,"T3*") -> 44
A17: T4 | B17: =COUNTIF('Document Register'!$F$2:$F$143,"T4*") -> 60
A18: Total | B18: =SUM(B13:B17) -> 142
A20: By ISO/IEC 27002 Theme | B20: Count
A21: Organizational | B21: =COUNTIF('Document Register'!$H$2:$H$143,"Organizational*") -> 94
A22: People | B22: =COUNTIF('Document Register'!$H$2:$H$143,"People*") -> 8
A23: Physical | B23: =COUNTIF('Document Register'!$H$2:$H$143,"Physical*") -> 4
A24: Technological | B24: =COUNTIF('Document Register'!$H$2:$H$143,"Technological*") -> 36
A25: Total | B25: =SUM(B21:B24) -> 142
A27: By Wave (recommended build order) | B27: Count
A28: W0 Mandate and Mobilize | B28: =COUNTIF('Document Register'!$X$2:$X$143,"W0 Mandate and Mobilize*") -> 15
A29: W1 Understand | B29: =COUNTIF('Document Register'!$X$2:$X$143,"W1 Understand*") -> 22
A30: W2 Direct | B30: =COUNTIF('Document Register'!$X$2:$X$143,"W2 Direct*") -> 25
A31: W3 Standardize | B31: =COUNTIF('Document Register'!$X$2:$X$143,"W3 Standardize*") -> 57
A32: W4 Operate and Prove | B32: =COUNTIF('Document Register'!$X$2:$X$143,"W4 Operate and Prove*") -> 14
A33: W5 Optimize | B33: =COUNTIF('Document Register'!$X$2:$X$143,"W5 Optimize*") -> 9
A34: Total | B34: =SUM(B28:B33) -> 142
A36: By Capability | B36: Count
A37: IT-ready | B37: =COUNTIF('Document Register'!$Z$2:$Z$143,"IT-ready*") -> 54
A38: Specialist-guided | B38: =COUNTIF('Document Register'!$Z$2:$Z$143,"Specialist-guided*") -> 54
A39: Specialist-required | B39: =COUNTIF('Document Register'!$Z$2:$Z$143,"Specialist-required*") -> 34
A40: Total | B40: =SUM(B37:B39) -> 142
A42: By Package | B42: Count
A43: Essential | B43: =COUNTIF('Document Register'!$I$2:$I$143,"Essential*") -> 59
A44: Core | B44: =COUNTIF('Document Register'!$I$2:$I$143,"Core*") -> 67
A45: Extended | B45: =COUNTIF('Document Register'!$I$2:$I$143,"Extended*") -> 16
A46: Total | B46: =SUM(B43:B45) -> 142
A48: By Level | B48: Count
A49: Required | B49: =COUNTIF('Document Register'!$J$2:$J$143,"Required*") -> 23
A50: Expected | B50: =COUNTIF('Document Register'!$J$2:$J$143,"Expected*") -> 110
A51: Optional | B51: =COUNTIF('Document Register'!$J$2:$J$143,"Optional*") -> 9
A52: Total | B52: =SUM(B49:B51) -> 142
A54: By Status (your organization) | B54: Count
A55: Not started | B55: =COUNTIF('Document Register'!$AE$2:$AE$143,"Not started*") -> 142
A56: Drafting | B56: =COUNTIF('Document Register'!$AE$2:$AE$143,"Drafting*") -> 0
A57: In review | B57: =COUNTIF('Document Register'!$AE$2:$AE$143,"In review*") -> 0
A58: Approved | B58: =COUNTIF('Document Register'!$AE$2:$AE$143,"Approved*") -> 0
A59: Not applicable | B59: =COUNTIF('Document Register'!$AE$2:$AE$143,"Not applicable*") -> 0
A60: Total | B60: =SUM(B55:B59) -> 142
A62: CSF 2.0 subcategories covered | B62: =COUNTIF('CSF Traceability'!$F$2:$F$107,">0") -> 106
A63: CSF 2.0 subcategories in total | B63: =COUNTA('CSF Traceability'!$A$2:$A$107) -> 106

Sheet Document Register
A1: Document ID | B1: Title (EN) | C1: Title (TH) | D1: Function | E1: Category | F1: Tier | G1: Type | H1: ISO 27002 Theme | I1: Package | J1: Level | K1: Trigger | L1: Basis | M1: Level for CMC | N1: CSF 2.0 Subcategories | O1: ISO/IEC 27001:2022 | P1: NIST SP 800-53 Rev. 5 | Q1: Owner (role) | R1: Approver (role) | S1: Review Cycle | T1: Parent Documents | U1: Child Documents | V1: Tags | W1: Build Order | X1: Wave | Y1: Track | Z1: Capability | AA1: Sourcing Options | AB1: Prerequisite Activities | AC1: Depends On | AD1: File (Template EN) | AE1: Status (your organization)
A2: GV-CHR-001 | B2: Cybersecurity Governance Charter | C2: กฎบัตรการกำกับดูแลความมั่นคงปลอดภัยไซเบอร์ | D2: Govern (GV) | E2: Organizational Context (GV.OC) | F2: T0 | G2: Charter | H2: Organizational | I2: Essential | J2: Expected | K2: All | L2: ISO/IEC 27001:2022 Clause 5.1 and 5.3; CSA s.44 (CII) | M2: Expected | N2: GV.OC-01, GV.RR-01, GV.OV-01 | O2: 5.1, 5.3, A.5.4 | P2: PM-1, PM-2, PM-29 | Q2: Chief Information Security Officer (CISO) or Security Manager | R2: Board of Directors | S2: Annual | U2: GV-STR-001, GV-RPT-001, GV-STM-001, GV-CHR-002, GV-REG-003, GV-POL-001, GV-PRC-007, RC-POL-001 | V2: Governance | W2: 1 | X2: W0 Mandate and Mobilize | Y2: Track A | Z2: Specialist-guided | AA2: In-house IT / Cybersecurity consultant (project) | AB2: ACT-01 Executive Kickoff and Mandate Meeting; ACT-02 Governance Structure and RACI Workshop | AD2: 02_Template_EN/01_GV_Govern/GV.OC_Organizational-Context/GV-CHR-001_Cybersecurity-Governance-Charter.docx | AE2: Not started
A3: GV-STR-001 | B3: Cybersecurity Strategy and Roadmap | C3: ยุทธศาสตร์และแผนงานด้านความมั่นคงปลอดภัยไซเบอร์ | D3: Govern (GV) | E3: Organizational Context (GV.OC) | F3: T0 | G3: Strategy | H3: Organizational | I3: Core | J3: Required | K3: ISO 27001 | L3: ISO/IEC 27001:2022 Clause 6.2 (documented information on information security objectives; the roadmap section is common practice) | M3: Expected | N3: GV.OC-01, GV.RM-01, GV.OV-01 | O3: 6.2 | P3: PM-1, PM-9 | Q3: Chief Information Security Officer (CISO) or Security Manager | R3: Board of Directors | S3: Annual | T3: GV-CHR-001 | U3: GV-PLN-001, GV-REG-008 | V3: Governance | W3: 38 | X3: W2 Direct | Y3: Track A | Z3: Specialist-guided | AA3: Cybersecurity consultant (project) / Security FTE | AB3: ACT-11 Current State Assessment and CSF Profile Gap Analysis; ACT-12 Strategy, Roadmap, and Budget Planning Session | AC3: ID-RPT-003, GV-RPT-001 | AD3: 02_Template_EN/01_GV_Govern/GV.OC_Organizational-Context/GV-STR-001_Cybersecurity-Strategy-and-Roadmap.docx | AE3: Not started
A4: GV-RPT-001 | B4: Organizational Context and ISMS Scope Statement | C4: เอกสารบริบทองค์กรและขอบเขตระบบบริหารจัดการความมั่นคงปลอดภัยสารสนเทศ | D4: Govern (GV) | E4: Organizational Context (GV.OC) | F4: T4 | G4: Report | H4: Organizational | I4: Core | J4: Required | K4: ISO 27001 | L4: ISO/IEC 27001:2022 Clause 4.3 (scope as documented information) | M4: Expected | N4: GV.OC-01, GV.OC-02, GV.OC-04, GV.OC-05 | O4: 4.1, 4.2, 4.3 | P4: PM-11, PM-8 | Q4: Chief Information Security Officer (CISO) or Security Manager | R4: Information Security Steering Committee (ISSC) | S4: Annual | T4: GV-CHR-001 | U4: GV-REG-001, GV-REG-002 | V4: Governance, Evidence | W4: 16 | X4: W1 Understand | Y4: Track A | Z4: Specialist-guided | AA4: Cybersecurity consultant (project) / Security FTE | AB4: ACT-04 Scope and Organizational Context Workshop | AC4: GV-CHR-001, GV-REG-001 | AD4: 02_Template_EN/01_GV_Govern/GV.OC_Organizational-Context/GV-RPT-001_Organizational-Context-and-ISMS-Scope-Statement.docx | AE4: Not started
A5: GV-REG-001 | B5: Legal, Regulatory, and Contractual Requirements Register | C5: ทะเบียนข้อกำหนดด้านกฎหมาย ระเบียบ และสัญญา | D5: Govern (GV) | E5: Organizational Context (GV.OC) | F5: T4 | G5: Register | H5: Organizational | I5: Essential | J5: Expected | K5: All | L5: ISO/IEC 27001:2022 Annex A 5.31; PDPA; CSA | M5: Expected | N5: GV.OC-03 | O5: A.5.31, A.5.32, A.5.34 | P5: PM-1, PT-1 | Q5: Legal Counsel | R5: Information Security Steering Committee (ISSC) | S5: Annual and on legal change | T5: GV-RPT-001 | U5: GV-REG-006 | V5: Governance, Evidence, Legal and Regulatory | W5: 4 | X5: W0 Mandate and Mobilize | Y5: Track A | Z5: Specialist-required | AA5: Legal counsel / Cybersecurity consultant (project) | AB5: ACT-03 Legal and Regulatory Applicability Review | AD5: 02_Template_EN/01_GV_Govern/GV.OC_Organizational-Context/GV-REG-001_Legal-Regulatory-and-Contractual-Requirements-Register.docx | AE5: Not started
A6: GV-REG-002 | B6: Stakeholder Requirements Register | C6: ทะเบียนความคาดหวังของผู้มีส่วนได้ส่วนเสีย | D6: Govern (GV) | E6: Organizational Context (GV.OC) | F6: T4 | G6: Register | H6: Organizational | I6: Extended | J6: Expected | K6: ISO 27001 | L6: ISO/IEC 27001:2022 Clause 4.2 (not mandated as documented information) | M6: Expected | N6: GV.OC-02 | O6: 4.2 | P6: PM-11 | Q6: Chief Information Security Officer (CISO) or Security Manager | R6: Information Security Steering Committee (ISSC) | S6: Annual | T6: GV-RPT-001 | V6: Governance, Evidence | W6: 17 | X6: W1 Understand | Y6: Track A | Z6: IT-ready | AA6: In-house IT | AB6: ACT-04 Scope and Organizational Context Workshop | AC6: GV-RPT-001 | AD6: 02_Template_EN/01_GV_Govern/GV.OC_Organizational-Context/GV-REG-002_Stakeholder-Requirements-Register.docx | AE6: Not started
A7: GV-STM-001 | B7: Risk Appetite and Tolerance Statement | C7: แถลงการณ์ระดับความเสี่ยงที่ยอมรับได้และค่าเบี่ยงเบนที่ยอมรับได้ | D7: Govern (GV) | E7: Risk Management Strategy (GV.RM) | F7: T0 | G7: Statement | H7: Organizational | I7: Essential | J7: Expected | K7: All | L7: NIST IR 8286; ISO/IEC 27001:2022 Clause 6.1.2(a) risk acceptance criteria | M7: Expected | N7: GV.RM-01, GV.RM-02, GV.RM-03 | O7: 6.1.2 | P7: PM-9, PM-28 | Q7: Chief Risk Officer (CRO) or Enterprise Risk Manager | R7: Board of Directors | S7: Annual | T7: GV-CHR-001 | U7: GV-POL-002 | V7: Governance | W7: 29 | X7: W1 Understand | Y7: Track A | Z7: Specialist-required | AA7: Cybersecurity consultant (project) | AB7: ACT-08 Risk Appetite Workshop | AC7: ID-RPT-002, GV-CHR-001 | AD7: 02_Template_EN/01_GV_Govern/GV.RM_Risk-Management-Strategy/GV-STM-001_Risk-Appetite-and-Tolerance-Statement.docx | AE7: Not started
A8: GV-POL-002 | B8: Cybersecurity Risk Management Policy | C8: นโยบายการบริหารความเสี่ยงด้านความมั่นคงปลอดภัยไซเบอร์ | D8: Govern (GV) | E8: Risk Management Strategy (GV.RM) | F8: T1 | G8: Policy | H8: Organizational | I8: Essential | J8: Expected | K8: All | L8: ISO/IEC 27001:2022 Clause 6.1; CSA s.44 (CII) | M8: Expected | N8: GV.RM-01, GV.RM-03, GV.RM-04, GV.RM-05, GV.RM-07, GV.SC-03 | O8: 6.1, 8.2, 8.3 | P8: RA-1, PM-9 | Q8: Chief Information Security Officer (CISO) or Security Manager | R8: Chief Executive Officer (CEO) | S8: Annual | T8: GV-POL-001, GV-STM-001 | U8: GV-PRC-001 | V8: Governance | W8: 30 | X8: W1 Understand | Y8: Track A | Z8: Specialist-guided | AA8: Cybersecurity consultant (project) / Security FTE | AB8: ACT-13 Policy Drafting and Stakeholder Review Cycle; ACT-14 Policy Approval and Communication | AC8: GV-POL-001, GV-STM-001 | AD8: 02_Template_EN/01_GV_Govern/GV.RM_Risk-Management-Strategy/GV-POL-002_Cybersecurity-Risk-Management-Policy.docx | AE8: Not started
A9: GV-PRC-001 | B9: Risk Assessment and Treatment Methodology | C9: ระเบียบวิธีการประเมินและจัดการความเสี่ยง | D9: Govern (GV) | E9: Risk Management Strategy (GV.RM) | F9: T3 | G9: Procedure | H9: Organizational | I9: Essential | J9: Required | K9: ISO 27001, CII | L9: ISO/IEC 27001:2022 Clause 6.1.2 and 6.1.3 (documented process); CSA s.54 | M9: Required | N9: GV.RM-06, ID.RA-03, ID.RA-04, ID.RA-05, ID.RA-06 | O9: 6.1.2, 6.1.3 | P9: RA-3, PM-9 | Q9: Chief Information Security Officer (CISO) or Security Manager | R9: Information Security Steering Committee (ISSC) | S9: Annual | T9: GV-POL-002 | U9: GV-FRM-001, GV-REG-005, ID-REG-005, ID-RPT-003, ID-PRC-004 | V9: Process, Legal and Regulatory | W9: 31 | X9: W1 Understand | Y9: Track A | Z9: Specialist-required | AA9: Cybersecurity consultant (project) / Security FTE | AB9: ACT-09 Risk Methodology Design and Calibration Session | AC9: GV-POL-002 | AD9: 02_Template_EN/01_GV_Govern/GV.RM_Risk-Management-Strategy/GV-PRC-001_Risk-Assessment-and-Treatment-Methodology.docx | AE9: Not started
A10: GV-FRM-001 | B10: Risk Acceptance Form | C10: แบบฟอร์มการยอมรับความเสี่ยง | D10: Govern (GV) | E10: Risk Management Strategy (GV.RM) | F10: T4 | G10: Form | H10: Organizational | I10: Core | J10: Expected | K10: ISO 27001 | L10: ISO/IEC 27001:2022 Clause 6.1.3(f) (risk owner approval of residual risk) | M10: Expected | N10: GV.RM-04, ID.RA-06 | O10: 6.1.3 | P10: RA-7, PM-9 | Q10: Chief Information Security Officer (CISO) or Security Manager | R10: Risk Owner | S10: Annual | T10: GV-PRC-001 | V10: Process, Evidence | W10: 41 | X10: W2 Direct | Y10: Track A | Z10: IT-ready | AA10: In-house IT | AC10: GV-PRC-001 | AD10: 02_Template_EN/01_GV_Govern/GV.RM_Risk-Management-Strategy/GV-FRM-001_Risk-Acceptance-Form.docx | AE10: Not started
A11: GV-CHR-002 | B11: Information Security Steering Committee Terms of Reference | C11: ขอบเขตอำนาจหน้าที่คณะกรรมการกำกับดูแลความมั่นคงปลอดภัยสารสนเทศ | D11: Govern (GV) | E11: Roles, Responsibilities, and Authorities (GV.RR) | F11: T0 | G11: Charter | H11: Organizational | I11: Essential | J11: Expected | K11: All | L11: ISO/IEC 27001:2022 Clause 5.1 and 5.3 | M11: Expected | N11: GV.RR-01, GV.OV-01, GV.OV-02 | O11: 5.1, 5.3 | P11: PM-2, PM-29 | Q11: Chief Information Security Officer (CISO) or Security Manager | R11: Chief Executive Officer (CEO) | S11: Annual | T11: GV-CHR-001 | U11: GV-PRC-006 | V11: Governance | W11: 2 | X11: W0 Mandate and Mobilize | Y11: Track A | Z11: IT-ready | AA11: In-house IT | AB11: ACT-02 Governance Structure and RACI Workshop | AC11: GV-CHR-001 | AD11: 02_Template_EN/01_GV_Govern/GV.RR_Roles-Responsibilities-and-Authorities/GV-CHR-002_Information-Security-Steering-Committee-Terms-of-Reference.docx | AE11: Not started
A12: GV-REG-003 | B12: Cybersecurity Roles, Responsibilities, and RACI Matrix | C12: ตารางบทบาท หน้าที่ และความรับผิดชอบด้านความมั่นคงปลอดภัย (RACI) | D12: Govern (GV) | E12: Roles, Responsibilities, and Authorities (GV.RR) | F12: T4 | G12: Register | H12: Organizational | I12: Essential | J12: Expected | K12: ISO 27001, CII | L12: ISO/IEC 27001:2022 Clause 5.3 and Annex A 5.2; CSA s.46 and s.52 (CII contact officers) | M12: Expected | N12: GV.RR-01, GV.RR-02 | O12: 5.3, A.5.2, A.5.3 | P12: PM-2, PS-9 | Q12: Chief Information Security Officer (CISO) or Security Manager | R12: Chief Information Officer (CIO) | S12: Annual | T12: GV-CHR-001 | U12: GV-TPL-001 | V12: People, Legal and Regulatory, Evidence | W12: 3 | X12: W0 Mandate and Mobilize | Y12: Track A | Z12: Specialist-guided | AA12: In-house IT / Cybersecurity consultant (project) | AB12: ACT-02 Governance Structure and RACI Workshop | AC12: GV-CHR-002 | AD12: 02_Template_EN/01_GV_Govern/GV.RR_Roles-Responsibilities-and-Authorities/GV-REG-003_Cybersecurity-Roles-Responsibilities-and-RACI-Matrix.docx | AE12: Not started
A13: GV-TPL-001 | B13: Cybersecurity Job Description Templates | C13: แม่แบบคำบรรยายลักษณะงานด้านความมั่นคงปลอดภัย | D13: Govern (GV) | E13: Roles, Responsibilities, and Authorities (GV.RR) | F13: T4 | G13: Template | H13: Organizational | I13: Extended | J13: Optional | K13: All | L13: Common practice; NICE Workforce Framework (NIST SP 800-181 Rev. 1) | M13: Optional | N13: GV.RR-02, GV.RR-04 | O13: A.5.2 | P13: PS-9 | Q13: Human Resources Director | R13: Chief Information Officer (CIO) | S13: Annual | T13: GV-REG-003 | V13: People, Evidence | W13: 134 | X13: W5 Optimize | Y13: Track A | Z13: IT-ready | AA13: Human Resources | AC13: GV-REG-003 | AD13: 02_Template_EN/01_GV_Govern/GV.RR_Roles-Responsibilities-and-Authorities/GV-TPL-001_Cybersecurity-Job-Description-Templates.docx | AE13: Not started
A14: GV-PLN-001 | B14: Cybersecurity Budget and Resource Plan | C14: แผนงบประมาณและทรัพยากรด้านความมั่นคงปลอดภัยไซเบอร์ | D14: Govern (GV) | E14: Roles, Responsibilities, and Authorities (GV.RR) | F14: T3 | G14: Plan | H14: Organizational | I14: Core | J14: Expected | K14: ISO 27001 | L14: ISO/IEC 27001:2022 Clause 7.1 (resources; not mandated as documented information) | M14: Expected | N14: GV.RR-03 | O14: 7.1 | P14: PM-3 | Q14: Chief Information Security Officer (CISO) or Security Manager | R14: Chief Financial Officer (CFO) | S14: Annual | T14: GV-STR-001 | V14: Governance | W14: 39 | X14: W2 Direct | Y14: Track A | Z14: Specialist-guided | AA14: Security FTE / In-house IT | AB14: ACT-12 Strategy, Roadmap, and Budget Planning Session | AC14: GV-STR-001 | AD14: 02_Template_EN/01_GV_Govern/GV.RR_Roles-Responsibilities-and-Authorities/GV-PLN-001_Cybersecurity-Budget-and-Resource-Plan.docx | AE14: Not started
A15: GV-STD-001 | B15: Human Resources Security Standard | C15: มาตรฐานความมั่นคงปลอดภัยด้านทรัพยากรบุคคล | D15: Govern (GV) | E15: Roles, Responsibilities, and Authorities (GV.RR) | F15: T2 | G15: Standard | H15: People | I15: Essential | J15: Expected | K15: All | L15: ISO/IEC 27001:2022 Annex A 6.1 to 6.5 | M15: Expected | N15: GV.RR-04, PR.AA-05 | O15: A.6.1, A.6.2, A.6.4, A.6.5 | P15: PS-2, PS-3, PS-4, PS-5, PS-7, PS-8 | Q15: Human Resources Director | R15: Information Security Steering Committee (ISSC) | S15: Annual | T15: GV-POL-001 | U15: GV-FRM-002, GV-FRM-003 | V15: People | W15: 51 | X15: W2 Direct | Y15: Track A | Z15: IT-ready | AA15: Human Resources | AB15: ACT-13 Policy Drafting and Stakeholder Review Cycle | AC15: GV-POL-001 | AD15: 02_Template_EN/01_GV_Govern/GV.RR_Roles-Responsibilities-and-Authorities/GV-STD-001_Human-Resources-Security-Standard.docx | AE15: Not started
A16: GV-FRM-002 | B16: Confidentiality and Non-Disclosure Agreement | C16: สัญญาการรักษาความลับ | D16: Govern (GV) | E16: Roles, Responsibilities, and Authorities (GV.RR) | F16: T4 | G16: Form | H16: People | I16: Essential | J16: Expected | K16: All | L16: ISO/IEC 27001:2022 Annex A 6.6 | M16: Expected | N16: GV.RR-04, GV.SC-05 | O16: A.6.6 | P16: PS-6 | Q16: Legal Counsel | R16: Legal Counsel | S16: Annual | T16: GV-STD-001 | V16: People, Evidence, Legal and Regulatory | W16: 52 | X16: W2 Direct | Y16: Track A | Z16: Specialist-guided | AA16: Legal counsel | AC16: GV-STD-001 | AD16: 02_Template_EN/01_GV_Govern/GV.RR_Roles-Responsibilities-and-Authorities/GV-FRM-002_Confidentiality-and-Non-Disclosure-Agreement.docx | AE16: Not started
A17: GV-FRM-003 | B17: Employee Offboarding Security Checklist | C17: แบบตรวจสอบด้านความมั่นคงปลอดภัยเมื่อพนักงานพ้นสภาพหรือย้ายงาน | D17: Govern (GV) | E17: Roles, Responsibilities, and Authorities (GV.RR) | F17: T4 | G17: Form | H17: People | I17: Essential | J17: Expected | K17: All | L17: ISO/IEC 27001:2022 Annex A 5.11 and 6.5 | M17: Expected | N17: GV.RR-04, PR.AA-05, ID.AM-08 | O17: A.5.11, A.6.5 | P17: PS-4, PS-5 | Q17: Human Resources Director | R17: Human Resources Director | S17: Annual | T17: GV-STD-001 | V17: People, Evidence | W17: 53 | X17: W2 Direct | Y17: Track A | Z17: IT-ready | AA17: Human Resources / In-house IT | AC17: GV-STD-001 | AD17: 02_Template_EN/01_GV_Govern/GV.RR_Roles-Responsibilities-and-Authorities/GV-FRM-003_Employee-Offboarding-Security-Checklist.docx | AE17: Not started
A18: GV-POL-001 | B18: Information Security Policy | C18: นโยบายความมั่นคงปลอดภัยสารสนเทศ | D18: Govern (GV) | E18: Policy (GV.PO) | F18: T1 | G18: Policy | H18: Organizational | I18: Essential | J18: Required | K18: ISO 27001 | L18: ISO/IEC 27001:2022 Clause 5.2 (documented information); PDPC Notification on Security Measures B.E. 2565 | M18: Expected | N18: GV.PO-01, GV.PO-02 | O18: 5.2, A.5.1 | P18: PM-1, PL-1 | Q18: Chief Information Security Officer (CISO) or Security Manager | R18: Chief Executive Officer (CEO) | S18: Annual | T18: GV-CHR-001 | U18: GV-POL-002, GV-STD-001, GV-PRC-002, GV-POL-003, GV-PRC-003, GV-POL-004, GV-POL-006, ID-STD-001, ID-STD-002, ID-PRC-006, PR-POL-001, PR-POL-002, PR-PLN-001, PR-POL-003, PR-STD-010, PR-PRC-006, PR-STD-011, PR-STD-012, PR-STD-013, PR-STD-015, PR-STD-016, DE-STD-001, RS-PLN-001 | V18: Governance | W18: 5 | X18: W0 Mandate and Mobilize | Y18: Track A | Z18: Specialist-guided | AA18: Cybersecurity consultant (project) / Security FTE | AB18: ACT-03 Legal and Regulatory Applicability Review; ACT-13 Policy Drafting and Stakeholder Review Cycle; ACT-14 Policy Approval and Communication | AC18: GV-CHR-001, GV-REG-001 | AD18: 02_Template_EN/01_GV_Govern/GV.PO_Policy/GV-POL-001_Information-Security-Policy.docx | AE18: Not started
A19: GV-PRC-002 | B19: Document Control Procedure | C19: ระเบียบปฏิบัติการควบคุมเอกสาร | D19: Govern (GV) | E19: Policy (GV.PO) | F19: T3 | G19: Procedure | H19: Organizational | I19: Essential | J19: Expected | K19: ISO 27001 | L19: ISO/IEC 27001:2022 Clause 7.5 (control of documented information; a procedure is not mandated) | M19: Expected | N19: GV.PO-02 | O19: 7.5, A.5.37 | P19: PL-1, PM-1 | Q19: Chief Information Security Officer (CISO) or Security Manager | R19: Chief Information Officer (CIO) | S19: Annual | T19: GV-POL-001 | V19: Process | W19: 6 | X19: W0 Mandate and Mobilize | Y19: Track A | Z19: IT-ready | AA19: In-house IT | AB19: ACT-14 Policy Approval and Communication | AC19: GV-POL-001 | AD19: 02_Template_EN/01_GV_Govern/GV.PO_Policy/GV-PRC-002_Document-Control-Procedure.docx | AE19: Not started
A20: GV-POL-003 | B20: Acceptable Use Policy | C20: นโยบายการใช้งานทรัพย์สินสารสนเทศที่ยอมรับได้ | D20: Govern (GV) | E20: Policy (GV.PO) | F20: T1 | G20: Policy | H20: Organizational | I20: Essential | J20: Expected | K20: All | L20: ISO/IEC 27001:2022 Annex A 5.10, 6.7, and 7.7 | M20: Expected | N20: GV.PO-01, PR.AT-01 | O20: A.5.10, A.6.7, A.7.7 | P20: PL-4 | Q20: Chief Information Security Officer (CISO) or Security Manager | R20: Chief Executive Officer (CEO) | S20: Annual | T20: GV-POL-001 | U20: GV-POL-005, PR-STD-009 | V20: People | W20: 45 | X20: W2 Direct | Y20: Track A | Z20: IT-ready | AA20: In-house IT / Human Resources | AB20: ACT-13 Policy Drafting and Stakeholder Review Cycle; ACT-14 Policy Approval and Communication | AC20: GV-POL-001 | AD20: 02_Template_EN/01_GV_Govern/GV.PO_Policy/GV-POL-003_Acceptable-Use-Policy.docx | AE20: Not started
A21: GV-POL-005 | B21: Generative AI Acceptable Use Policy | C21: นโยบายการใช้งาน Generative AI | D21: Govern (GV) | E21: Policy (GV.PO) | F21: T1 | G21: Policy | H21: Organizational | I21: Extended | J21: Optional | K21: All | L21: NIST AI RMF 1.0; NIST AI 600-1 (Generative AI Profile) | M21: Optional | N21: GV.PO-01, GV.OC-03, PR.DS-10 | O21: A.5.10 | P21: PL-4 | Q21: Chief Information Security Officer (CISO) or Security Manager | R21: Chief Executive Officer (CEO) | S21: Annual | T21: GV-POL-003 | V21: People, AI | W21: 135 | X21: W5 Optimize | Y21: Track A | Z21: Specialist-guided | AA21: Security FTE / Cybersecurity consultant (project) | AB21: ACT-13 Policy Drafting and Stakeholder Review Cycle; ACT-14 Policy Approval and Communication | AC21: GV-POL-003 | AD21: 02_Template_EN/01_GV_Govern/GV.PO_Policy/GV-POL-005_Generative-AI-Acceptable-Use-Policy.docx | AE21: Not started
A22: GV-PRC-003 | B22: Policy Exception Management Procedure | C22: ระเบียบปฏิบัติการขอยกเว้นการปฏิบัติตามนโยบาย | D22: Govern (GV) | E22: Policy (GV.PO) | F22: T3 | G22: Procedure | H22: Organizational | I22: Essential | J22: Expected | K22: All | L22: ISO/IEC 27001:2022 Annex A 5.36 | M22: Expected | N22: GV.PO-02, ID.RA-07 | O22: A.5.36 | P22: PL-1, RA-7 | Q22: Chief Information Security Officer (CISO) or Security Manager | R22: Chief Information Officer (CIO) | S22: Annual | T22: GV-POL-001 | U22: GV-FRM-004, GV-REG-004 | V22: Process | W22: 55 | X22: W2 Direct | Y22: Track A | Z22: IT-ready | AA22: In-house IT | AC22: GV-POL-001 | AD22: 02_Template_EN/01_GV_Govern/GV.PO_Policy/GV-PRC-003_Policy-Exception-Management-Procedure.docx | AE22: Not started
A23: GV-FRM-004 | B23: Policy Exception Request Form | C23: แบบฟอร์มขอยกเว้นการปฏิบัติตามนโยบาย | D23: Govern (GV) | E23: Policy (GV.PO) | F23: T4 | G23: Form | H23: Organizational | I23: Core | J23: Expected | K23: All | L23: ISO/IEC 27001:2022 Annex A 5.36 | M23: Expected | N23: ID.RA-07 | O23: A.5.36 | P23: RA-7 | Q23: Chief Information Security Officer (CISO) or Security Manager | R23: Chief Information Officer (CIO) | S23: Annual | T23: GV-PRC-003 | V23: Process, Evidence | W23: 56 | X23: W2 Direct | Y23: Track A | Z23: IT-ready | AA23: In-house IT | AC23: GV-PRC-003 | AD23: 02_Template_EN/01_GV_Govern/GV.PO_Policy/GV-FRM-004_Policy-Exception-Request-Form.docx | AE23: Not started
A24: GV-REG-004 | B24: Policy Exception Register | C24: ทะเบียนข้อยกเว้นการปฏิบัติตามนโยบาย | D24: Govern (GV) | E24: Policy (GV.PO) | F24: T4 | G24: Register | H24: Organizational | I24: Core | J24: Expected | K24: All | L24: ISO/IEC 27001:2022 Annex A 5.36 | M24: Expected | N24: ID.RA-07, GV.OV-02 | O24: A.5.36 | P24: RA-7, PM-4 | Q24: Chief Information Security Officer (CISO) or Security Manager | R24: Information Security Steering Committee (ISSC) | S24: Quarterly | T24: GV-PRC-003 | V24: Process, Evidence | W24: 57 | X24: W2 Direct | Y24: Track A | Z24: IT-ready | AA24: In-house IT | AC24: GV-PRC-003 | AD24: 02_Template_EN/01_GV_Govern/GV.PO_Policy/GV-REG-004_Policy-Exception-Register.docx | AE24: Not started
A25: GV-REG-005 | B25: Statement of Applicability (SoA) | C25: เอกสารแสดงการนำมาตรการควบคุมไปใช้ (SoA) | D25: Govern (GV) | E25: Policy (GV.PO) | F25: T4 | G25: Register | H25: Organizational | I25: Extended | J25: Required | K25: ISO 27001 | L25: ISO/IEC 27001:2022 Clause 6.1.3(d) | M25: Expected | N25: GV.PO-01, GV.RM-06 | O25: 6.1.3 | P25: PL-2 | Q25: Chief Information Security Officer (CISO) or Security Manager | R25: Information Security Steering Committee (ISSC) | S25: Annual | T25: GV-PRC-001 | V25: Governance, Evidence | W25: 42 | X25: W2 Direct | Y25: Track A | Z25: Specialist-required | AA25: Cybersecurity consultant (project) / Security FTE | AB25: ACT-11 Current State Assessment and CSF Profile Gap Analysis | AC25: ID-PLN-001, GV-RPT-001 | AD25: 02_Template_EN/01_GV_Govern/GV.PO_Policy/GV-REG-005_Statement-of-Applicability-SoA.docx | AE25: Not started
A26: GV-REG-006 | B26: CII Code of Practice Compliance Matrix | C26: ตารางการปฏิบัติตามประมวลแนวทางปฏิบัติสำหรับหน่วยงานโครงสร้างพื้นฐานสำคัญทางสารสนเทศ (CII) | D26: Govern (GV) | E26: Policy (GV.PO) | F26: T4 | G26: Register | H26: Organizational | I26: Extended | J26: Required | K26: CII | L26: CSA s.44; NCSC Notification on Code of Practice and Standard Framework B.E. 2564; CRC Notification on CII duties 2024 [VERIFY] | M26: Required | N26: GV.OC-03, GV.PO-01 | O26: A.5.31 | P26: PM-1 | Q26: Chief Information Security Officer (CISO) or Security Manager | R26: Information Security Steering Committee (ISSC) | S26: Annual | T26: GV-REG-001 | V26: Governance, Legal and Regulatory, Evidence | W26: 43 | X26: W2 Direct | Y26: Track A | Z26: Specialist-required | AA26: Cybersecurity consultant (project) / Legal counsel | AB26: ACT-03 Legal and Regulatory Applicability Review; ACT-11 Current State Assessment and CSF Profile Gap Analysis | AC26: GV-REG-001 | AD26: 02_Template_EN/01_GV_Govern/GV.PO_Policy/GV-REG-006_CII-Code-of-Practice-Compliance-Matrix.docx | AE26: Not started
A27: GV-POL-004 | B27: Personal Data Protection Policy | C27: นโยบายการคุ้มครองข้อมูลส่วนบุคคล | D27: Govern (GV) | E27: Policy (GV.PO) | F27: T1 | G27: Policy | H27: Organizational | I27: Essential | J27: Expected | K27: PDPA | L27: PDPA s.37(1); PDPC Notification on Security Measures B.E. 2565 | M27: Expected | N27: GV.OC-03, GV.PO-01 | O27: A.5.34 | P27: PT-1 | Q27: Data Protection Officer (DPO) | R27: Chief Executive Officer (CEO) | S27: Annual | T27: GV-POL-001 | U27: GV-REG-007, GV-TPL-002, GV-PRC-004, GV-PRC-005, GV-TPL-004, RS-PLB-003 | V27: Governance, Legal and Regulatory, Privacy | W27: 24 | X27: W1 Understand | Y27: Track A | Z27: Specialist-guided | AA27: DPO or privacy counsel service / Legal counsel | AB27: ACT-03 Legal and Regulatory Applicability Review; ACT-13 Policy Drafting and Stakeholder Review Cycle; ACT-14 Policy Approval and Communication | AC27: GV-REG-001, GV-POL-001 | AD27: 02_Template_EN/01_GV_Govern/GV.PO_Policy/GV-POL-004_Personal-Data-Protection-Policy.docx | AE27: Not started
A28: GV-REG-007 | B28: Record of Processing Activities (ROPA) | C28: บันทึกรายการกิจกรรมการประมวลผลข้อมูลส่วนบุคคล (ROPA) | D28: Govern (GV) | E28: Policy (GV.PO) | F28: T4 | G28: Register | H28: Organizational | I28: Essential | J28: Required | K28: PDPA | L28: PDPA s.39 (controller) and s.40 (processor) | M28: Required | N28: GV.OC-03, ID.AM-07 | O28: A.5.34 | P28: PT-2, PT-3 | Q28: Data Protection Officer (DPO) | R28: Data Protection Officer (DPO) | S28: Annual and on change | T28: GV-POL-004 | V28: Process, Legal and Regulatory, Privacy, Evidence | W28: 25 | X28: W1 Understand | Y28: Track A | Z28: Specialist-guided | AA28: DPO or privacy counsel service | AB28: ACT-06 Data Mapping Interviews | AC28: ID-REG-003 | AD28: 02_Template_EN/01_GV_Govern/GV.PO_Policy/GV-REG-007_Record-of-Processing-Activities-ROPA.docx | AE28: Not started
A29: GV-TPL-002 | B29: Privacy Notice Template | C29: แม่แบบประกาศความเป็นส่วนตัว | D29: Govern (GV) | E29: Policy (GV.PO) | F29: T4 | G29: Template | H29: Organizational | I29: Essential | J29: Required | K29: PDPA | L29: PDPA s.23 | M29: Required | N29: GV.OC-03 | O29: A.5.34 | P29: PT-5 | Q29: Data Protection Officer (DPO) | R29: Legal Counsel | S29: Annual | T29: GV-POL-004 | V29: Process, Legal and Regulatory, Privacy, Evidence | W29: 26 | X29: W1 Understand | Y29: Track A | Z29: Specialist-guided | AA29: DPO or privacy counsel service / Legal counsel | AB29: ACT-06 Data Mapping Interviews | AC29: GV-REG-007 | AD29: 02_Template_EN/01_GV_Govern/GV.PO_Policy/GV-TPL-002_Privacy-Notice-Template.docx | AE29: Not started
A30: GV-PRC-004 | B30: Data Protection Impact Assessment (DPIA) Procedure | C30: ระเบียบปฏิบัติการประเมินผลกระทบด้านการคุ้มครองข้อมูลส่วนบุคคล (DPIA) | D30: Govern (GV) | E30: Policy (GV.PO) | F30: T3 | G30: Procedure | H30: Organizational | I30: Core | J30: Expected | K30: PDPA | L30: Not explicitly mandated by the PDPA; supports the risk-based measures in PDPA s.37(1) [VERIFY current PDPC guidance] | M30: Expected | N30: GV.OC-03, ID.RA-04 | O30: A.5.34 | P30: RA-8 | Q30: Data Protection Officer (DPO) | R30: Information Security Steering Committee (ISSC) | S30: Annual | T30: GV-POL-004 | U30: GV-TPL-003 | V30: Process, Legal and Regulatory, Privacy | W30: 61 | X30: W2 Direct | Y30: Track A | Z30: Specialist-guided | AA30: DPO or privacy counsel service | AB30: ACT-13 Policy Drafting and Stakeholder Review Cycle | AC30: GV-POL-004 | AD30: 02_Template_EN/01_GV_Govern/GV.PO_Policy/GV-PRC-004_Data-Protection-Impact-Assessment-DPIA-Procedure.docx | AE30: Not started
A31: GV-TPL-003 | B31: DPIA Template | C31: แม่แบบการประเมินผลกระทบด้านการคุ้มครองข้อมูลส่วนบุคคล (DPIA) | D31: Govern (GV) | E31: Policy (GV.PO) | F31: T4 | G31: Template | H31: Organizational | I31: Core | J31: Expected | K31: PDPA | L31: Supports PDPA s.37(1) | M31: Expected | N31: ID.RA-04 | O31: A.5.34 | P31: RA-8 | Q31: Data Protection Officer (DPO) | R31: Data Protection Officer (DPO) | S31: Annual | T31: GV-PRC-004 | V31: Process, Legal and Regulatory, Privacy, Evidence | W31: 62 | X31: W2 Direct | Y31: Track A | Z31: Specialist-guided | AA31: DPO or privacy counsel service | AB31: ACT-27 Data Protection Impact Assessment (DPIA) Workshop | AC31: GV-PRC-004 | AD31: 02_Template_EN/01_GV_Govern/GV.PO_Policy/GV-TPL-003_DPIA-Template.docx | AE31: Not started
A32: GV-PRC-005 | B32: Data Subject Rights Request Procedure | C32: ระเบียบปฏิบัติการจัดการคำขอใช้สิทธิของเจ้าของข้อมูลส่วนบุคคล | D32: Govern (GV) | E32: Policy (GV.PO) | F32: T3 | G32: Procedure | H32: Organizational | I32: Essential | J32: Expected | K32: PDPA | L32: PDPA s.30 to s.36 (data subject rights; 30-day response under s.30) | M32: Expected | N32: GV.OC-03 | O32: A.5.34 | P32: PT-1 | Q32: Data Protection Officer (DPO) | R32: Information Security Steering Committee (ISSC) | S32: Annual | T32: GV-POL-004 | U32: GV-FRM-005 | V32: Process, Legal and Regulatory, Privacy | W32: 59 | X32: W2 Direct | Y32: Track A | Z32: Specialist-guided | AA32: DPO or privacy counsel service | AB32: ACT-13 Policy Drafting and Stakeholder Review Cycle | AC32: GV-POL-004 | AD32: 02_Template_EN/01_GV_Govern/GV.PO_Policy/GV-PRC-005_Data-Subject-Rights-Request-Procedure.docx | AE32: Not started
A33: GV-FRM-005 | B33: Data Subject Request Form | C33: แบบคำขอใช้สิทธิของเจ้าของข้อมูลส่วนบุคคล | D33: Govern (GV) | E33: Policy (GV.PO) | F33: T4 | G33: Form | H33: Organizational | I33: Core | J33: Expected | K33: PDPA | L33: PDPA s.30 to s.36 | M33: Expected | N33: GV.OC-03 | O33: A.5.34 | P33: PT-1 | Q33: Data Protection Officer (DPO) | R33: Data Protection Officer (DPO) | S33: Annual | T33: GV-PRC-005 | V33: Process, Legal and Regulatory, Privacy, Evidence | W33: 60 | X33: W2 Direct | Y33: Track A | Z33: IT-ready | AA33: In-house IT | AC33: GV-PRC-005 | AD33: 02_Template_EN/01_GV_Govern/GV.PO_Policy/GV-FRM-005_Data-Subject-Request-Form.docx | AE33: Not started
A34: GV-TPL-004 | B34: Data Processing Agreement Template | C34: แม่แบบข้อตกลงการประมวลผลข้อมูลส่วนบุคคล (DPA) | D34: Govern (GV) | E34: Policy (GV.PO) | F34: T4 | G34: Template | H34: Organizational | I34: Essential | J34: Required | K34: PDPA | L34: PDPA s.40; PDPC Notification on Security Measures B.E. 2565 (processor agreement) | M34: Required | N34: GV.SC-05, GV.OC-03 | O34: A.5.20, A.5.34 | P34: SA-9, PT-1 | Q34: Data Protection Officer (DPO) | R34: Legal Counsel | S34: Annual | T34: GV-POL-004, GV-STD-002 | V34: Process, Legal and Regulatory, Privacy, Evidence, Third Party | W34: 58 | X34: W2 Direct | Y34: Track A | Z34: Specialist-guided | AA34: Legal counsel / DPO or privacy counsel service | AC34: GV-POL-004 | AD34: 02_Template_EN/01_GV_Govern/GV.PO_Policy/GV-TPL-004_Data-Processing-Agreement-Template.docx | AE34: Not started
A35: GV-PRC-006 | B35: Management Review Procedure | C35: ระเบียบปฏิบัติการทบทวนโดยฝ่ายบริหาร | D35: Govern (GV) | E35: Oversight (GV.OV) | F35: T3 | G35: Procedure | H35: Organizational | I35: Core | J35: Expected | K35: ISO 27001 | L35: ISO/IEC 27001:2022 Clause 9.3 | M35: Expected | N35: GV.OV-01, GV.OV-02, GV.OV-03 | O35: 9.3 | P35: PM-6, PM-9 | Q35: Chief Information Security Officer (CISO) or Security Manager | R35: Information Security Steering Committee (ISSC) | S35: Annual | T35: GV-CHR-002 | U35: GV-REC-001 | V35: Governance | W35: 122 | X35: W4 Operate and Prove | Y35: Track A | Z35: Specialist-guided | AA35: Security FTE / Cybersecurity consultant (project) | AB35: ACT-24 Management Review Meeting | AC35: GV-CHR-002 | AD35: 02_Template_EN/01_GV_Govern/GV.OV_Oversight/GV-PRC-006_Management-Review-Procedure.docx | AE35: Not started
A36: GV-REC-001 | B36: Management Review Minutes | C36: บันทึกการประชุมทบทวนโดยฝ่ายบริหาร | D36: Govern (GV) | E36: Oversight (GV.OV) | F36: T4 | G36: Record | H36: Organizational | I36: Core | J36: Required | K36: ISO 27001 | L36: ISO/IEC 27001:2022 Clause 9.3.3 (results of management reviews) | M36: Expected | N36: GV.OV-01, GV.OV-02 | O36: 9.3 | P36: PM-9 | Q36: Chief Information Security Officer (CISO) or Security Manager | R36: Information Security Steering Committee (ISSC) | S36: Each meeting | T36: GV-PRC-006 | V36: Governance, Evidence | W36: 123 | X36: W4 Operate and Prove | Y36: Track A | Z36: IT-ready | AA36: In-house IT | AB36: ACT-24 Management Review Meeting | AC36: GV-PRC-006 | AD36: 02_Template_EN/01_GV_Govern/GV.OV_Oversight/GV-REC-001_Management-Review-Minutes.docx | AE36: Not started
A37: GV-REG-008 | B37: Cybersecurity Metrics Catalog (KPI and KRI) | C37: บัญชีตัวชี้วัดผลการดำเนินงานและตัวชี้วัดความเสี่ยงด้านไซเบอร์ (KPI และ KRI) | D37: Govern (GV) | E37: Oversight (GV.OV) | F37: T4 | G37: Register | H37: Organizational | I37: Core | J37: Required | K37: ISO 27001 | L37: ISO/IEC 27001:2022 Clause 9.1 (documented evidence of monitoring and measurement results; the catalog records definitions and results) | M37: Expected | N37: GV.OV-03, ID.IM-01 | O37: 9.1 | P37: PM-6, CA-7 | Q37: Chief Information Security Officer (CISO) or Security Manager | R37: Information Security Steering Committee (ISSC) | S37: Annual | T37: GV-STR-001 | U37: GV-TPL-005 | V37: Governance, Evidence | W37: 44 | X37: W2 Direct | Y37: Track A | Z37: Specialist-guided | AA37: Security FTE / Cybersecurity consultant (project) | AB37: ACT-12 Strategy, Roadmap, and Budget Planning Session | AC37: GV-STR-001 | AD37: 02_Template_EN/01_GV_Govern/GV.OV_Oversight/GV-REG-008_Cybersecurity-Metrics-Catalog-KPI-and-KRI.docx | AE37: Not started
A38: GV-TPL-005 | B38: Board Cybersecurity Report Template | C38: แม่แบบรายงานด้านความมั่นคงปลอดภัยไซเบอร์ต่อคณะกรรมการ | D38: Govern (GV) | E38: Oversight (GV.OV) | F38: T4 | G38: Template | H38: Organizational | I38: Core | J38: Expected | K38: All | L38: Common practice; NIST IR 8286 series | M38: Expected | N38: GV.OV-01, GV.OV-03 | O38: 9.1, 9.3 | P38: PM-6 | Q38: Chief Information Security Officer (CISO) or Security Manager | R38: Chief Executive Officer (CEO) | S38: Annual | T38: GV-REG-008 | V38: Governance, Evidence | W38: 98 | X38: W3 Standardize | Y38: Track A | Z38: Specialist-guided | AA38: Security FTE / Cybersecurity consultant (project) | AC38: GV-REG-008 | AD38: 02_Template_EN/01_GV_Govern/GV.OV_Oversight/GV-TPL-005_Board-Cybersecurity-Report-Template.docx | AE38: Not started
A39: GV-PRC-007 | B39: Internal Audit Procedure | C39: ระเบียบปฏิบัติการตรวจสอบภายในด้านความมั่นคงปลอดภัยสารสนเทศ | D39: Govern (GV) | E39: Oversight (GV.OV) | F39: T3 | G39: Procedure | H39: Organizational | I39: Core | J39: Expected | K39: ISO 27001, CII | L39: ISO/IEC 27001:2022 Clause 9.2; CSA s.54 | M39: Expected | N39: GV.OV-02, ID.IM-01 | O39: 9.2, A.5.35 | P39: CA-2, CA-7 | Q39: Head of Internal Audit | R39: Audit Committee | S39: Annual | T39: GV-CHR-001 | U39: GV-PLN-002, GV-TPL-006 | V39: Governance, Legal and Regulatory | W39: 124 | X39: W4 Operate and Prove | Y39: Track A | Z39: Specialist-required | AA39: Co-sourced internal audit | AB39: ACT-25 Internal Audit Planning and Fieldwork | AC39: GV-CHR-001 | AD39: 02_Template_EN/01_GV_Govern/GV.OV_Oversight/GV-PRC-007_Internal-Audit-Procedure.docx | AE39: Not started
A40: GV-PLN-002 | B40: Internal Audit Program | C40: แผนการตรวจสอบภายในประจำปี | D40: Govern (GV) | E40: Oversight (GV.OV) | F40: T3 | G40: Plan | H40: Organizational | I40: Core | J40: Required | K40: ISO 27001, CII | L40: ISO/IEC 27001:2022 Clause 9.2.2 (audit program); CSA s.54 (annual audit) | M40: Required | N40: GV.OV-02 | O40: 9.2 | P40: CA-2 | Q40: Head of Internal Audit | R40: Audit Committee | S40: Annual | T40: GV-PRC-007 | V40: Governance, Legal and Regulatory | W40: 125 | X40: W4 Operate and Prove | Y40: Track A | Z40: Specialist-required | AA40: Co-sourced internal audit | AB40: ACT-25 Internal Audit Planning and Fieldwork | AC40: GV-PRC-007 | AD40: 02_Template_EN/01_GV_Govern/GV.OV_Oversight/GV-PLN-002_Internal-Audit-Program.docx | AE40: Not started
A41: GV-TPL-006 | B41: Internal Audit Report Template | C41: แม่แบบรายงานผลการตรวจสอบภายใน | D41: Govern (GV) | E41: Oversight (GV.OV) | F41: T4 | G41: Template | H41: Organizational | I41: Core | J41: Required | K41: ISO 27001, CII | L41: ISO/IEC 27001:2022 Clause 9.2.2 (audit results); CSA s.54 (summary report to NCSA within 30 days) | M41: Required | N41: GV.OV-02, ID.IM-01 | O41: 9.2 | P41: CA-2 | Q41: Head of Internal Audit | R41: Audit Committee | S41: Annual | T41: GV-PRC-007 | V41: Governance, Legal and Regulatory, Evidence | W41: 126 | X41: W4 Operate and Prove | Y41: Track A | Z41: Specialist-guided | AA41: Co-sourced internal audit | AC41: GV-PRC-007 | AD41: 02_Template_EN/01_GV_Govern/GV.OV_Oversight/GV-TPL-006_Internal-Audit-Report-Template.docx | AE41: Not started
A42: GV-POL-006 | B42: Third-Party and Supply Chain Security Policy | C42: นโยบายความมั่นคงปลอดภัยด้านผู้ให้บริการภายนอกและห่วงโซ่อุปทาน | D42: Govern (GV) | E42: Cybersecurity Supply Chain Risk Management (GV.SC) | F42: T1 | G42: Policy | H42: Organizational | I42: Essential | J42: Expected | K42: All | L42: ISO/IEC 27001:2022 Annex A 5.19; NIST SP 800-161 Rev. 1 | M42: Expected | N42: GV.SC-01, GV.SC-02, GV.SC-03 | O42: A.5.19, A.5.21 | P42: SR-1, SA-9 | Q42: Chief Information Security Officer (CISO) or Security Manager | R42: Chief Executive Officer (CEO) | S42: Annual | T42: GV-POL-001 | U42: GV-PRC-008, GV-STD-002, GV-STD-003, PR-STD-014 | V42: Process, Third Party | W42: 48 | X42: W2 Direct | Y42: Track A | Z42: Specialist-guided | AA42: Security FTE / Cybersecurity consultant (project) | AB42: ACT-13 Policy Drafting and Stakeholder Review Cycle; ACT-14 Policy Approval and Communication | AC42: GV-POL-001, GV-REG-009 | AD42: 02_Template_EN/01_GV_Govern/GV.SC_Cybersecurity-Supply-Chain-Risk-Management/GV-POL-006_Third-Party-and-Supply-Chain-Security-Policy.docx | AE42: Not started
A43: GV-PRC-008 | B43: Third-Party Risk Management Procedure | C43: ระเบียบปฏิบัติการบริหารความเสี่ยงผู้ให้บริการภายนอก | D43: Govern (GV) | E43: Cybersecurity Supply Chain Risk Management (GV.SC) | F43: T3 | G43: Procedure | H43: Organizational | I43: Core | J43: Expected | K43: All | L43: ISO/IEC 27001:2022 Annex A 5.19 and 5.22; NIST SP 800-161 Rev. 1 | M43: Expected | N43: GV.SC-04, GV.SC-06, GV.SC-07, GV.SC-10, ID.RA-10 | O43: A.5.19, A.5.22 | P43: SR-2, SR-6, SA-9 | Q43: Chief Information Security Officer (CISO) or Security Manager | R43: Chief Information Officer (CIO) | S43: Annual | T43: GV-POL-006 | U43: GV-REG-009, GV-FRM-006, GV-FRM-007 | V43: Process, Third Party | W43: 94 | X43: W3 Standardize | Y43: Track A | Z43: Specialist-guided | AA43: Security FTE / Cybersecurity consultant (project) | AB43: ACT-16 Supplier Tiering Workshop | AC43: GV-POL-006 | AD43: 02_Template_EN/01_GV_Govern/GV.SC_Cybersecurity-Supply-Chain-Risk-Management/GV-PRC-008_Third-Party-Risk-Management-Procedure.docx | AE43: Not started
A44: GV-REG-009 | B44: Supplier Inventory and Criticality Register | C44: ทะเบียนผู้ให้บริการและระดับความสำคัญ | D44: Govern (GV) | E44: Cybersecurity Supply Chain Risk Management (GV.SC) | F44: T4 | G44: Register | H44: Organizational | I44: Essential | J44: Expected | K44: All | L44: ISO/IEC 27001:2022 Annex A 5.19 | M44: Expected | N44: GV.SC-04, ID.AM-04 | O44: A.5.19 | P44: SR-6, PM-30 | Q44: Procurement Manager | R44: Chief Information Security Officer (CISO) or Security Manager | S44: Semi-annual | T44: GV-PRC-008 | V44: Process, Third Party, Evidence | W44: 27 | X44: W1 Understand | Y44: Track A | Z44: IT-ready | AA44: In-house IT | AB44: ACT-16 Supplier Tiering Workshop | AD44: 02_Template_EN/01_GV_Govern/GV.SC_Cybersecurity-Supply-Chain-Risk-Management/GV-REG-009_Supplier-Inventory-and-Criticality-Register.docx | AE44: Not started
A45: GV-FRM-006 | B45: Vendor Security Assessment Questionnaire | C45: แบบสอบถามประเมินความมั่นคงปลอดภัยของผู้ให้บริการ | D45: Govern (GV) | E45: Cybersecurity Supply Chain Risk Management (GV.SC) | F45: T4 | G45: Form | H45: Organizational | I45: Core | J45: Expected | K45: All | L45: ISO/IEC 27001:2022 Annex A 5.19 and 5.21 | M45: Expected | N45: GV.SC-06, GV.SC-07, ID.RA-10 | O45: A.5.19, A.5.21 | P45: SR-6, SA-9 | Q45: Chief Information Security Officer (CISO) or Security Manager | R45: Chief Information Security Officer (CISO) or Security Manager | S45: Annual | T45: GV-PRC-008 | V45: Process, Third Party, Evidence | W45: 96 | X45: W3 Standardize | Y45: Track A | Z45: Specialist-guided | AA45: Security FTE / Cybersecurity consultant (project) | AB45: ACT-16 Supplier Tiering Workshop | AC45: GV-PRC-008 | AD45: 02_Template_EN/01_GV_Govern/GV.SC_Cybersecurity-Supply-Chain-Risk-Management/GV-FRM-006_Vendor-Security-Assessment-Questionnaire.docx | AE45: Not started
A46: GV-STD-002 | B46: Supplier Security Requirements Standard | C46: มาตรฐานข้อกำหนดความมั่นคงปลอดภัยในสัญญาผู้ให้บริการ | D46: Govern (GV) | E46: Cybersecurity Supply Chain Risk Management (GV.SC) | F46: T2 | G46: Standard | H46: Organizational | I46: Core | J46: Expected | K46: All | L46: ISO/IEC 27001:2022 Annex A 5.20; PDPA s.40 | M46: Expected | N46: GV.SC-05, GV.SC-08 | O46: A.5.20, A.5.21 | P46: SA-4, SA-9, SR-5 | Q46: Chief Information Security Officer (CISO) or Security Manager | R46: Chief Information Officer (CIO) | S46: Annual | T46: GV-POL-006 | U46: GV-TPL-004, DE-GDL-001 | V46: Process, Third Party | W46: 95 | X46: W3 Standardize | Y46: Track A | Z46: Specialist-guided | AA46: Security FTE / Legal counsel | AB46: ACT-16 Supplier Tiering Workshop | AC46: GV-POL-006 | AD46: 02_Template_EN/01_GV_Govern/GV.SC_Cybersecurity-Supply-Chain-Risk-Management/GV-STD-002_Supplier-Security-Requirements-Standard.docx | AE46: Not started
A47: GV-STD-003 | B47: Secure Acquisition Standard | C47: มาตรฐานการจัดหาระบบและผลิตภัณฑ์อย่างมั่นคงปลอดภัย | D47: Govern (GV) | E47: Cybersecurity Supply Chain Risk Management (GV.SC) | F47: T2 | G47: Standard | H47: Organizational | I47: Extended | J47: Expected | K47: All | L47: ISO/IEC 27001:2022 Annex A 5.21 and 5.23; NIST SP 800-161 Rev. 1 | M47: Expected | N47: GV.SC-09, ID.RA-09, ID.RA-10 | O47: A.5.21, A.5.23 | P47: SA-4, SR-3, SR-11 | Q47: Chief Information Security Officer (CISO) or Security Manager | R47: Chief Information Officer (CIO) | S47: Annual | T47: GV-POL-006 | V47: Technology, Third Party, Cloud | W47: 97 | X47: W3 Standardize | Y47: Track A | Z47: Specialist-guided | AA47: Security FTE / Cybersecurity consultant (project) | AC47: GV-POL-006 | AD47: 02_Template_EN/01_GV_Govern/GV.SC_Cybersecurity-Supply-Chain-Risk-Management/GV-STD-003_Secure-Acquisition-Standard.docx | AE47: Not started
A48: GV-FRM-007 | B48: Supplier Offboarding Checklist | C48: แบบตรวจสอบการยุติความสัมพันธ์กับผู้ให้บริการ | D48: Govern (GV) | E48: Cybersecurity Supply Chain Risk Management (GV.SC) | F48: T4 | G48: Form | H48: Organizational | I48: Core | J48: Expected | K48: All | L48: ISO/IEC 27001:2022 Annex A 5.20 | M48: Expected | N48: GV.SC-10 | O48: A.5.20 | P48: SA-9, PS-7 | Q48: Procurement Manager | R48: Chief Information Security Officer (CISO) or Security Manager | S48: Annual | T48: GV-PRC-008 | V48: Process, Third Party, Evidence | W48: 132 | X48: W4 Operate and Prove | Y48: Track A | Z48: IT-ready | AA48: In-house IT | AC48: GV-PRC-008 | AD48: 02_Template_EN/01_GV_Govern/GV.SC_Cybersecurity-Supply-Chain-Risk-Management/GV-FRM-007_Supplier-Offboarding-Checklist.docx | AE48: Not started
A49: ID-STD-001 | B49: Asset Management Standard | C49: มาตรฐานการบริหารจัดการทรัพย์สินสารสนเทศ | D49: Identify (ID) | E49: Asset Management (ID.AM) | F49: T2 | G49: Standard | H49: Organizational | I49: Essential | J49: Expected | K49: All | L49: ISO/IEC 27001:2022 Annex A 5.9 and 5.11; CIS Controls v8.1 Controls 1 and 2 | M49: Expected | N49: ID.AM-01, ID.AM-02, ID.AM-04, ID.AM-05, ID.AM-07, ID.AM-08 | O49: A.5.9, A.5.11 | P49: CM-8, PM-5 | Q49: IT Infrastructure Manager | R49: Chief Information Officer (CIO) | S49: Annual | T49: GV-POL-001 | U49: ID-PRC-001, ID-REG-001, ID-REG-002, ID-REG-003, ID-RPT-001, ID-REG-004 | V49: Technology | W49: 18 | X49: W1 Understand | Y49: Track A | Z49: IT-ready | AA49: In-house IT | AB49: ACT-13 Policy Drafting and Stakeholder Review Cycle | AC49: GV-POL-001 | AD49: 02_Template_EN/02_ID_Identify/ID.AM_Asset-Management/ID-STD-001_Asset-Management-Standard.docx | AE49: Not started
A50: ID-PRC-001 | B50: Asset Lifecycle Management Procedure | C50: ระเบียบปฏิบัติการบริหารวงจรชีวิตทรัพย์สิน | D50: Identify (ID) | E50: Asset Management (ID.AM) | F50: T3 | G50: Procedure | H50: Organizational | I50: Core | J50: Expected | K50: All | L50: ISO/IEC 27001:2022 Annex A 5.9, 7.13, and 7.14 | M50: Expected | N50: ID.AM-08, PR.PS-03 | O50: A.5.9, A.7.13, A.7.14 | P50: CM-8, MA-2, MP-6 | Q50: IT Infrastructure Manager | R50: Chief Information Officer (CIO) | S50: Annual | T50: ID-STD-001 | U50: ID-FRM-001 | V50: Process | W50: 63 | X50: W3 Standardize | Y50: Track A | Z50: IT-ready | AA50: In-house IT | AC50: ID-STD-001 | AD50: 02_Template_EN/02_ID_Identify/ID.AM_Asset-Management/ID-PRC-001_Asset-Lifecycle-Management-Procedure.docx | AE50: Not started
A51: ID-REG-001 | B51: Hardware Asset Inventory | C51: ทะเบียนทรัพย์สินฮาร์ดแวร์ | D51: Identify (ID) | E51: Asset Management (ID.AM) | F51: T4 | G51: Register | H51: Organizational | I51: Essential | J51: Expected | K51: All | L51: ISO/IEC 27001:2022 Annex A 5.9; CIS Controls v8.1 Control 1 | M51: Expected | N51: ID.AM-01, ID.AM-05 | O51: A.5.9 | P51: CM-8 | Q51: IT Infrastructure Manager | R51: Chief Information Officer (CIO) | S51: Continuous; reconcile quarterly | T51: ID-STD-001 | V51: Technology, Evidence | W51: 19 | X51: W1 Understand | Y51: Track A | Z51: IT-ready | AA51: In-house IT | AB51: ACT-05 Asset Discovery and Inventory Reconciliation | AD51: 02_Template_EN/02_ID_Identify/ID.AM_Asset-Management/ID-REG-001_Hardware-Asset-Inventory.docx | AE51: Not started
A52: ID-REG-002 | B52: Software and Service Inventory | C52: ทะเบียนซอฟต์แวร์และบริการ | D52: Identify (ID) | E52: Asset Management (ID.AM) | F52: T4 | G52: Register | H52: Organizational | I52: Essential | J52: Expected | K52: All | L52: ISO/IEC 27001:2022 Annex A 5.9; CIS Controls v8.1 Control 2 | M52: Expected | N52: ID.AM-02, ID.AM-04, ID.AM-05 | O52: A.5.9 | P52: CM-8, CM-10 | Q52: IT Infrastructure Manager | R52: Chief Information Officer (CIO) | S52: Continuous; reconcile quarterly | T52: ID-STD-001 | V52: Technology, Evidence | W52: 20 | X52: W1 Understand | Y52: Track A | Z52: IT-ready | AA52: In-house IT | AB52: ACT-05 Asset Discovery and Inventory Reconciliation | AD52: 02_Template_EN/02_ID_Identify/ID.AM_Asset-Management/ID-REG-002_Software-and-Service-Inventory.docx | AE52: Not started
A53: ID-REG-003 | B53: Data Inventory and Data Flow Register | C53: ทะเบียนข้อมูลและการไหลของข้อมูล | D53: Identify (ID) | E53: Asset Management (ID.AM) | F53: T4 | G53: Register | H53: Organizational | I53: Essential | J53: Expected | K53: PDPA | L53: ISO/IEC 27001:2022 Annex A 5.9 and 5.12; supports PDPA s.39 | M53: Expected | N53: ID.AM-03, ID.AM-07 | O53: A.5.9, A.5.12, A.5.14 | P53: PM-5(1), CM-12 | Q53: Data Protection Officer (DPO) | R53: Chief Information Security Officer (CISO) or Security Manager | S53: Annual | T53: ID-STD-001 | V53: Process, Legal and Regulatory, Privacy, Evidence | W53: 23 | X53: W1 Understand | Y53: Track A | Z53: Specialist-guided | AA53: DPO or privacy counsel service / In-house IT | AB53: ACT-06 Data Mapping Interviews | AC53: ID-REG-002 | AD53: 02_Template_EN/02_ID_Identify/ID.AM_Asset-Management/ID-REG-003_Data-Inventory-and-Data-Flow-Register.docx | AE53: Not started
A54: ID-RPT-001 | B54: Network Architecture and Data Flow Diagram | C54: แผนผังสถาปัตยกรรมเครือข่ายและการไหลของข้อมูล | D54: Identify (ID) | E54: Asset Management (ID.AM) | F54: T4 | G54: Report | H54: Technological | I54: Essential | J54: Expected | K54: All | L54: ISO/IEC 27001:2022 Annex A 8.20 and 8.22; CIS Controls v8.1 Control 12 | M54: Expected | N54: ID.AM-03, PR.IR-01 | O54: A.8.20, A.8.22 | P54: PL-8, CA-9 | Q54: IT Infrastructure Manager | R54: Chief Information Officer (CIO) | S54: Annual and on major change | T54: ID-STD-001 | V54: Technology, Evidence | W54: 21 | X54: W1 Understand | Y54: Track A | Z54: IT-ready | AA54: In-house IT | AB54: ACT-05 Asset Discovery and Inventory Reconciliation | AC54: ID-REG-001 | AD54: 02_Template_EN/02_ID_Identify/ID.AM_Asset-Management/ID-RPT-001_Network-Architecture-and-Data-Flow-Diagram.docx | AE54: Not started
A55: ID-REG-004 | B55: OT and Medical Device Inventory | C55: ทะเบียนอุปกรณ์เทคโนโลยีปฏิบัติการ (OT) และอุปกรณ์การแพทย์ | D55: Identify (ID) | E55: Asset Management (ID.AM) | F55: T4 | G55: Register | H55: Organizational | I55: Extended | J55: Optional | K55: All | L55: NIST SP 800-82 Rev. 3; IEC 80001-1 | M55: Optional | N55: ID.AM-01, ID.AM-02, ID.AM-05 | O55: A.5.9 | P55: CM-8 | Q55: Facilities Manager | R55: Chief Information Officer (CIO) | S55: Quarterly | T55: ID-STD-001 | V55: Technology, Evidence, OT and Medical Device | W55: 22 | X55: W1 Understand | Y55: Track A | Z55: IT-ready | AA55: In-house IT | AB55: ACT-05 Asset Discovery and Inventory Reconciliation | AC55: ID-REG-001 | AD55: 02_Template_EN/02_ID_Identify/ID.AM_Asset-Management/ID-REG-004_OT-and-Medical-Device-Inventory.docx | AE55: Not started
A56: ID-RPT-002 | B56: Business Impact Analysis (BIA) | C56: การวิเคราะห์ผลกระทบทางธุรกิจ (BIA) | D56: Identify (ID) | E56: Asset Management (ID.AM) | F56: T4 | G56: Report | H56: Organizational | I56: Essential | J56: Expected | K56: CII | L56: ISO 22301:2019 Clause 8.2.2; CRC Notification on CII duties 2024 (BCP criteria) [VERIFY] | M56: Expected (high priority for CII) | N56: ID.AM-05, GV.OC-04, GV.OC-05 | O56: A.5.29, A.5.30 | P56: CP-2(8), RA-9 | Q56: Business Continuity Management (BCM) Coordinator | R56: Information Security Steering Committee (ISSC) | S56: Annual | T56: RC-POL-001 | V56: Process, Legal and Regulatory, Evidence, Resilience | W56: 28 | X56: W1 Understand | Y56: Track A | Z56: Specialist-required | AA56: Cybersecurity consultant (project) | AB56: ACT-07 Business Impact Analysis (BIA) Interviews and Validation Workshop | AC56: ID-REG-001, ID-REG-002 | AD56: 02_Template_EN/02_ID_Identify/ID.AM_Asset-Management/ID-RPT-002_Business-Impact-Analysis-BIA.docx | AE56: Not started
A57: ID-FRM-001 | B57: Media Sanitization and Disposal Record | C57: บันทึกการทำลายข้อมูลและการจำหน่ายอุปกรณ์ | D57: Identify (ID) | E57: Asset Management (ID.AM) | F57: T4 | G57: Form | H57: Physical | I57: Core | J57: Expected | K57: PDPA | L57: ISO/IEC 27001:2022 Annex A 7.14 and 8.10; PDPA s.37(3); NIST SP 800-88 | M57: Expected | N57: ID.AM-08, PR.DS-01 | O57: A.7.10, A.7.14, A.8.10 | P57: MP-6 | Q57: IT Infrastructure Manager | R57: IT Infrastructure Manager | S57: Annual | T57: ID-PRC-001 | V57: Technology, Legal and Regulatory, Privacy, Evidence | W57: 64 | X57: W3 Standardize | Y57: Track A | Z57: IT-ready | AA57: In-house IT | AC57: ID-PRC-001 | AD57: 02_Template_EN/02_ID_Identify/ID.AM_Asset-Management/ID-FRM-001_Media-Sanitization-and-Disposal-Record.docx | AE57: Not started
A58: ID-REG-005 | B58: IT and Cybersecurity Risk Register | C58: ทะเบียนความเสี่ยงด้าน IT และความมั่นคงปลอดภัยไซเบอร์ | D58: Identify (ID) | E58: Risk Assessment (ID.RA) | F58: T4 | G58: Register | H58: Organizational | I58: Essential | J58: Required | K58: ISO 27001, CII | L58: ISO/IEC 27001:2022 Clause 8.2 (results of risk assessments); CSA s.54 | M58: Required | N58: ID.RA-03, ID.RA-04, ID.RA-05, ID.RA-06, GV.RM-06 | O58: 6.1.2, 8.2 | P58: RA-3, PM-28 | Q58: Chief Information Security Officer (CISO) or Security Manager | R58: Information Security Steering Committee (ISSC) | S58: Quarterly | T58: GV-PRC-001 | U58: ID-PLN-001 | V58: Process, Legal and Regulatory, Evidence | W58: 32 | X58: W1 Understand | Y58: Track A | Z58: Specialist-required | AA58: Cybersecurity consultant (project) / Security FTE | AB58: ACT-10 Risk Assessment Workshops | AC58: GV-PRC-001, ID-REG-001, ID-RPT-002 | AD58: 02_Template_EN/02_ID_Identify/ID.RA_Risk-Assessment/ID-REG-005_IT-and-Cybersecurity-Risk-Register.docx | AE58: Not started
A59: ID-PLN-001 | B59: Risk Treatment Plan | C59: แผนการจัดการความเสี่ยง | D59: Identify (ID) | E59: Risk Assessment (ID.RA) | F59: T3 | G59: Plan | H59: Organizational | I59: Core | J59: Required | K59: ISO 27001 | L59: ISO/IEC 27001:2022 Clause 6.1.3(e) and 8.3 | M59: Expected | N59: ID.RA-06 | O59: 6.1.3, 8.3 | P59: PM-4, CA-5 | Q59: Chief Information Security Officer (CISO) or Security Manager | R59: Information Security Steering Committee (ISSC) | S59: Quarterly | T59: ID-REG-005 | V59: Process | W59: 40 | X59: W2 Direct | Y59: Track A | Z59: Specialist-guided | AA59: Security FTE / Cybersecurity consultant (project) | AB59: ACT-10 Risk Assessment Workshops | AC59: ID-REG-005 | AD59: 02_Template_EN/02_ID_Identify/ID.RA_Risk-Assessment/ID-PLN-001_Risk-Treatment-Plan.docx | AE59: Not started
A60: ID-RPT-003 | B60: Cybersecurity Risk Assessment Report | C60: รายงานผลการประเมินความเสี่ยงด้านความมั่นคงปลอดภัยไซเบอร์ | D60: Identify (ID) | E60: Risk Assessment (ID.RA) | F60: T4 | G60: Report | H60: Organizational | I60: Core | J60: Required | K60: CII | L60: CSA s.54 (annual risk assessment; summary to NCSA within 30 days); CRC Notification on CII duties 2024 [VERIFY] | M60: Required | N60: ID.RA-04, ID.RA-05 | O60: 8.2 | P60: RA-3 | Q60: Chief Information Security Officer (CISO) or Security Manager | R60: Information Security Steering Committee (ISSC) | S60: Annual | T60: GV-PRC-001 | V60: Process, Legal and Regulatory, Evidence | W60: 33 | X60: W1 Understand | Y60: Track A | Z60: Specialist-required | AA60: Cybersecurity consultant (project) / Security FTE | AB60: ACT-10 Risk Assessment Workshops; ACT-11 Current State Assessment and CSF Profile Gap Analysis | AC60: ID-REG-005 | AD60: 02_Template_EN/02_ID_Identify/ID.RA_Risk-Assessment/ID-RPT-003_Cybersecurity-Risk-Assessment-Report.docx | AE60: Not started
A61: ID-STD-002 | B61: Vulnerability Scanning and Remediation Standard | C61: มาตรฐานการสแกนและแก้ไขช่องโหว่ | D61: Identify (ID) | E61: Risk Assessment (ID.RA) | F61: T2 | G61: Standard | H61: Technological | I61: Essential | J61: Expected | K61: All | L61: ISO/IEC 27001:2022 Annex A 8.8; CIS Controls v8.1 Control 7 | M61: Expected | N61: ID.RA-01, PR.PS-02 | O61: A.8.8 | P61: RA-5, SI-2 | Q61: Chief Information Security Officer (CISO) or Security Manager | R61: Chief Information Officer (CIO) | S61: Annual | T61: GV-POL-001 | U61: ID-PRC-002, ID-PRC-003, PR-PRC-007 | V61: Technology | W61: 65 | X61: W3 Standardize | Y61: Track A | Z61: Specialist-guided | AA61: Security FTE / Cybersecurity consultant (project) | AB61: ACT-26 Vulnerability Scanning and Penetration Test Scoping | AC61: GV-POL-001 | AD61: 02_Template_EN/02_ID_Identify/ID.RA_Risk-Assessment/ID-STD-002_Vulnerability-Scanning-and-Remediation-Standard.docx | AE61: Not started
A62: ID-PRC-002 | B62: Vulnerability Management Procedure | C62: ระเบียบปฏิบัติการบริหารจัดการช่องโหว่ | D62: Identify (ID) | E62: Risk Assessment (ID.RA) | F62: T3 | G62: Procedure | H62: Technological | I62: Core | J62: Expected | K62: All | L62: ISO/IEC 27001:2022 Annex A 8.8 | M62: Expected | N62: ID.RA-01, ID.RA-08, PR.PS-02 | O62: A.8.8 | P62: RA-5, SI-2 | Q62: Chief Information Security Officer (CISO) or Security Manager | R62: Chief Information Officer (CIO) | S62: Annual | T62: ID-STD-002 | U62: ID-REG-006, ID-PRC-005 | V62: Process | W62: 66 | X62: W3 Standardize | Y62: Track A | Z62: Specialist-guided | AA62: Security FTE / Managed Security Service Provider (MSSP) | AB62: ACT-26 Vulnerability Scanning and Penetration Test Scoping | AC62: ID-STD-002 | AD62: 02_Template_EN/02_ID_Identify/ID.RA_Risk-Assessment/ID-PRC-002_Vulnerability-Management-Procedure.docx | AE62: Not started
A63: ID-REG-006 | B63: Vulnerability Remediation Tracker | C63: ทะเบียนติดตามการแก้ไขช่องโหว่ | D63: Identify (ID) | E63: Risk Assessment (ID.RA) | F63: T4 | G63: Register | H63: Technological | I63: Core | J63: Expected | K63: All | L63: ISO/IEC 27001:2022 Annex A 8.8 | M63: Expected | N63: ID.RA-01, ID.RA-06 | O63: A.8.8 | P63: RA-5, PM-4 | Q63: Chief Information Security Officer (CISO) or Security Manager | R63: Chief Information Officer (CIO) | S63: Continuous; report monthly | T63: ID-PRC-002 | V63: Technology, Evidence | W63: 67 | X63: W3 Standardize | Y63: Track A | Z63: IT-ready | AA63: In-house IT | AC63: ID-PRC-002 | AD63: 02_Template_EN/02_ID_Identify/ID.RA_Risk-Assessment/ID-REG-006_Vulnerability-Remediation-Tracker.docx | AE63: Not started
A64: ID-PRC-003 | B64: Penetration Testing Procedure | C64: ระเบียบปฏิบัติการทดสอบเจาะระบบ | D64: Identify (ID) | E64: Risk Assessment (ID.RA) | F64: T3 | G64: Procedure | H64: Technological | I64: Core | J64: Expected | K64: All | L64: ISO/IEC 27001:2022 Annex A 8.8 and 8.29; CIS Controls v8.1 Control 18 | M64: Expected | N64: ID.RA-01, ID.IM-02 | O64: A.8.8, A.8.29 | P64: CA-8 | Q64: Chief Information Security Officer (CISO) or Security Manager | R64: Chief Information Officer (CIO) | S64: Annual | T64: ID-STD-002 | U64: ID-FRM-002 | V64: Technology | W64: 68 | X64: W3 Standardize | Y64: Track A | Z64: Specialist-required | AA64: Cybersecurity consultant (project) | AB64: ACT-26 Vulnerability Scanning and Penetration Test Scoping | AC64: ID-STD-002 | AD64: 02_Template_EN/02_ID_Identify/ID.RA_Risk-Assessment/ID-PRC-003_Penetration-Testing-Procedure.docx | AE64: Not started
A65: ID-FRM-002 | B65: Penetration Test Authorization and Rules of Engagement | C65: แบบอนุมัติและกติกาการทดสอบเจาะระบบ | D65: Identify (ID) | E65: Risk Assessment (ID.RA) | F65: T4 | G65: Form | H65: Technological | I65: Core | J65: Expected | K65: All | L65: Computer Crime Act B.E. 2550 s.5 and s.7 (written authorization separates testing from unauthorized access) | M65: Expected | N65: ID.RA-01 | O65: A.8.29 | P65: CA-8 | Q65: Chief Information Security Officer (CISO) or Security Manager | R65: Chief Information Officer (CIO) | S65: Annual | T65: ID-PRC-003 | V65: Process, Evidence, Legal and Regulatory | W65: 69 | X65: W3 Standardize | Y65: Track A | Z65: Specialist-required | AA65: Cybersecurity consultant (project) / Legal counsel | AB65: ACT-26 Vulnerability Scanning and Penetration Test Scoping | AC65: ID-PRC-003 | AD65: 02_Template_EN/02_ID_Identify/ID.RA_Risk-Assessment/ID-FRM-002_Penetration-Test-Authorization-and-Rules-of-Engagement.docx | AE65: Not started
A66: ID-PRC-004 | B66: Threat Intelligence Procedure | C66: ระเบียบปฏิบัติการบริหารข้อมูลข่าวกรองภัยคุกคาม | D66: Identify (ID) | E66: Risk Assessment (ID.RA) | F66: T3 | G66: Procedure | H66: Organizational | I66: Extended | J66: Expected | K66: ISO 27001 | L66: ISO/IEC 27001:2022 Annex A 5.7 | M66: Expected | N66: ID.RA-02, ID.RA-03 | O66: A.5.7, A.5.6 | P66: PM-16, RA-10 | Q66: Chief Information Security Officer (CISO) or Security Manager | R66: Chief Information Officer (CIO) | S66: Annual | T66: GV-PRC-001 | V66: Technology | W66: 139 | X66: W5 Optimize | Y66: Track A | Z66: Specialist-required | AA66: Managed Security Service Provider (MSSP) / Security FTE | AC66: GV-PRC-001 | AD66: 02_Template_EN/02_ID_Identify/ID.RA_Risk-Assessment/ID-PRC-004_Threat-Intelligence-Procedure.docx | AE66: Not started
A67: ID-PRC-005 | B67: Vulnerability Disclosure Handling Procedure | C67: ระเบียบปฏิบัติการรับแจ้งช่องโหว่จากภายนอก | D67: Identify (ID) | E67: Risk Assessment (ID.RA) | F67: T3 | G67: Procedure | H67: Technological | I67: Extended | J67: Optional | K67: All | L67: ISO/IEC 29147 and ISO/IEC 30111 | M67: Optional | N67: ID.RA-08 | O67: A.8.8 | P67: RA-5(11) | Q67: Chief Information Security Officer (CISO) or Security Manager | R67: Chief Information Officer (CIO) | S67: Annual | T67: ID-PRC-002 | V67: Process | W67: 140 | X67: W5 Optimize | Y67: Track A | Z67: Specialist-guided | AA67: Security FTE / Legal counsel | AC67: ID-PRC-002 | AD67: 02_Template_EN/02_ID_Identify/ID.RA_Risk-Assessment/ID-PRC-005_Vulnerability-Disclosure-Handling-Procedure.docx | AE67: Not started
A68: ID-PRC-006 | B68: Continual Improvement and Corrective Action Procedure | C68: ระเบียบปฏิบัติการปรับปรุงอย่างต่อเนื่องและการแก้ไขข้อบกพร่อง | D68: Identify (ID) | E68: Improvement (ID.IM) | F68: T3 | G68: Procedure | H68: Organizational | I68: Core | J68: Expected | K68: ISO 27001 | L68: ISO/IEC 27001:2022 Clause 10.1 and 10.2 | M68: Expected | N68: ID.IM-01, ID.IM-02, ID.IM-03, ID.IM-04 | O68: 10.1, 10.2 | P68: PM-4, CA-5 | Q68: Chief Information Security Officer (CISO) or Security Manager | R68: Information Security Steering Committee (ISSC) | S68: Annual | T68: GV-POL-001 | U68: ID-REG-007, ID-PLN-002, ID-TPL-001 | V68: Process | W68: 127 | X68: W4 Operate and Prove | Y68: Track A | Z68: IT-ready | AA68: In-house IT | AC68: GV-POL-001 | AD68: 02_Template_EN/02_ID_Identify/ID.IM_Improvement/ID-PRC-006_Continual-Improvement-and-Corrective-Action-Procedure.docx | AE68: Not started
A69: ID-REG-007 | B69: Corrective Action and Improvement Register | C69: ทะเบียนการแก้ไขข้อบกพร่องและการปรับปรุง | D69: Identify (ID) | E69: Improvement (ID.IM) | F69: T4 | G69: Register | H69: Organizational | I69: Core | J69: Required | K69: ISO 27001 | L69: ISO/IEC 27001:2022 Clause 10.2 (nature of nonconformities and results of corrective action) | M69: Expected | N69: ID.IM-01, ID.IM-02, ID.IM-03, ID.IM-04 | O69: 10.2 | P69: PM-4, CA-5 | Q69: Chief Information Security Officer (CISO) or Security Manager | R69: Information Security Steering Committee (ISSC) | S69: Continuous; review monthly | T69: ID-PRC-006 | V69: Process, Evidence | W69: 128 | X69: W4 Operate and Prove | Y69: Track A | Z69: IT-ready | AA69: In-house IT | AC69: ID-PRC-006 | AD69: 02_Template_EN/02_ID_Identify/ID.IM_Improvement/ID-REG-007_Corrective-Action-and-Improvement-Register.docx | AE69: Not started
A70: ID-PLN-002 | B70: Cybersecurity Exercise and Testing Program | C70: แผนการฝึกซ้อมและทดสอบด้านความมั่นคงปลอดภัยไซเบอร์ | D70: Identify (ID) | E70: Improvement (ID.IM) | F70: T3 | G70: Plan | H70: Organizational | I70: Core | J70: Expected | K70: CII | L70: CSA s.56 (readiness tests); CRC Notification on CII duties 2024 (annual BCP exercise) [VERIFY] | M70: Expected (high priority for CII) | N70: ID.IM-02, ID.IM-04 | O70: A.5.24, A.5.30 | P70: CP-4, IR-3 | Q70: Chief Information Security Officer (CISO) or Security Manager | R70: Information Security Steering Committee (ISSC) | S70: Annual | T70: ID-PRC-006 | U70: RC-REC-001 | V70: Process, Legal and Regulatory, Resilience | W70: 129 | X70: W4 Operate and Prove | Y70: Track A | Z70: Specialist-guided | AA70: Cybersecurity consultant (project) / Security FTE | AB70: ACT-20 Tabletop Exercise; ACT-21 Business Continuity and Disaster Recovery Exercise | AC70: RS-PLN-001, RC-PLN-001 | AD70: 02_Template_EN/02_ID_Identify/ID.IM_Improvement/ID-PLN-002_Cybersecurity-Exercise-and-Testing-Program.docx | AE70: Not started
A71: ID-TPL-001 | B71: Lessons Learned Report Template | C71: แม่แบบรายงานบทเรียนที่ได้รับ | D71: Identify (ID) | E71: Improvement (ID.IM) | F71: T4 | G71: Template | H71: Organizational | I71: Core | J71: Expected | K71: ISO 27001 | L71: ISO/IEC 27001:2022 Annex A 5.27 | M71: Expected | N71: ID.IM-03, ID.IM-04 | O71: A.5.27 | P71: IR-4, IR-8 | Q71: Chief Information Security Officer (CISO) or Security Manager | R71: Chief Information Officer (CIO) | S71: Annual | T71: ID-PRC-006 | V71: Process, Evidence | W71: 130 | X71: W4 Operate and Prove | Y71: Track A | Z71: Specialist-guided | AA71: Security FTE / Cybersecurity consultant (project) | AB71: ACT-29 Post-Incident and Lessons Learned Review | AC71: ID-PRC-006 | AD71: 02_Template_EN/02_ID_Identify/ID.IM_Improvement/ID-TPL-001_Lessons-Learned-Report-Template.docx | AE71: Not started
A72: PR-POL-001 | B72: Access Control Policy | C72: นโยบายการควบคุมการเข้าถึง | D72: Protect (PR) | E72: Identity Management, Authentication, and Access Control (PR.AA) | F72: T1 | G72: Policy | H72: Organizational | I72: Essential | J72: Expected | K72: PDPA | L72: ISO/IEC 27001:2022 Annex A 5.15; PDPC Notification on Security Measures B.E. 2565 (access control and audit trail) | M72: Expected | N72: PR.AA-01, PR.AA-02, PR.AA-03, PR.AA-04, PR.AA-05 | O72: A.5.15, A.5.18, A.8.3 | P72: AC-1, IA-1 | Q72: Chief Information Security Officer (CISO) or Security Manager | R72: Chief Executive Officer (CEO) | S72: Annual | T72: GV-POL-001 | U72: PR-STD-001, PR-STD-002, PR-STD-003, PR-PRC-001, PR-PRC-002 | V72: Technology, Legal and Regulatory, Privacy | W72: 46 | X72: W2 Direct | Y72: Track A | Z72: Specialist-guided | AA72: Security FTE / Cybersecurity consultant (project) | AB72: ACT-13 Policy Drafting and Stakeholder Review Cycle; ACT-14 Policy Approval and Communication | AC72: GV-POL-001 | AD72: 02_Template_EN/03_PR_Protect/PR.AA_Identity-Management-Authentication-and-Access-Control/PR-POL-001_Access-Control-Policy.docx | AE72: Not started
A73: PR-STD-001 | B73: Identity and Authentication Standard | C73: มาตรฐานการบริหารตัวตนและการยืนยันตัวตน | D73: Protect (PR) | E73: Identity Management, Authentication, and Access Control (PR.AA) | F73: T2 | G73: Standard | H73: Technological | I73: Essential | J73: Expected | K73: All | L73: ISO/IEC 27001:2022 Annex A 5.16, 5.17, and 8.5; NIST SP 800-63B-4 | M73: Expected | N73: PR.AA-01, PR.AA-02, PR.AA-03, PR.AA-04 | O73: A.5.16, A.5.17, A.8.5 | P73: IA-2, IA-5, IA-8 | Q73: Chief Information Security Officer (CISO) or Security Manager | R73: Chief Information Officer (CIO) | S73: Annual | T73: PR-POL-001 | V73: Technology | W73: 14 | X73: W0 Mandate and Mobilize | Y73: Track B | Z73: Specialist-guided | AA73: In-house IT / Cybersecurity consultant (project) | AB73: ACT-19 Identity and Privileged Access Review | AD73: 02_Template_EN/03_PR_Protect/PR.AA_Identity-Management-Authentication-and-Access-Control/PR-STD-001_Identity-and-Authentication-Standard.docx | AE73: Not started
A74: PR-STD-002 | B74: Privileged Access Management Standard | C74: มาตรฐานการบริหารจัดการสิทธิ์ระดับสูง | D74: Protect (PR) | E74: Identity Management, Authentication, and Access Control (PR.AA) | F74: T2 | G74: Standard | H74: Technological | I74: Essential | J74: Expected | K74: All | L74: ISO/IEC 27001:2022 Annex A 8.2 and 8.18 | M74: Expected | N74: PR.AA-05, PR.AA-01 | O74: A.8.2, A.8.18 | P74: AC-6, AC-2 | Q74: Chief Information Security Officer (CISO) or Security Manager | R74: Chief Information Officer (CIO) | S74: Annual | T74: PR-POL-001 | U74: PR-FRM-002, PR-REG-001 | V74: Technology | W74: 35 | X74: W1 Understand | Y74: Track B | Z74: Specialist-guided | AA74: In-house IT / Cybersecurity consultant (project) | AB74: ACT-19 Identity and Privileged Access Review | AC74: PR-STD-001 | AD74: 02_Template_EN/03_PR_Protect/PR.AA_Identity-Management-Authentication-and-Access-Control/PR-STD-002_Privileged-Access-Management-Standard.docx | AE74: Not started
A75: PR-STD-003 | B75: Remote Access Standard | C75: มาตรฐานการเข้าถึงระยะไกล | D75: Protect (PR) | E75: Identity Management, Authentication, and Access Control (PR.AA) | F75: T2 | G75: Standard | H75: Technological | I75: Essential | J75: Expected | K75: All | L75: ISO/IEC 27001:2022 Annex A 6.7 and 8.20 | M75: Expected | N75: PR.AA-03, PR.AA-05, PR.IR-01 | O75: A.6.7, A.8.20 | P75: AC-17 | Q75: Chief Information Security Officer (CISO) or Security Manager | R75: Chief Information Officer (CIO) | S75: Annual | T75: PR-POL-001 | U75: PR-FRM-003 | V75: Technology | W75: 36 | X75: W1 Understand | Y75: Track B | Z75: Specialist-guided | AA75: In-house IT / Cybersecurity consultant (project) | AB75: ACT-19 Identity and Privileged Access Review | AC75: PR-STD-001 | AD75: 02_Template_EN/03_PR_Protect/PR.AA_Identity-Management-Authentication-and-Access-Control/PR-STD-003_Remote-Access-Standard.docx | AE75: Not started
A76: PR-PRC-001 | B76: User Access Management Procedure | C76: ระเบียบปฏิบัติการบริหารจัดการสิทธิ์ผู้ใช้งาน | D76: Protect (PR) | E76: Identity Management, Authentication, and Access Control (PR.AA) | F76: T3 | G76: Procedure | H76: Organizational | I76: Essential | J76: Expected | K76: PDPA | L76: ISO/IEC 27001:2022 Annex A 5.16 and 5.18; PDPC Notification on Security Measures B.E. 2565 | M76: Expected | N76: PR.AA-01, PR.AA-05 | O76: A.5.16, A.5.18 | P76: AC-2 | Q76: IT Infrastructure Manager | R76: Chief Information Officer (CIO) | S76: Annual | T76: PR-POL-001 | U76: PR-FRM-001 | V76: Process, Legal and Regulatory, Privacy | W76: 86 | X76: W3 Standardize | Y76: Track A | Z76: IT-ready | AA76: In-house IT | AC76: PR-POL-001 | AD76: 02_Template_EN/03_PR_Protect/PR.AA_Identity-Management-Authentication-and-Access-Control/PR-PRC-001_User-Access-Management-Procedure.docx | AE76: Not started
A77: PR-PRC-002 | B77: User Access Review Procedure | C77: ระเบียบปฏิบัติการทบทวนสิทธิ์ผู้ใช้งาน | D77: Protect (PR) | E77: Identity Management, Authentication, and Access Control (PR.AA) | F77: T3 | G77: Procedure | H77: Organizational | I77: Essential | J77: Expected | K77: All | L77: ISO/IEC 27001:2022 Annex A 5.18 | M77: Expected | N77: PR.AA-05 | O77: A.5.18 | P77: AC-2 | Q77: Chief Information Security Officer (CISO) or Security Manager | R77: Chief Information Officer (CIO) | S77: Annual | T77: PR-POL-001 | U77: PR-REC-001 | V77: Process | W77: 90 | X77: W3 Standardize | Y77: Track A | Z77: IT-ready | AA77: In-house IT | AC77: PR-POL-001 | AD77: 02_Template_EN/03_PR_Protect/PR.AA_Identity-Management-Authentication-and-Access-Control/PR-PRC-002_User-Access-Review-Procedure.docx | AE77: Not started
A78: PR-FRM-001 | B78: User Access Request Form | C78: แบบฟอร์มขอสิทธิ์เข้าใช้งานระบบ | D78: Protect (PR) | E78: Identity Management, Authentication, and Access Control (PR.AA) | F78: T4 | G78: Form | H78: Organizational | I78: Essential | J78: Expected | K78: All | L78: ISO/IEC 27001:2022 Annex A 5.18 | M78: Expected | N78: PR.AA-01, PR.AA-05 | O78: A.5.18 | P78: AC-2 | Q78: IT Infrastructure Manager | R78: Chief Information Officer (CIO) | S78: Annual | T78: PR-PRC-001 | V78: Process, Evidence | W78: 87 | X78: W3 Standardize | Y78: Track A | Z78: IT-ready | AA78: In-house IT | AC78: PR-PRC-001 | AD78: 02_Template_EN/03_PR_Protect/PR.AA_Identity-Management-Authentication-and-Access-Control/PR-FRM-001_User-Access-Request-Form.docx | AE78: Not started
A79: PR-FRM-002 | B79: Privileged Access Request Form | C79: แบบฟอร์มขอสิทธิ์ระดับสูง | D79: Protect (PR) | E79: Identity Management, Authentication, and Access Control (PR.AA) | F79: T4 | G79: Form | H79: Technological | I79: Core | J79: Expected | K79: All | L79: ISO/IEC 27001:2022 Annex A 8.2 | M79: Expected | N79: PR.AA-05 | O79: A.8.2 | P79: AC-6, AC-2 | Q79: Chief Information Security Officer (CISO) or Security Manager | R79: Chief Information Officer (CIO) | S79: Annual | T79: PR-STD-002 | V79: Process, Evidence | W79: 88 | X79: W3 Standardize | Y79: Track A | Z79: IT-ready | AA79: In-house IT | AC79: PR-STD-002 | AD79: 02_Template_EN/03_PR_Protect/PR.AA_Identity-Management-Authentication-and-Access-Control/PR-FRM-002_Privileged-Access-Request-Form.docx | AE79: Not started
A80: PR-FRM-003 | B80: Third-Party Remote Access Request Form | C80: แบบฟอร์มขอเข้าถึงระยะไกลสำหรับบุคคลภายนอก | D80: Protect (PR) | E80: Identity Management, Authentication, and Access Control (PR.AA) | F80: T4 | G80: Form | H80: Organizational | I80: Core | J80: Expected | K80: All | L80: ISO/IEC 27001:2022 Annex A 5.19 and 8.20 | M80: Expected | N80: PR.AA-05, GV.SC-07 | O80: A.5.19, A.8.20 | P80: AC-17, MA-4 | Q80: Chief Information Security Officer (CISO) or Security Manager | R80: Chief Information Officer (CIO) | S80: Annual | T80: PR-STD-003 | V80: Process, Evidence, Third Party | W80: 89 | X80: W3 Standardize | Y80: Track A | Z80: IT-ready | AA80: In-house IT | AC80: PR-STD-003 | AD80: 02_Template_EN/03_PR_Protect/PR.AA_Identity-Management-Authentication-and-Access-Control/PR-FRM-003_Third-Party-Remote-Access-Request-Form.docx | AE80: Not started
A81: PR-REC-001 | B81: User Access Review Record | C81: บันทึกผลการทบทวนสิทธิ์ผู้ใช้งาน | D81: Protect (PR) | E81: Identity Management, Authentication, and Access Control (PR.AA) | F81: T4 | G81: Record | H81: Organizational | I81: Core | J81: Expected | K81: All | L81: ISO/IEC 27001:2022 Annex A 5.18 | M81: Expected | N81: PR.AA-05 | O81: A.5.18 | P81: AC-2 | Q81: System Owner | R81: Chief Information Security Officer (CISO) or Security Manager | S81: Each review cycle | T81: PR-PRC-002 | V81: Process, Evidence | W81: 120 | X81: W4 Operate and Prove | Y81: Track A | Z81: IT-ready | AA81: In-house IT | AB81: ACT-19 Identity and Privileged Access Review | AC81: PR-PRC-002 | AD81: 02_Template_EN/03_PR_Protect/PR.AA_Identity-Management-Authentication-and-Access-Control/PR-REC-001_User-Access-Review-Record.docx | AE81: Not started
A82: PR-REG-001 | B82: Privileged Account Register | C82: ทะเบียนบัญชีสิทธิ์ระดับสูง | D82: Protect (PR) | E82: Identity Management, Authentication, and Access Control (PR.AA) | F82: T4 | G82: Register | H82: Technological | I82: Essential | J82: Expected | K82: All | L82: ISO/IEC 27001:2022 Annex A 8.2 | M82: Expected | N82: PR.AA-05, PR.AA-01 | O82: A.8.2 | P82: AC-2, AC-6 | Q82: Chief Information Security Officer (CISO) or Security Manager | R82: Chief Information Officer (CIO) | S82: Quarterly | T82: PR-STD-002 | V82: Technology, Evidence | W82: 15 | X82: W0 Mandate and Mobilize | Y82: Track B | Z82: IT-ready | AA82: In-house IT | AB82: ACT-19 Identity and Privileged Access Review | AD82: 02_Template_EN/03_PR_Protect/PR.AA_Identity-Management-Authentication-and-Access-Control/PR-REG-001_Privileged-Account-Register.docx | AE82: Not started
A83: PR-POL-002 | B83: Physical and Environmental Security Policy | C83: นโยบายความมั่นคงปลอดภัยทางกายภาพและสภาพแวดล้อม | D83: Protect (PR) | E83: Identity Management, Authentication, and Access Control (PR.AA) | F83: T1 | G83: Policy | H83: Physical | I83: Core | J83: Expected | K83: All | L83: ISO/IEC 27001:2022 Annex A 7.1 to 7.14 | M83: Expected | N83: PR.AA-06, PR.IR-02, DE.CM-02 | O83: A.7.1, A.7.2, A.7.4, A.7.5, A.7.11 | P83: PE-1 | Q83: Facilities Manager | R83: Chief Executive Officer (CEO) | S83: Annual | T83: GV-POL-001 | U83: PR-PRC-003 | V83: Physical | W83: 50 | X83: W2 Direct | Y83: Track A | Z83: IT-ready | AA83: In-house IT | AB83: ACT-13 Policy Drafting and Stakeholder Review Cycle; ACT-14 Policy Approval and Communication | AC83: GV-POL-001 | AD83: 02_Template_EN/03_PR_Protect/PR.AA_Identity-Management-Authentication-and-Access-Control/PR-POL-002_Physical-and-Environmental-Security-Policy.docx | AE83: Not started
A84: PR-PRC-003 | B84: Physical Access Management Procedure | C84: ระเบียบปฏิบัติการควบคุมการเข้าถึงพื้นที่ | D84: Protect (PR) | E84: Identity Management, Authentication, and Access Control (PR.AA) | F84: T3 | G84: Procedure | H84: Physical | I84: Core | J84: Expected | K84: All | L84: ISO/IEC 27001:2022 Annex A 7.2 and 7.6 | M84: Expected | N84: PR.AA-06, DE.CM-02 | O84: A.7.2, A.7.6 | P84: PE-2, PE-3, PE-6 | Q84: Facilities Manager | R84: Chief Information Officer (CIO) | S84: Annual | T84: PR-POL-002 | U84: PR-FRM-004 | V84: Physical | W84: 91 | X84: W3 Standardize | Y84: Track A | Z84: IT-ready | AA84: In-house IT | AC84: PR-POL-002 | AD84: 02_Template_EN/03_PR_Protect/PR.AA_Identity-Management-Authentication-and-Access-Control/PR-PRC-003_Physical-Access-Management-Procedure.docx | AE84: Not started
A85: PR-FRM-004 | B85: Secure Area Access and Visitor Log | C85: แบบบันทึกการเข้าพื้นที่ควบคุมและผู้มาติดต่อ | D85: Protect (PR) | E85: Identity Management, Authentication, and Access Control (PR.AA) | F85: T4 | G85: Form | H85: Physical | I85: Core | J85: Expected | K85: All | L85: ISO/IEC 27001:2022 Annex A 7.2 | M85: Expected | N85: PR.AA-06 | O85: A.7.2 | P85: PE-8 | Q85: Facilities Manager | R85: Facilities Manager | S85: Annual | T85: PR-PRC-003 | V85: Physical, Evidence | W85: 92 | X85: W3 Standardize | Y85: Track A | Z85: IT-ready | AA85: In-house IT | AC85: PR-PRC-003 | AD85: 02_Template_EN/03_PR_Protect/PR.AA_Identity-Management-Authentication-and-Access-Control/PR-FRM-004_Secure-Area-Access-and-Visitor-Log.docx | AE85: Not started
A86: PR-PLN-001 | B86: Security Awareness and Training Program | C86: แผนการสร้างความตระหนักรู้และการฝึกอบรมด้านความมั่นคงปลอดภัย | D86: Protect (PR) | E86: Awareness and Training (PR.AT) | F86: T3 | G86: Plan | H86: People | I86: Essential | J86: Expected | K86: PDPA | L86: ISO/IEC 27001:2022 Clause 7.3 and Annex A 6.3; PDPC Notification on Security Measures B.E. 2565 (awareness) | M86: Expected | N86: PR.AT-01, PR.AT-02 | O86: 7.3, A.6.3 | P86: AT-1, AT-2, AT-3 | Q86: Chief Information Security Officer (CISO) or Security Manager | R86: Information Security Steering Committee (ISSC) | S86: Annual | T86: GV-POL-001 | U86: PR-REG-002, PR-REC-002, PR-PRC-004 | V86: People, Legal and Regulatory, Privacy | W86: 54 | X86: W2 Direct | Y86: Track A | Z86: IT-ready | AA86: In-house IT / Human Resources | AB86: ACT-23 Training Needs Analysis and Awareness Planning | AC86: GV-POL-003 | AD86: 02_Template_EN/03_PR_Protect/PR.AT_Awareness-and-Training/PR-PLN-001_Security-Awareness-and-Training-Program.docx | AE86: Not started
A87: PR-REG-002 | B87: Role-Based Training and Skills Matrix | C87: ตารางทักษะและการฝึกอบรมตามบทบาท | D87: Protect (PR) | E87: Awareness and Training (PR.AT) | F87: T4 | G87: Register | H87: People | I87: Core | J87: Required | K87: ISO 27001 | L87: ISO/IEC 27001:2022 Clause 7.2 (documented evidence of competence) | M87: Expected | N87: PR.AT-02, GV.RR-04 | O87: 7.2 | P87: AT-3, PM-13 | Q87: Chief Information Security Officer (CISO) or Security Manager | R87: Human Resources Director | S87: Annual | T87: PR-PLN-001 | V87: People, Evidence | W87: 93 | X87: W3 Standardize | Y87: Track A | Z87: IT-ready | AA87: In-house IT / Human Resources | AB87: ACT-23 Training Needs Analysis and Awareness Planning | AC87: PR-PLN-001 | AD87: 02_Template_EN/03_PR_Protect/PR.AT_Awareness-and-Training/PR-REG-002_Role-Based-Training-and-Skills-Matrix.docx | AE87: Not started
A88: PR-REC-002 | B88: Training Completion Record | C88: บันทึกการเข้ารับการฝึกอบรม | D88: Protect (PR) | E88: Awareness and Training (PR.AT) | F88: T4 | G88: Record | H88: People | I88: Core | J88: Required | K88: ISO 27001 | L88: ISO/IEC 27001:2022 Clause 7.2 (documented evidence of competence) | M88: Expected | N88: PR.AT-01, PR.AT-02 | O88: 7.2, A.6.3 | P88: AT-4 | Q88: Human Resources Director | R88: Chief Information Security Officer (CISO) or Security Manager | S88: Continuous | T88: PR-PLN-001 | V88: People, Evidence | W88: 121 | X88: W4 Operate and Prove | Y88: Track A | Z88: IT-ready | AA88: Human Resources | AB88: ACT-23 Training Needs Analysis and Awareness Planning | AC88: PR-PLN-001 | AD88: 02_Template_EN/03_PR_Protect/PR.AT_Awareness-and-Training/PR-REC-002_Training-Completion-Record.docx | AE88: Not started
A89: PR-PRC-004 | B89: Phishing Simulation Procedure | C89: ระเบียบปฏิบัติการทดสอบฟิชชิ่งจำลอง | D89: Protect (PR) | E89: Awareness and Training (PR.AT) | F89: T3 | G89: Procedure | H89: People | I89: Extended | J89: Optional | K89: All | L89: NIST SP 800-50 Rev. 1 | M89: Optional | N89: PR.AT-01 | O89: A.6.3 | P89: AT-2(1) | Q89: Chief Information Security Officer (CISO) or Security Manager | R89: Chief Information Officer (CIO) | S89: Annual | T89: PR-PLN-001 | V89: People | W89: 136 | X89: W5 Optimize | Y89: Track A | Z89: IT-ready | AA89: In-house IT / Managed Security Service Provider (MSSP) | AB89: ACT-23 Training Needs Analysis and Awareness Planning | AC89: PR-PLN-001 | AD89: 02_Template_EN/03_PR_Protect/PR.AT_Awareness-and-Training/PR-PRC-004_Phishing-Simulation-Procedure.docx | AE89: Not started
A90: PR-POL-003 | B90: Data Protection and Classification Policy | C90: นโยบายการจัดชั้นและการปกป้องข้อมูล | D90: Protect (PR) | E90: Data Security (PR.DS) | F90: T1 | G90: Policy | H90: Organizational | I90: Essential | J90: Expected | K90: PDPA | L90: ISO/IEC 27001:2022 Annex A 5.12 and 5.13; PDPA s.37(1) | M90: Expected | N90: PR.DS-01, PR.DS-02, PR.DS-10 | O90: A.5.12, A.5.13, A.5.14 | P90: RA-2, MP-1, SC-1 | Q90: Chief Information Security Officer (CISO) or Security Manager | R90: Chief Executive Officer (CEO) | S90: Annual | T90: GV-POL-001 | U90: PR-STD-004, PR-STD-005, PR-STD-006, PR-STD-007, PR-STD-008 | V90: Governance, Legal and Regulatory, Privacy | W90: 47 | X90: W2 Direct | Y90: Track A | Z90: Specialist-guided | AA90: Security FTE / DPO or privacy counsel service | AB90: ACT-13 Policy Drafting and Stakeholder Review Cycle; ACT-14 Policy Approval and Communication | AC90: GV-POL-001, ID-REG-003 | AD90: 02_Template_EN/03_PR_Protect/PR.DS_Data-Security/PR-POL-003_Data-Protection-and-Classification-Policy.docx | AE90: Not started
A91: PR-STD-004 | B91: Information Classification and Handling Standard | C91: มาตรฐานการจัดชั้นความลับและการจัดการข้อมูล | D91: Protect (PR) | E91: Data Security (PR.DS) | F91: T2 | G91: Standard | H91: Organizational | I91: Essential | J91: Expected | K91: All | L91: ISO/IEC 27001:2022 Annex A 5.12, 5.13, and 5.14 | M91: Expected | N91: PR.DS-01, PR.DS-02, PR.DS-10 | O91: A.5.12, A.5.13, A.5.14 | P91: RA-2, MP-3, MP-4 | Q91: Chief Information Security Officer (CISO) or Security Manager | R91: Chief Information Officer (CIO) | S91: Annual | T91: PR-POL-003 | V91: Process | W91: 70 | X91: W3 Standardize | Y91: Track A | Z91: Specialist-guided | AA91: Security FTE / DPO or privacy counsel service | AB91: ACT-13 Policy Drafting and Stakeholder Review Cycle | AC91: PR-POL-003 | AD91: 02_Template_EN/03_PR_Protect/PR.DS_Data-Security/PR-STD-004_Information-Classification-and-Handling-Standard.docx | AE91: Not started
A92: PR-STD-005 | B92: Cryptography and Key Management Standard | C92: มาตรฐานการเข้ารหัสและการบริหารจัดการกุญแจ | D92: Protect (PR) | E92: Data Security (PR.DS) | F92: T2 | G92: Standard | H92: Technological | I92: Core | J92: Expected | K92: All | L92: ISO/IEC 27001:2022 Annex A 8.24 | M92: Expected | N92: PR.DS-01, PR.DS-02 | O92: A.8.24 | P92: SC-8, SC-12, SC-13, SC-28 | Q92: Chief Information Security Officer (CISO) or Security Manager | R92: Chief Information Officer (CIO) | S92: Annual | T92: PR-POL-003 | V92: Technology | W92: 71 | X92: W3 Standardize | Y92: Track A | Z92: Specialist-required | AA92: Security FTE / Cybersecurity consultant (project) | AB92: ACT-13 Policy Drafting and Stakeholder Review Cycle | AC92: PR-POL-003 | AD92: 02_Template_EN/03_PR_Protect/PR.DS_Data-Security/PR-STD-005_Cryptography-and-Key-Management-Standard.docx | AE92: Not started
A93: PR-STD-006 | B93: Backup Standard | C93: มาตรฐานการสำรองข้อมูล | D93: Protect (PR) | E93: Data Security (PR.DS) | F93: T2 | G93: Standard | H93: Technological | I93: Essential | J93: Expected | K93: All | L93: ISO/IEC 27001:2022 Annex A 8.13; CIS Controls v8.1 Control 11 | M93: Expected | N93: PR.DS-11 | O93: A.8.13 | P93: CP-9 | Q93: IT Infrastructure Manager | R93: Chief Information Officer (CIO) | S93: Annual | T93: PR-POL-003 | U93: PR-PRC-005 | V93: Technology, Resilience | W93: 11 | X93: W0 Mandate and Mobilize | Y93: Track B | Z93: IT-ready | AA93: In-house IT | AB93: ACT-18 Backup and Restore Validation Test | AD93: 02_Template_EN/03_PR_Protect/PR.DS_Data-Security/PR-STD-006_Backup-Standard.docx | AE93: Not started
A94: PR-PRC-005 | B94: Backup and Restore Procedure | C94: ระเบียบปฏิบัติการสำรองและกู้คืนข้อมูล | D94: Protect (PR) | E94: Data Security (PR.DS) | F94: T3 | G94: Procedure | H94: Technological | I94: Essential | J94: Expected | K94: All | L94: ISO/IEC 27001:2022 Annex A 8.13 | M94: Expected | N94: PR.DS-11, RC.RP-03 | O94: A.8.13 | P94: CP-9, CP-10 | Q94: IT Infrastructure Manager | R94: Chief Information Officer (CIO) | S94: Annual | T94: PR-STD-006 | U94: PR-REC-003 | V94: Technology, Resilience | W94: 12 | X94: W0 Mandate and Mobilize | Y94: Track B | Z94: IT-ready | AA94: In-house IT | AB94: ACT-18 Backup and Restore Validation Test | AC94: PR-STD-006 | AD94: 02_Template_EN/03_PR_Protect/PR.DS_Data-Security/PR-PRC-005_Backup-and-Restore-Procedure.docx | AE94: Not started
A95: PR-REC-003 | B95: Backup and Restore Test Record | C95: บันทึกผลการทดสอบการกู้คืนข้อมูล | D95: Protect (PR) | E95: Data Security (PR.DS) | F95: T4 | G95: Record | H95: Technological | I95: Essential | J95: Expected | K95: All | L95: ISO/IEC 27001:2022 Annex A 8.13 | M95: Expected | N95: PR.DS-11, RC.RP-03 | O95: A.8.13 | P95: CP-9(1) | Q95: IT Infrastructure Manager | R95: Chief Information Security Officer (CISO) or Security Manager | S95: Each test | T95: PR-PRC-005 | V95: Technology, Evidence, Resilience | W95: 13 | X95: W0 Mandate and Mobilize | Y95: Track B | Z95: IT-ready | AA95: In-house IT | AB95: ACT-18 Backup and Restore Validation Test | AC95: PR-PRC-005 | AD95: 02_Template_EN/03_PR_Protect/PR.DS_Data-Security/PR-REC-003_Backup-and-Restore-Test-Record.docx | AE95: Not started
A96: PR-STD-007 | B96: Data Retention and Disposal Standard | C96: มาตรฐานการเก็บรักษาและการทำลายข้อมูล | D96: Protect (PR) | E96: Data Security (PR.DS) | F96: T2 | G96: Standard | H96: Organizational | I96: Core | J96: Expected | K96: PDPA | L96: PDPA s.37(3); ISO/IEC 27001:2022 Annex A 5.33 and 8.10 | M96: Expected | N96: PR.DS-01, ID.AM-08 | O96: A.5.33, A.8.10 | P96: SI-12, MP-6 | Q96: Data Protection Officer (DPO) | R96: Chief Information Officer (CIO) | S96: Annual | T96: PR-POL-003 | V96: Process, Legal and Regulatory, Privacy | W96: 72 | X96: W3 Standardize | Y96: Track A | Z96: Specialist-guided | AA96: DPO or privacy counsel service / Legal counsel | AB96: ACT-13 Policy Drafting and Stakeholder Review Cycle | AC96: PR-POL-003 | AD96: 02_Template_EN/03_PR_Protect/PR.DS_Data-Security/PR-STD-007_Data-Retention-and-Disposal-Standard.docx | AE96: Not started
A97: PR-STD-008 | B97: Data Loss Prevention Standard | C97: มาตรฐานการป้องกันข้อมูลรั่วไหล | D97: Protect (PR) | E97: Data Security (PR.DS) | F97: T2 | G97: Standard | H97: Technological | I97: Extended | J97: Optional | K97: All | L97: ISO/IEC 27001:2022 Annex A 8.12 | M97: Optional | N97: PR.DS-01, PR.DS-02, PR.DS-10 | O97: A.8.12 | P97: AC-4, SI-4 | Q97: Chief Information Security Officer (CISO) or Security Manager | R97: Chief Information Officer (CIO) | S97: Annual | T97: PR-POL-003 | V97: Technology | W97: 137 | X97: W5 Optimize | Y97: Track A | Z97: Specialist-required | AA97: Cybersecurity consultant (project) | AC97: PR-STD-004 | AD97: 02_Template_EN/03_PR_Protect/PR.DS_Data-Security/PR-STD-008_Data-Loss-Prevention-Standard.docx | AE97: Not started
A98: PR-STD-009 | B98: Mobile Device and BYOD Standard | C98: มาตรฐานอุปกรณ์เคลื่อนที่และอุปกรณ์ส่วนตัว (BYOD) | D98: Protect (PR) | E98: Data Security (PR.DS) | F98: T2 | G98: Standard | H98: Technological | I98: Core | J98: Expected | K98: All | L98: ISO/IEC 27001:2022 Annex A 8.1 and 6.7 | M98: Expected | N98: PR.DS-01, PR.AA-03, PR.PS-01 | O98: A.8.1, A.6.7 | P98: AC-19 | Q98: Chief Information Security Officer (CISO) or Security Manager | R98: Chief Information Officer (CIO) | S98: Annual | T98: GV-POL-003 | V98: Technology, People | W98: 73 | X98: W3 Standardize | Y98: Track A | Z98: Specialist-guided | AA98: In-house IT / Cybersecurity consultant (project) | AB98: ACT-13 Policy Drafting and Stakeholder Review Cycle | AC98: GV-POL-003 | AD98: 02_Template_EN/03_PR_Protect/PR.DS_Data-Security/PR-STD-009_Mobile-Device-and-BYOD-Standard.docx | AE98: Not started
A99: PR-STD-010 | B99: Secure Configuration Baseline Standard | C99: มาตรฐานการตั้งค่าระบบอย่างมั่นคงปลอดภัย | D99: Protect (PR) | E99: Platform Security (PR.PS) | F99: T2 | G99: Standard | H99: Technological | I99: Core | J99: Expected | K99: All | L99: ISO/IEC 27001:2022 Annex A 8.9; CIS Controls v8.1 Control 4; CIS Benchmarks | M99: Expected | N99: PR.PS-01 | O99: A.8.9 | P99: CM-2, CM-6, CM-7 | Q99: IT Infrastructure Manager | R99: Chief Information Officer (CIO) | S99: Annual | T99: GV-POL-001 | V99: Technology | W99: 74 | X99: W3 Standardize | Y99: Track A | Z99: Specialist-guided | AA99: In-house IT / Cybersecurity consultant (project) | AB99: ACT-15 Technical Baseline Review | AC99: ID-REG-001 | AD99: 02_Template_EN/03_PR_Protect/PR.PS_Platform-Security/PR-STD-010_Secure-Configuration-Baseline-Standard.docx | AE99: Not started
A100: PR-PRC-006 | B100: Change Management Procedure | C100: ระเบียบปฏิบัติการบริหารการเปลี่ยนแปลง | D100: Protect (PR) | E100: Platform Security (PR.PS) | F100: T3 | G100: Procedure | H100: Technological | I100: Essential | J100: Expected | K100: All | L100: ISO/IEC 27001:2022 Annex A 8.32 | M100: Expected | N100: PR.PS-01, ID.RA-07 | O100: A.8.32 | P100: CM-3, CM-4 | Q100: IT Infrastructure Manager | R100: Chief Information Officer (CIO) | S100: Annual | T100: GV-POL-001 | U100: PR-FRM-005 | V100: Process | W100: 75 | X100: W3 Standardize | Y100: Track A | Z100: IT-ready | AA100: In-house IT | AB100: ACT-28 Change Advisory Board (CAB) Setup | AC100: GV-POL-001 | AD100: 02_Template_EN/03_PR_Protect/PR.PS_Platform-Security/PR-PRC-006_Change-Management-Procedure.docx | AE100: Not started
...

Sheet Implementation Roadmap
A1: Build Order | B1: Wave | C1: Wave Name | D1: Timing | E1: Track | F1: Document ID | G1: Title | H1: Level | I1: Capability | J1: Why | K1: Sourcing Options | L1: Prerequisite Activities | M1: Depends On | N1: Unlocks | O1: Interim: Align Later To | P1: Advice
A2: 1 | B2: W0 | C2: Mandate and Mobilize | D2: Month 0 to 2 | E2: Track A: Governance build | F2: GV-CHR-001 | G2: Cybersecurity Governance Charter | H2: Expected | I2: Specialist-guided | J2: Needs neutral facilitation of executive or cross-department decisions. | K2: In-house IT / Cybersecurity consultant (project) | L2: ACT-01 Executive Kickoff and Mandate Meeting; ACT-02 Governance Structure and RACI Workshop | N2: GV-CHR-002, GV-POL-001, GV-RPT-001, GV-STM-001, RC-POL-001, GV-PRC-007
A3: 2 | B3: W0 | C3: Mandate and Mobilize | D3: Month 0 to 2 | E3: Track A: Governance build | F3: GV-CHR-002 | G3: Information Security Steering Committee Terms of Reference | H3: Expected | I3: IT-ready | J3: Template-driven: content is mostly factual or administrative. | K3: In-house IT | L3: ACT-02 Governance Structure and RACI Workshop | M3: GV-CHR-001 | N3: GV-REG-003, GV-PRC-006
A4: 3 | B4: W0 | C4: Mandate and Mobilize | D4: Month 0 to 2 | E4: Track A: Governance build | F4: GV-REG-003 | G4: Cybersecurity Roles, Responsibilities, and RACI Matrix | H4: Expected | I4: Specialist-guided | J4: Needs neutral facilitation of executive or cross-department decisions. | K4: In-house IT / Cybersecurity consultant (project) | L4: ACT-02 Governance Structure and RACI Workshop | M4: GV-CHR-002 | N4: GV-TPL-001
A5: 4 | B5: W0 | C5: Mandate and Mobilize | D5: Month 0 to 2 | E5: Track A: Governance build | F5: GV-REG-001 | G5: Legal, Regulatory, and Contractual Requirements Register | H5: Expected | I5: Specialist-required | J5: Needs interpretation of Thai cybersecurity, PDPA, or contract obligations. | K5: Legal counsel / Cybersecurity consultant (project) | L5: ACT-03 Legal and Regulatory Applicability Review | N5: GV-POL-001, GV-RPT-001, GV-POL-004, GV-REG-006, PR-STD-011, RS-PRC-003 | O5: GV-RPT-001
A6: 5 | B6: W0 | C6: Mandate and Mobilize | D6: Month 0 to 2 | E6: Track A: Governance build | F6: GV-POL-001 | G6: Information Security Policy | H6: Required | I6: Specialist-guided | J6: Needs neutral facilitation of executive or cross-department decisions. Needs interpretation of Thai cybersecurity, PDPA, or contract obligations. | K6: Cybersecurity consultant (project) / Security FTE | L6: ACT-03 Legal and Regulatory Applicability Review; ACT-13 Policy Drafting and Stakeholder Review Cycle; ACT-14 Policy Approval and Communication | M6: GV-CHR-001, GV-REG-001 | N6: GV-PRC-002, ID-STD-001, GV-POL-004, GV-POL-002, GV-POL-003, PR-POL-001, PR-POL-003, GV-POL-006, PR-POL-002, GV-STD-001, GV-PRC-003, ID-STD-002, PR-PRC-006, PR-STD-013, ID-PRC-006 | P6: Issue a short umbrella policy early. Topic policies follow once the risk picture is known.
A7: 6 | B7: W0 | C7: Mandate and Mobilize | D7: Month 0 to 2 | E7: Track A: Governance build | F7: GV-PRC-002 | G7: Document Control Procedure | H7: Expected | I7: IT-ready | J7: Template-driven: content is mostly factual or administrative. | K7: In-house IT | L7: ACT-14 Policy Approval and Communication | M7: GV-POL-001
A8: 7 | B8: W0 | C8: Mandate and Mobilize | D8: Month 0 to 2 | E8: Track B: Threat-driven quick wins (Day 0 to 90) | F8: RS-REG-002 | G8: Incident Response Contact List | H8: Required | I8: IT-ready | J8: Template-driven: content is mostly factual or administrative. | K8: In-house IT | N8: RS-PLN-001
A9: 8 | B9: W0 | C9: Mandate and Mobilize | D9: Month 0 to 2 | E9: Track B: Threat-driven quick wins (Day 0 to 90) | F9: RS-PLN-001 | G9: Cybersecurity Incident Response Plan | H9: Required | I9: Specialist-required | J9: Needs incident handling and digital forensics experience. Needs interpretation of Thai cybersecurity, PDPA, or contract obligations. | K9: Incident response retainer / Cybersecurity consultant (project) | L9: ACT-17 Incident Response Readiness Workshop | M9: RS-REG-002 | N9: RS-FRM-001, RS-REG-001, RS-PLB-001, DE-STD-002, RS-PRC-001, RS-PRC-002, RS-PRC-003, ID-PLN-002 | P9: Start with a 5 to 10 page interim plan in the first 30 days. Expand it in Wave 3 once severity levels and procedures exist.
A10: 9 | B10: W0 | C10: Mandate and Mobilize | D10: Month 0 to 2 | E10: Track B: Threat-driven quick wins (Day 0 to 90) | F10: RS-FRM-001 | G10: Incident Report Form | H10: Expected | I10: IT-ready | J10: Template-driven: content is mostly factual or administrative. | K10: In-house IT | M10: RS-PLN-001 | O10: RS-PRC-001
A11: 10 | B11: W0 | C11: Mandate and Mobilize | D11: Month 0 to 2 | E11: Track B: Threat-driven quick wins (Day 0 to 90) | F11: RS-REG-001 | G11: Incident Register | H11: Expected | I11: IT-ready | J11: Template-driven: content is mostly factual or administrative. | K11: In-house IT | M11: RS-PLN-001 | O11: RS-PRC-001
A12: 11 | B12: W0 | C12: Mandate and Mobilize | D12: Month 0 to 2 | E12: Track B: Threat-driven quick wins (Day 0 to 90) | F12: PR-STD-006 | G12: Backup Standard | H12: Expected | I12: IT-ready | J12: Template-driven: content is mostly factual or administrative. | K12: In-house IT | L12: ACT-18 Backup and Restore Validation Test | N12: PR-PRC-005 | O12: PR-POL-003
A13: 12 | B13: W0 | C13: Mandate and Mobilize | D13: Month 0 to 2 | E13: Track B: Threat-driven quick wins (Day 0 to 90) | F13: PR-PRC-005 | G13: Backup and Restore Procedure | H13: Expected | I13: IT-ready | J13: Operational: IT runs it day to day once the parent standard exists. | K13: In-house IT | L13: ACT-18 Backup and Restore Validation Test | M13: PR-STD-006 | N13: PR-REC-003, RS-PLB-001
A14: 13 | B14: W0 | C14: Mandate and Mobilize | D14: Month 0 to 2 | E14: Track B: Threat-driven quick wins (Day 0 to 90) | F14: PR-REC-003 | G14: Backup and Restore Test Record | H14: Expected | I14: IT-ready | J14: Operational: IT runs it day to day once the parent standard exists. | K14: In-house IT | L14: ACT-18 Backup and Restore Validation Test | M14: PR-PRC-005
A15: 14 | B15: W0 | C15: Mandate and Mobilize | D15: Month 0 to 2 | E15: Track B: Threat-driven quick wins (Day 0 to 90) | F15: PR-STD-001 | G15: Identity and Authentication Standard | H15: Expected | I15: Specialist-guided | J15: Needs security architecture judgment to set technical requirements. | K15: In-house IT / Cybersecurity consultant (project) | L15: ACT-19 Identity and Privileged Access Review | N15: PR-STD-002, PR-STD-003 | O15: PR-POL-001 | P15: Multi-factor authentication for remote access, email, and administrators is the first technical control to enforce.
A16: 15 | B16: W0 | C16: Mandate and Mobilize | D16: Month 0 to 2 | E16: Track B: Threat-driven quick wins (Day 0 to 90) | F16: PR-REG-001 | G16: Privileged Account Register | H16: Expected | I16: IT-ready | J16: Operational: IT runs it day to day once the parent standard exists. | K16: In-house IT | L16: ACT-19 Identity and Privileged Access Review | O16: PR-STD-002
A17: 16 | B17: W1 | C17: Understand | D17: Month 1 to 4 | E17: Track A: Governance build | F17: GV-RPT-001 | G17: Organizational Context and ISMS Scope Statement | H17: Required | I17: Specialist-guided | J17: Needs neutral facilitation of executive or cross-department decisions. | K17: Cybersecurity consultant (project) / Security FTE | L17: ACT-04 Scope and Organizational Context Workshop | M17: GV-CHR-001, GV-REG-001 | N17: GV-REG-002, GV-STR-001, GV-REG-005
A18: 17 | B18: W1 | C18: Understand | D18: Month 1 to 4 | E18: Track A: Governance build | F18: GV-REG-002 | G18: Stakeholder Requirements Register | H18: Expected | I18: IT-ready | J18: Template-driven: content is mostly factual or administrative. | K18: In-house IT | L18: ACT-04 Scope and Organizational Context Workshop | M18: GV-RPT-001
A19: 18 | B19: W1 | C19: Understand | D19: Month 1 to 4 | E19: Track A: Governance build | F19: ID-STD-001 | G19: Asset Management Standard | H19: Expected | I19: IT-ready | J19: Template-driven: content is mostly factual or administrative. | K19: In-house IT | L19: ACT-13 Policy Drafting and Stakeholder Review Cycle | M19: GV-POL-001 | N19: ID-PRC-001
A20: 19 | B20: W1 | C20: Understand | D20: Month 1 to 4 | E20: Track A: Governance build | F20: ID-REG-001 | G20: Hardware Asset Inventory | H20: Expected | I20: IT-ready | J20: Template-driven: content is mostly factual or administrative. Operational: IT runs it day to day once the parent standard exists. | K20: In-house IT | L20: ACT-05 Asset Discovery and Inventory Reconciliation | N20: ID-RPT-001, ID-REG-004, ID-RPT-002, ID-REG-005, PR-STD-012, PR-STD-010 | P20: Do not wait for the asset standard. Build the inventory now and formalize the rules later.
A21: 20 | B21: W1 | C21: Understand | D21: Month 1 to 4 | E21: Track A: Governance build | F21: ID-REG-002 | G21: Software and Service Inventory | H21: Expected | I21: IT-ready | J21: Template-driven: content is mostly factual or administrative. Operational: IT runs it day to day once the parent standard exists. | K21: In-house IT | L21: ACT-05 Asset Discovery and Inventory Reconciliation | N21: ID-REG-003, ID-RPT-002
A22: 21 | B22: W1 | C22: Understand | D22: Month 1 to 4 | E22: Track A: Governance build | F22: ID-RPT-001 | G22: Network Architecture and Data Flow Diagram | H22: Expected | I22: IT-ready | J22: Template-driven: content is mostly factual or administrative. | K22: In-house IT | L22: ACT-05 Asset Discovery and Inventory Reconciliation | M22: ID-REG-001 | N22: PR-STD-016
A23: 22 | B23: W1 | C23: Understand | D23: Month 1 to 4 | E23: Track A: Governance build | F23: ID-REG-004 | G23: OT and Medical Device Inventory | H23: Optional | I23: IT-ready | J23: Template-driven: content is mostly factual or administrative. | K23: In-house IT | L23: ACT-05 Asset Discovery and Inventory Reconciliation | M23: ID-REG-001 | N23: PR-STD-015
A24: 23 | B24: W1 | C24: Understand | D24: Month 1 to 4 | E24: Track A: Governance build | F24: ID-REG-003 | G24: Data Inventory and Data Flow Register | H24: Expected | I24: Specialist-guided | J24: Needs privacy expertise: PDPA lawful basis, DPIA, data subject rights. | K24: DPO or privacy counsel service / In-house IT | L24: ACT-06 Data Mapping Interviews | M24: ID-REG-002 | N24: GV-REG-007, PR-POL-003
A25: 24 | B25: W1 | C25: Understand | D25: Month 1 to 4 | E25: Track A: Governance build | F25: GV-POL-004 | G25: Personal Data Protection Policy | H25: Expected | I25: Specialist-guided | J25: Needs privacy expertise: PDPA lawful basis, DPIA, data subject rights. Needs interpretation of Thai cybersecurity, PDPA, or contract obligations. | K25: DPO or privacy counsel service / Legal counsel | L25: ACT-03 Legal and Regulatory Applicability Review; ACT-13 Policy Drafting and Stakeholder Review Cycle; ACT-14 Policy Approval and Communication | M25: GV-REG-001, GV-POL-001 | N25: GV-TPL-004, GV-PRC-005, GV-PRC-004, RS-PLB-003
A26: 25 | B26: W1 | C26: Understand | D26: Month 1 to 4 | E26: Track A: Governance build | F26: GV-REG-007 | G26: Record of Processing Activities (ROPA) | H26: Required | I26: Specialist-guided | J26: Needs privacy expertise: PDPA lawful basis, DPIA, data subject rights. | K26: DPO or privacy counsel service | L26: ACT-06 Data Mapping Interviews | M26: ID-REG-003 | N26: GV-TPL-002
A27: 26 | B27: W1 | C27: Understand | D27: Month 1 to 4 | E27: Track A: Governance build | F27: GV-TPL-002 | G27: Privacy Notice Template | H27: Required | I27: Specialist-guided | J27: Needs privacy expertise: PDPA lawful basis, DPIA, data subject rights. Needs interpretation of Thai cybersecurity, PDPA, or contract obligations. | K27: DPO or privacy counsel service / Legal counsel | L27: ACT-06 Data Mapping Interviews | M27: GV-REG-007
A28: 27 | B28: W1 | C28: Understand | D28: Month 1 to 4 | E28: Track A: Governance build | F28: GV-REG-009 | G28: Supplier Inventory and Criticality Register | H28: Expected | I28: IT-ready | J28: Template-driven: content is mostly factual or administrative. | K28: In-house IT | L28: ACT-16 Supplier Tiering Workshop | N28: GV-POL-006 | O28: GV-PRC-008
A29: 28 | B29: W1 | C29: Understand | D29: Month 1 to 4 | E29: Track A: Governance build | F29: ID-RPT-002 | G29: Business Impact Analysis (BIA) | H29: Expected | I29: Specialist-required | J29: Needs business continuity methodology (ISO 22301). Needs neutral facilitation of executive or cross-department decisions. | K29: Cybersecurity consultant (project) | L29: ACT-07 Business Impact Analysis (BIA) Interviews and Validation Workshop | M29: ID-REG-001, ID-REG-002 | N29: GV-STM-001, ID-REG-005, RC-POL-001, PR-STD-017, RC-PLN-001 | O29: RC-POL-001 | P29: BIA usually runs before the continuity policy is approved. Align it to RC-POL-001 when issued.
A30: 29 | B30: W1 | C30: Understand | D30: Month 1 to 4 | E30: Track A: Governance build | F30: GV-STM-001 | G30: Risk Appetite and Tolerance Statement | H30: Expected | I30: Specialist-required | J30: Needs neutral facilitation of executive or cross-department decisions. Needs risk methodology design and calibration skills. | K30: Cybersecurity consultant (project) | L30: ACT-08 Risk Appetite Workshop | M30: ID-RPT-002, GV-CHR-001 | N30: GV-POL-002
A31: 30 | B31: W1 | C31: Understand | D31: Month 1 to 4 | E31: Track A: Governance build | F31: GV-POL-002 | G31: Cybersecurity Risk Management Policy | H31: Expected | I31: Specialist-guided | J31: Needs risk methodology design and calibration skills. | K31: Cybersecurity consultant (project) / Security FTE | L31: ACT-13 Policy Drafting and Stakeholder Review Cycle; ACT-14 Policy Approval and Communication | M31: GV-POL-001, GV-STM-001 | N31: GV-PRC-001
A32: 31 | B32: W1 | C32: Understand | D32: Month 1 to 4 | E32: Track A: Governance build | F32: GV-PRC-001 | G32: Risk Assessment and Treatment Methodology | H32: Required | I32: Specialist-required | J32: Needs risk methodology design and calibration skills. | K32: Cybersecurity consultant (project) / Security FTE | L32: ACT-09 Risk Methodology Design and Calibration Session | M32: GV-POL-002 | N32: ID-REG-005, GV-FRM-001, ID-PRC-004
A33: 32 | B33: W1 | C33: Understand | D33: Month 1 to 4 | E33: Track A: Governance build | F33: ID-REG-005 | G33: IT and Cybersecurity Risk Register | H33: Required | I33: Specialist-required | J33: Needs risk methodology design and calibration skills. | K33: Cybersecurity consultant (project) / Security FTE | L33: ACT-10 Risk Assessment Workshops | M33: GV-PRC-001, ID-REG-001, ID-RPT-002 | N33: ID-RPT-003, ID-PLN-001, DE-STD-001
A34: 33 | B34: W1 | C34: Understand | D34: Month 1 to 4 | E34: Track A: Governance build | F34: ID-RPT-003 | G34: Cybersecurity Risk Assessment Report | H34: Required | I34: Specialist-required | J34: Needs risk methodology design and calibration skills. | K34: Cybersecurity consultant (project) / Security FTE | L34: ACT-10 Risk Assessment Workshops; ACT-11 Current State Assessment and CSF Profile Gap Analysis | M34: ID-REG-005 | N34: GV-STR-001
A35: 34 | B35: W1 | C35: Understand | D35: Month 1 to 4 | E35: Track B: Threat-driven quick wins (Day 0 to 90) | F35: RS-PLB-001 | G35: Ransomware Response Playbook | H35: Expected | I35: Specialist-required | J35: Needs incident handling and digital forensics experience. | K35: Incident response retainer / Cybersecurity consultant (project) | L35: ACT-17 Incident Response Readiness Workshop; ACT-20 Tabletop Exercise | M35: RS-PLN-001, PR-PRC-005 | O35: RS-PRC-001
A36: 35 | B36: W1 | C36: Understand | D36: Month 1 to 4 | E36: Track B: Threat-driven quick wins (Day 0 to 90) | F36: PR-STD-002 | G36: Privileged Access Management Standard | H36: Expected | I36: Specialist-guided | J36: Needs security architecture judgment to set technical requirements. | K36: In-house IT / Cybersecurity consultant (project) | L36: ACT-19 Identity and Privileged Access Review | M36: PR-STD-001 | N36: PR-FRM-002 | O36: PR-POL-001
A37: 36 | B37: W1 | C37: Understand | D37: Month 1 to 4 | E37: Track B: Threat-driven quick wins (Day 0 to 90) | F37: PR-STD-003 | G37: Remote Access Standard | H37: Expected | I37: Specialist-guided | J37: Needs security architecture judgment to set technical requirements. | K37: In-house IT / Cybersecurity consultant (project) | L37: ACT-19 Identity and Privileged Access Review | M37: PR-STD-001 | N37: PR-FRM-003 | O37: PR-POL-001
A38: 37 | B38: W1 | C38: Understand | D38: Month 1 to 4 | E38: Track B: Threat-driven quick wins (Day 0 to 90) | F38: PR-STD-012 | G38: Endpoint Protection Standard | H38: Expected | I38: Specialist-guided | J38: Needs security architecture judgment to set technical requirements. | K38: In-house IT / Managed Security Service Provider (MSSP) | M38: ID-REG-001 | N38: PR-REG-003
A39: 38 | B39: W2 | C39: Direct | D39: Month 3 to 7 | E39: Track A: Governance build | F39: GV-STR-001 | G39: Cybersecurity Strategy and Roadmap | H39: Required | I39: Specialist-guided | J39: Needs neutral facilitation of executive or cross-department decisions. | K39: Cybersecurity consultant (project) / Security FTE | L39: ACT-11 Current State Assessment and CSF Profile Gap Analysis; ACT-12 Strategy, Roadmap, and Budget Planning Session | M39: ID-RPT-003, GV-RPT-001 | N39: GV-PLN-001, GV-REG-008
A40: 39 | B40: W2 | C40: Direct | D40: Month 3 to 7 | E40: Track A: Governance build | F40: GV-PLN-001 | G40: Cybersecurity Budget and Resource Plan | H40: Expected | I40: Specialist-guided | J40: Needs neutral facilitation of executive or cross-department decisions. | K40: Security FTE / In-house IT | L40: ACT-12 Strategy, Roadmap, and Budget Planning Session | M40: GV-STR-001
A41: 40 | B41: W2 | C41: Direct | D41: Month 3 to 7 | E41: Track A: Governance build | F41: ID-PLN-001 | G41: Risk Treatment Plan | H41: Required | I41: Specialist-guided | J41: Needs risk methodology design and calibration skills. | K41: Security FTE / Cybersecurity consultant (project) | L41: ACT-10 Risk Assessment Workshops | M41: ID-REG-005 | N41: GV-REG-005
A42: 41 | B42: W2 | C42: Direct | D42: Month 3 to 7 | E42: Track A: Governance build | F42: GV-FRM-001 | G42: Risk Acceptance Form | H42: Expected | I42: IT-ready | J42: Template-driven: content is mostly factual or administrative. | K42: In-house IT | M42: GV-PRC-001
A43: 42 | B43: W2 | C43: Direct | D43: Month 3 to 7 | E43: Track A: Governance build | F43: GV-REG-005 | G43: Statement of Applicability (SoA) | H43: Required | I43: Specialist-required | J43: Needs risk methodology design and calibration skills. | K43: Cybersecurity consultant (project) / Security FTE | L43: ACT-11 Current State Assessment and CSF Profile Gap Analysis | M43: ID-PLN-001, GV-RPT-001 | P43: Only needed for ISO/IEC 27001 certification. Otherwise use the CSF Target Profile as the control selection record.
A44: 43 | B44: W2 | C44: Direct | D44: Month 3 to 7 | E44: Track A: Governance build | F44: GV-REG-006 | G44: CII Code of Practice Compliance Matrix | H44: Required | I44: Specialist-required | J44: Needs interpretation of Thai cybersecurity, PDPA, or contract obligations. | K44: Cybersecurity consultant (project) / Legal counsel | L44: ACT-03 Legal and Regulatory Applicability Review; ACT-11 Current State Assessment and CSF Profile Gap Analysis | M44: GV-REG-001
A45: 44 | B45: W2 | C45: Direct | D45: Month 3 to 7 | E45: Track A: Governance build | F45: GV-REG-008 | G45: Cybersecurity Metrics Catalog (KPI and KRI) | H45: Required | I45: Specialist-guided | J45: Needs risk methodology design and calibration skills. | K45: Security FTE / Cybersecurity consultant (project) | L45: ACT-12 Strategy, Roadmap, and Budget Planning Session | M45: GV-STR-001 | N45: GV-TPL-005
A46: 45 | B46: W2 | C46: Direct | D46: Month 3 to 7 | E46: Track A: Governance build | F46: GV-POL-003 | G46: Acceptable Use Policy | H46: Expected | I46: IT-ready | J46: Template-driven: content is mostly factual or administrative. | K46: In-house IT / Human Resources | L46: ACT-13 Policy Drafting and Stakeholder Review Cycle; ACT-14 Policy Approval and Communication | M46: GV-POL-001 | N46: PR-PLN-001, PR-STD-009, GV-POL-005
A47: 46 | B47: W2 | C47: Direct | D47: Month 3 to 7 | E47: Track A: Governance build | F47: PR-POL-001 | G47: Access Control Policy | H47: Expected | I47: Specialist-guided | J47: Needs security architecture judgment to set technical requirements. | K47: Security FTE / Cybersecurity consultant (project) | L47: ACT-13 Policy Drafting and Stakeholder Review Cycle; ACT-14 Policy Approval and Communication | M47: GV-POL-001 | N47: PR-PRC-001, PR-PRC-002
A48: 47 | B48: W2 | C48: Direct | D48: Month 3 to 7 | E48: Track A: Governance build | F48: PR-POL-003 | G48: Data Protection and Classification Policy | H48: Expected | I48: Specialist-guided | J48: Needs privacy expertise: PDPA lawful basis, DPIA, data subject rights. | K48: Security FTE / DPO or privacy counsel service | L48: ACT-13 Policy Drafting and Stakeholder Review Cycle; ACT-14 Policy Approval and Communication | M48: GV-POL-001, ID-REG-003 | N48: PR-STD-004, PR-STD-005, PR-STD-007
A49: 48 | B49: W2 | C49: Direct | D49: Month 3 to 7 | E49: Track A: Governance build | F49: GV-POL-006 | G49: Third-Party and Supply Chain Security Policy | H49: Expected | I49: Specialist-guided | J49: Needs vendor security assessment experience. | K49: Security FTE / Cybersecurity consultant (project) | L49: ACT-13 Policy Drafting and Stakeholder Review Cycle; ACT-14 Policy Approval and Communication | M49: GV-POL-001, GV-REG-009 | N49: PR-STD-014, GV-PRC-008, GV-STD-002, GV-STD-003
A50: 49 | B50: W2 | C50: Direct | D50: Month 3 to 7 | E50: Track A: Governance build | F50: RC-POL-001 | G50: Business Continuity Management Policy | H50: Expected | I50: Specialist-guided | J50: Needs business continuity methodology (ISO 22301). | K50: Cybersecurity consultant (project) / In-house IT | L50: ACT-13 Policy Drafting and Stakeholder Review Cycle; ACT-14 Policy Approval and Communication | M50: GV-CHR-001, ID-RPT-002
A51: 50 | B51: W2 | C51: Direct | D51: Month 3 to 7 | E51: Track A: Governance build | F51: PR-POL-002 | G51: Physical and Environmental Security Policy | H51: Expected | I51: IT-ready | J51: Template-driven: content is mostly factual or administrative. | K51: In-house IT | L51: ACT-13 Policy Drafting and Stakeholder Review Cycle; ACT-14 Policy Approval and Communication | M51: GV-POL-001 | N51: PR-PRC-003
A52: 51 | B52: W2 | C52: Direct | D52: Month 3 to 7 | E52: Track A: Governance build | F52: GV-STD-001 | G52: Human Resources Security Standard | H52: Expected | I52: IT-ready | J52: HR process: HR owns it and security supplies the content. | K52: Human Resources | L52: ACT-13 Policy Drafting and Stakeholder Review Cycle | M52: GV-POL-001 | N52: GV-FRM-002, GV-FRM-003
A53: 52 | B53: W2 | C53: Direct | D53: Month 3 to 7 | E53: Track A: Governance build | F53: GV-FRM-002 | G53: Confidentiality and Non-Disclosure Agreement | H53: Expected | I53: Specialist-guided | J53: Needs interpretation of Thai cybersecurity, PDPA, or contract obligations. | K53: Legal counsel | M53: GV-STD-001
A54: 53 | B54: W2 | C54: Direct | D54: Month 3 to 7 | E54: Track A: Governance build | F54: GV-FRM-003 | G54: Employee Offboarding Security Checklist | H54: Expected | I54: IT-ready | J54: HR process: HR owns it and security supplies the content. | K54: Human Resources / In-house IT | M54: GV-STD-001
A55: 54 | B55: W2 | C55: Direct | D55: Month 3 to 7 | E55: Track A: Governance build | F55: PR-PLN-001 | G55: Security Awareness and Training Program | H55: Expected | I55: IT-ready | J55: Template-driven: content is mostly factual or administrative. | K55: In-house IT / Human Resources | L55: ACT-23 Training Needs Analysis and Awareness Planning | M55: GV-POL-003 | N55: PR-REG-002, PR-REC-002, PR-PRC-004
A56: 55 | B56: W2 | C56: Direct | D56: Month 3 to 7 | E56: Track A: Governance build | F56: GV-PRC-003 | G56: Policy Exception Management Procedure | H56: Expected | I56: IT-ready | J56: Template-driven: content is mostly factual or administrative. | K56: In-house IT | M56: GV-POL-001 | N56: GV-FRM-004, GV-REG-004
A57: 56 | B57: W2 | C57: Direct | D57: Month 3 to 7 | E57: Track A: Governance build | F57: GV-FRM-004 | G57: Policy Exception Request Form | H57: Expected | I57: IT-ready | J57: Template-driven: content is mostly factual or administrative. | K57: In-house IT | M57: GV-PRC-003
A58: 57 | B58: W2 | C58: Direct | D58: Month 3 to 7 | E58: Track A: Governance build | F58: GV-REG-004 | G58: Policy Exception Register | H58: Expected | I58: IT-ready | J58: Template-driven: content is mostly factual or administrative. | K58: In-house IT | M58: GV-PRC-003
A59: 58 | B59: W2 | C59: Direct | D59: Month 3 to 7 | E59: Track A: Governance build | F59: GV-TPL-004 | G59: Data Processing Agreement Template | H59: Required | I59: Specialist-guided | J59: Needs privacy expertise: PDPA lawful basis, DPIA, data subject rights. Needs interpretation of Thai cybersecurity, PDPA, or contract obligations. | K59: Legal counsel / DPO or privacy counsel service | M59: GV-POL-004 | O59: GV-STD-002
A60: 59 | B60: W2 | C60: Direct | D60: Month 3 to 7 | E60: Track A: Governance build | F60: GV-PRC-005 | G60: Data Subject Rights Request Procedure | H60: Expected | I60: Specialist-guided | J60: Needs privacy expertise: PDPA lawful basis, DPIA, data subject rights. | K60: DPO or privacy counsel service | L60: ACT-13 Policy Drafting and Stakeholder Review Cycle | M60: GV-POL-004 | N60: GV-FRM-005
A61: 60 | B61: W2 | C61: Direct | D61: Month 3 to 7 | E61: Track A: Governance build | F61: GV-FRM-005 | G61: Data Subject Request Form | H61: Expected | I61: IT-ready | J61: Template-driven: content is mostly factual or administrative. | K61: In-house IT | M61: GV-PRC-005
A62: 61 | B62: W2 | C62: Direct | D62: Month 3 to 7 | E62: Track A: Governance build | F62: GV-PRC-004 | G62: Data Protection Impact Assessment (DPIA) Procedure | H62: Expected | I62: Specialist-guided | J62: Needs privacy expertise: PDPA lawful basis, DPIA, data subject rights. | K62: DPO or privacy counsel service | L62: ACT-13 Policy Drafting and Stakeholder Review Cycle | M62: GV-POL-004 | N62: GV-TPL-003
A63: 62 | B63: W2 | C63: Direct | D63: Month 3 to 7 | E63: Track A: Governance build | F63: GV-TPL-003 | G63: DPIA Template | H63: Expected | I63: Specialist-guided | J63: Needs privacy expertise: PDPA lawful basis, DPIA, data subject rights. | K63: DPO or privacy counsel service | L63: ACT-27 Data Protection Impact Assessment (DPIA) Workshop | M63: GV-PRC-004
A64: 63 | B64: W3 | C64: Standardize | D64: Month 6 to 12 | E64: Track A: Governance build | F64: ID-PRC-001 | G64: Asset Lifecycle Management Procedure | H64: Expected | I64: IT-ready | J64: Template-driven: content is mostly factual or administrative. Operational: IT runs it day to day once the parent standard exists. | K64: In-house IT | M64: ID-STD-001 | N64: ID-FRM-001
A65: 64 | B65: W3 | C65: Standardize | D65: Month 6 to 12 | E65: Track A: Governance build | F65: ID-FRM-001 | G65: Media Sanitization and Disposal Record | H65: Expected | I65: IT-ready | J65: Template-driven: content is mostly factual or administrative. | K65: In-house IT | M65: ID-PRC-001
A66: 65 | B66: W3 | C66: Standardize | D66: Month 6 to 12 | E66: Track A: Governance build | F66: ID-STD-002 | G66: Vulnerability Scanning and Remediation Standard | H66: Expected | I66: Specialist-guided | J66: Needs security architecture judgment to set technical requirements. | K66: Security FTE / Cybersecurity consultant (project) | L66: ACT-26 Vulnerability Scanning and Penetration Test Scoping | M66: GV-POL-001 | N66: ID-PRC-002, ID-PRC-003, PR-PRC-007
A67: 66 | B67: W3 | C67: Standardize | D67: Month 6 to 12 | E67: Track A: Governance build | F67: ID-PRC-002 | G67: Vulnerability Management Procedure | H67: Expected | I67: Specialist-guided | J67: Needs security architecture judgment to set technical requirements. | K67: Security FTE / Managed Security Service Provider (MSSP) | L67: ACT-26 Vulnerability Scanning and Penetration Test Scoping | M67: ID-STD-002 | N67: ID-REG-006, ID-PRC-005
A68: 67 | B68: W3 | C68: Standardize | D68: Month 6 to 12 | E68: Track A: Governance build | F68: ID-REG-006 | G68: Vulnerability Remediation Tracker | H68: Expected | I68: IT-ready | J68: Operational: IT runs it day to day once the parent standard exists. | K68: In-house IT | M68: ID-PRC-002
A69: 68 | B69: W3 | C69: Standardize | D69: Month 6 to 12 | E69: Track A: Governance build | F69: ID-PRC-003 | G69: Penetration Testing Procedure | H69: Expected | I69: Specialist-required | J69: Needs experienced offensive security testers, preferably certified. | K69: Cybersecurity consultant (project) | L69: ACT-26 Vulnerability Scanning and Penetration Test Scoping | M69: ID-STD-002 | N69: ID-FRM-002
A70: 69 | B70: W3 | C70: Standardize | D70: Month 6 to 12 | E70: Track A: Governance build | F70: ID-FRM-002 | G70: Penetration Test Authorization and Rules of Engagement | H70: Expected | I70: Specialist-required | J70: Needs experienced offensive security testers, preferably certified. Needs interpretation of Thai cybersecurity, PDPA, or contract obligations. | K70: Cybersecurity consultant (project) / Legal counsel | L70: ACT-26 Vulnerability Scanning and Penetration Test Scoping | M70: ID-PRC-003
A71: 70 | B71: W3 | C71: Standardize | D71: Month 6 to 12 | E71: Track A: Governance build | F71: PR-STD-004 | G71: Information Classification and Handling Standard | H71: Expected | I71: Specialist-guided | J71: Needs privacy expertise: PDPA lawful basis, DPIA, data subject rights. | K71: Security FTE / DPO or privacy counsel service | L71: ACT-13 Policy Drafting and Stakeholder Review Cycle | M71: PR-POL-003 | N71: PR-STD-008
A72: 71 | B72: W3 | C72: Standardize | D72: Month 6 to 12 | E72: Track A: Governance build | F72: PR-STD-005 | G72: Cryptography and Key Management Standard | H72: Expected | I72: Specialist-required | J72: Needs security architecture judgment to set technical requirements. | K72: Security FTE / Cybersecurity consultant (project) | L72: ACT-13 Policy Drafting and Stakeholder Review Cycle | M72: PR-POL-003
A73: 72 | B73: W3 | C73: Standardize | D73: Month 6 to 12 | E73: Track A: Governance build | F73: PR-STD-007 | G73: Data Retention and Disposal Standard | H73: Expected | I73: Specialist-guided | J73: Needs privacy expertise: PDPA lawful basis, DPIA, data subject rights. Needs interpretation of Thai cybersecurity, PDPA, or contract obligations. | K73: DPO or privacy counsel service / Legal counsel | L73: ACT-13 Policy Drafting and Stakeholder Review Cycle | M73: PR-POL-003
A74: 73 | B74: W3 | C74: Standardize | D74: Month 6 to 12 | E74: Track A: Governance build | F74: PR-STD-009 | G74: Mobile Device and BYOD Standard | H74: Expected | I74: Specialist-guided | J74: Needs security architecture judgment to set technical requirements. | K74: In-house IT / Cybersecurity consultant (project) | L74: ACT-13 Policy Drafting and Stakeholder Review Cycle | M74: GV-POL-003
A75: 74 | B75: W3 | C75: Standardize | D75: Month 6 to 12 | E75: Track A: Governance build | F75: PR-STD-010 | G75: Secure Configuration Baseline Standard | H75: Expected | I75: Specialist-guided | J75: Needs security architecture judgment to set technical requirements. | K75: In-house IT / Cybersecurity consultant (project) | L75: ACT-15 Technical Baseline Review | M75: ID-REG-001
A76: 75 | B76: W3 | C76: Standardize | D76: Month 6 to 12 | E76: Track A: Governance build | F76: PR-PRC-006 | G76: Change Management Procedure | H76: Expected | I76: IT-ready | J76: Template-driven: content is mostly factual or administrative. Operational: IT runs it day to day once the parent standard exists. | K76: In-house IT | L76: ACT-28 Change Advisory Board (CAB) Setup | M76: GV-POL-001 | N76: PR-FRM-005
A77: 76 | B77: W3 | C77: Standardize | D77: Month 6 to 12 | E77: Track A: Governance build | F77: PR-FRM-005 | G77: Change Request Form | H77: Expected | I77: IT-ready | J77: Template-driven: content is mostly factual or administrative. | K77: In-house IT | L77: ACT-28 Change Advisory Board (CAB) Setup | M77: PR-PRC-006
A78: 77 | B78: W3 | C78: Standardize | D78: Month 6 to 12 | E78: Track A: Governance build | F78: PR-PRC-007 | G78: Patch Management Procedure | H78: Expected | I78: IT-ready | J78: Operational: IT runs it day to day once the parent standard exists. | K78: In-house IT | M78: ID-STD-002
A79: 78 | B79: W3 | C79: Standardize | D79: Month 6 to 12 | E79: Track A: Governance build | F79: PR-STD-011 | G79: Logging Standard | H79: Expected | I79: Specialist-guided | J79: Needs security architecture judgment to set technical requirements. Needs interpretation of Thai cybersecurity, PDPA, or contract obligations. | K79: Security FTE / Cybersecurity consultant (project) | L79: ACT-22 Security Monitoring Design Session | M79: GV-REG-001 | N79: DE-STD-001
A80: 79 | B80: W3 | C80: Standardize | D80: Month 6 to 12 | E80: Track A: Governance build | F80: PR-REG-003 | G80: Approved Software Register | H80: Expected | I80: IT-ready | J80: Template-driven: content is mostly factual or administrative. Operational: IT runs it day to day once the parent standard exists. | K80: In-house IT | M80: PR-STD-012
A81: 80 | B81: W3 | C81: Standardize | D81: Month 6 to 12 | E81: Track A: Governance build | F81: PR-STD-013 | G81: Secure Software Development Standard | H81: Expected | I81: Specialist-required | J81: Needs security architecture judgment to set technical requirements. | K81: Cybersecurity consultant (project) / Security FTE | L81: ACT-13 Policy Drafting and Stakeholder Review Cycle | M81: GV-POL-001
A82: 81 | B82: W3 | C82: Standardize | D82: Month 6 to 12 | E82: Track A: Governance build | F82: PR-STD-014 | G82: Cloud Security Standard | H82: Expected | I82: Specialist-required | J82: Needs security architecture judgment to set technical requirements. | K82: Cybersecurity consultant (project) / Security FTE | L82: ACT-15 Technical Baseline Review | M82: GV-POL-006
A83: 82 | B83: W3 | C83: Standardize | D83: Month 6 to 12 | E83: Track A: Governance build | F83: PR-STD-016 | G83: Network Security Standard | H83: Expected | I83: Specialist-guided | J83: Needs security architecture judgment to set technical requirements. | K83: In-house IT / Cybersecurity consultant (project) | L83: ACT-15 Technical Baseline Review | M83: ID-RPT-001 | N83: PR-PRC-008
A84: 83 | B84: W3 | C84: Standardize | D84: Month 6 to 12 | E84: Track A: Governance build | F84: PR-PRC-008 | G84: Firewall Rule Management Procedure | H84: Expected | I84: IT-ready | J84: Operational: IT runs it day to day once the parent standard exists. | K84: In-house IT | L84: ACT-28 Change Advisory Board (CAB) Setup | M84: PR-STD-016 | N84: PR-FRM-006
A85: 84 | B85: W3 | C85: Standardize | D85: Month 6 to 12 | E85: Track A: Governance build | F85: PR-FRM-006 | G85: Firewall Rule Change Request Form | H85: Expected | I85: IT-ready | J85: Template-driven: content is mostly factual or administrative. | K85: In-house IT | M85: PR-PRC-008
A86: 85 | B86: W3 | C86: Standardize | D86: Month 6 to 12 | E86: Track A: Governance build | F86: PR-STD-017 | G86: Technology Resilience and Capacity Standard | H86: Expected | I86: Specialist-guided | J86: Needs security architecture judgment to set technical requirements. Needs business continuity methodology (ISO 22301). | K86: In-house IT / Cybersecurity consultant (project) | M86: ID-RPT-002
A87: 86 | B87: W3 | C87: Standardize | D87: Month 6 to 12 | E87: Track A: Governance build | F87: PR-PRC-001 | G87: User Access Management Procedure | H87: Expected | I87: IT-ready | J87: Template-driven: content is mostly factual or administrative. Operational: IT runs it day to day once the parent standard exists. | K87: In-house IT | M87: PR-POL-001 | N87: PR-FRM-001
A88: 87 | B88: W3 | C88: Standardize | D88: Month 6 to 12 | E88: Track A: Governance build | F88: PR-FRM-001 | G88: User Access Request Form | H88: Expected | I88: IT-ready | J88: Template-driven: content is mostly factual or administrative. | K88: In-house IT | M88: PR-PRC-001
A89: 88 | B89: W3 | C89: Standardize | D89: Month 6 to 12 | E89: Track A: Governance build | F89: PR-FRM-002 | G89: Privileged Access Request Form | H89: Expected | I89: IT-ready | J89: Template-driven: content is mostly factual or administrative. | K89: In-house IT | M89: PR-STD-002
A90: 89 | B90: W3 | C90: Standardize | D90: Month 6 to 12 | E90: Track A: Governance build | F90: PR-FRM-003 | G90: Third-Party Remote Access Request Form | H90: Expected | I90: IT-ready | J90: Template-driven: content is mostly factual or administrative. | K90: In-house IT | M90: PR-STD-003
A91: 90 | B91: W3 | C91: Standardize | D91: Month 6 to 12 | E91: Track A: Governance build | F91: PR-PRC-002 | G91: User Access Review Procedure | H91: Expected | I91: IT-ready | J91: Operational: IT runs it day to day once the parent standard exists. | K91: In-house IT | M91: PR-POL-001 | N91: PR-REC-001
A92: 91 | B92: W3 | C92: Standardize | D92: Month 6 to 12 | E92: Track A: Governance build | F92: PR-PRC-003 | G92: Physical Access Management Procedure | H92: Expected | I92: IT-ready | J92: Template-driven: content is mostly factual or administrative. | K92: In-house IT | M92: PR-POL-002 | N92: PR-FRM-004
A93: 92 | B93: W3 | C93: Standardize | D93: Month 6 to 12 | E93: Track A: Governance build | F93: PR-FRM-004 | G93: Secure Area Access and Visitor Log | H93: Expected | I93: IT-ready | J93: Template-driven: content is mostly factual or administrative. | K93: In-house IT | M93: PR-PRC-003
A94: 93 | B94: W3 | C94: Standardize | D94: Month 6 to 12 | E94: Track A: Governance build | F94: PR-REG-002 | G94: Role-Based Training and Skills Matrix | H94: Required | I94: IT-ready | J94: HR process: HR owns it and security supplies the content. | K94: In-house IT / Human Resources | L94: ACT-23 Training Needs Analysis and Awareness Planning | M94: PR-PLN-001
A95: 94 | B95: W3 | C95: Standardize | D95: Month 6 to 12 | E95: Track A: Governance build | F95: GV-PRC-008 | G95: Third-Party Risk Management Procedure | H95: Expected | I95: Specialist-guided | J95: Needs vendor security assessment experience. | K95: Security FTE / Cybersecurity consultant (project) | L95: ACT-16 Supplier Tiering Workshop | M95: GV-POL-006 | N95: GV-FRM-006, GV-FRM-007
A96: 95 | B96: W3 | C96: Standardize | D96: Month 6 to 12 | E96: Track A: Governance build | F96: GV-STD-002 | G96: Supplier Security Requirements Standard | H96: Expected | I96: Specialist-guided | J96: Needs vendor security assessment experience. Needs interpretation of Thai cybersecurity, PDPA, or contract obligations. | K96: Security FTE / Legal counsel | L96: ACT-16 Supplier Tiering Workshop | M96: GV-POL-006
A97: 96 | B97: W3 | C97: Standardize | D97: Month 6 to 12 | E97: Track A: Governance build | F97: GV-FRM-006 | G97: Vendor Security Assessment Questionnaire | H97: Expected | I97: Specialist-guided | J97: Needs vendor security assessment experience. | K97: Security FTE / Cybersecurity consultant (project) | L97: ACT-16 Supplier Tiering Workshop | M97: GV-PRC-008
A98: 97 | B98: W3 | C98: Standardize | D98: Month 6 to 12 | E98: Track A: Governance build | F98: GV-STD-003 | G98: Secure Acquisition Standard | H98: Expected | I98: Specialist-guided | J98: Needs security architecture judgment to set technical requirements. Needs vendor security assessment experience. | K98: Security FTE / Cybersecurity consultant (project) | M98: GV-POL-006
A99: 98 | B99: W3 | C99: Standardize | D99: Month 6 to 12 | E99: Track A: Governance build | F99: GV-TPL-005 | G99: Board Cybersecurity Report Template | H99: Expected | I99: Specialist-guided | J99: Needs neutral facilitation of executive or cross-department decisions. | K99: Security FTE / Cybersecurity consultant (project) | M99: GV-REG-008
A100: 99 | B100: W3 | C100: Standardize | D100: Month 6 to 12 | E100: Track A: Governance build | F100: DE-STD-001 | G100: Security Monitoring Standard | H100: Expected | I100: Specialist-required | J100: Needs detection engineering and security monitoring expertise. | K100: Cybersecurity consultant (project) / Managed Security Service Provider (MSSP) | L100: ACT-22 Security Monitoring Design Session | M100: PR-STD-011, ID-REG-005 | N100: DE-PRC-001, DE-REG-001, DE-GDL-001
...

Sheet Prerequisite Activities
A1: Activity ID | B1: Activity (EN) | C1: Activity (TH) | D1: Purpose | E1: Agenda | F1: Participants | G1: Inputs | H1: Duration | I1: Frequency | J1: Facilitator Capability | K1: First Time in This Organization | L1: Feeds Documents
A2: ACT-01 | B2: Executive Kickoff and Mandate Meeting | C2: ประชุม Kickoff ผู้บริหารและการมอบอำนาจหน้าที่ | D2: Secure executive sponsorship, agree why the organization is formalizing cybersecurity, and confirm who owns the program. | E2: 1. Trigger and business case: incidents in the sector, legal duties (CII, PDPA), customer demands 2. Program objectives for the first 12 months 3. Who sponsors, who owns, and who runs the program 4. Reporting line of the security lead and escalation route to the Board 5. Decisions needed: approve charter drafting, name the program owner, set the next meeting | F2: Chief Executive Officer (CEO), Chief Information Officer (CIO), Chief Financial Officer (CFO), Chief Information Security Officer (CISO) or Security Manager, Chief Risk Officer (CRO) or Enterprise Risk Manager, Legal Counsel | G2: Sector incident news, legal applicability notes | H2: 90 minutes | I2: One time | J2: Specialist-guided | K2: Keep it short and decision focused. Bring one page with three decisions only. Without a named sponsor, every later document will stall at approval. | L2: GV-CHR-001
A3: ACT-02 | B3: Governance Structure and RACI Workshop | C3: Workshop โครงสร้างการกำกับดูแลและ RACI | D3: Design the steering committee, define roles across IT, security, privacy, risk, and audit, and agree a Responsible, Accountable, Consulted, Informed (RACI) matrix. | E3: 1. Current state: who does security work today, formally or informally 2. Steering committee membership, chair, quorum, and meeting frequency 3. Separation of duties: security versus IT operations versus internal audit 4. RACI for the top 15 security activities 5. Gaps that need a new role, a part-time assignment, or an external provider | F3: Chief Information Officer (CIO), Chief Information Security Officer (CISO) or Security Manager, Human Resources Director, Data Protection Officer (DPO), Chief Risk Officer (CRO) or Enterprise Risk Manager, Head of Internal Audit | G3: Organization chart, current job descriptions | H3: Half day | I3: One time, then annual review | J3: Specialist-guided | K3: Map real work before drawing boxes. A common trap is naming the IT Manager as both the person who operates systems and the person who checks them. | L3: GV-CHR-001, GV-CHR-002, GV-REG-003
A4: ACT-03 | B4: Legal and Regulatory Applicability Review | C4: การทบทวนกฎหมายและกฎระเบียบที่บังคับใช้ | D4: Confirm which laws, regulator notifications, and contracts apply, and translate each into concrete obligations and owners. | E4: 1. Is the organization a Critical Information Infrastructure (CII) operator under the Cybersecurity Act B.E. 2562 2. Personal data processed and whether sensitive data under PDPA s.26 is involved 3. Computer Crime Act duties if the organization provides network access to others 4. Sector regulator rules and key customer or partner contract clauses 5. Obligation list with owner, evidence, and deadline | F4: Legal Counsel, Chief Information Security Officer (CISO) or Security Manager, Data Protection Officer (DPO), Chief Information Officer (CIO) | G4: Laws and notifications, key contracts, regulator letters | H4: 2 to 3 working sessions | I4: One time, then semiannual update | J4: Specialist-required | K4: Thai cybersecurity notifications change often. Have legal counsel or a specialist consultant confirm current CII and PDPC requirements before writing obligations into policy. | L4: GV-REG-001, GV-POL-001, GV-REG-006, GV-POL-004, RS-PRC-003
A5: ACT-04 | B5: Scope and Organizational Context Workshop | C5: Workshop ขอบเขตและบริบทองค์กร | D5: Agree what the security program covers: sites, services, systems, interfaces, and stakeholders. | E5: 1. Critical services and the systems behind them 2. Sites, cloud services, and outsourced functions in and out of scope 3. Internal and external stakeholders and their expectations 4. Interfaces and dependencies with third parties 5. Draft scope statement and exclusions with justification | F5: Chief Information Security Officer (CISO) or Security Manager, Chief Information Officer (CIO), Chief Risk Officer (CRO) or Enterprise Risk Manager, System Owner | G5: Service catalog, system list, legal obligation list | H5: Half day | I5: One time, then annual review | J5: Specialist-guided | K5: Start narrow if resources are thin, such as the critical services only, and widen the scope each year. | L5: GV-RPT-001, GV-REG-002
A6: ACT-05 | B6: Asset Discovery and Inventory Reconciliation | C6: การสำรวจและกระทบยอดทะเบียนทรัพย์สิน | D6: Build a trusted inventory of hardware, software, cloud services, and data by comparing several sources. | E6: 1. Collect sources: network scan, endpoint agent, directory service, finance asset register, purchase records 2. Reconcile differences and identify unknown or unmanaged devices 3. Assign an owner and criticality to each asset 4. Agree the system of record and the update trigger (purchase, change, disposal) | F6: IT Infrastructure Manager, System Owner, Chief Financial Officer (CFO), Facilities Manager | G6: Scan results, directory export, finance register | H6: 2 to 6 weeks | I6: Initial build, then continuous | J6: IT-ready | K6: IT can run this alone. Do not wait for a perfect list; 90 percent coverage with owners is enough to start risk assessment. | L6: ID-REG-001, ID-REG-002, ID-RPT-001, ID-REG-004
A7: ACT-06 | B7: Data Mapping Interviews | C7: การสัมภาษณ์เพื่อจัดทำแผนผังข้อมูล | D7: Find out what personal and sensitive data each department collects, why, where it is stored, and who receives it. | E7: 1. Processing activities per department and their purpose 2. Lawful basis for each activity under PDPA 3. Systems, storage locations, and retention period 4. Transfers to processors and cross-border transfers 5. Follow-up items: missing consent, missing contract, excessive retention | F7: Data Protection Officer (DPO), System Owner, Legal Counsel, IT Infrastructure Manager | G7: Department list, forms and systems used to collect data | H7: 45 to 60 minutes per department | I7: Initial, then annual refresh | J7: Specialist-guided | K7: Use a short questionnaire before each interview. Lawful basis decisions need privacy counsel or a DPO service if no one in-house has PDPA experience. | L7: GV-REG-007, GV-TPL-002, ID-REG-003
A8: ACT-07 | B8: Business Impact Analysis (BIA) Interviews and Validation Workshop | C8: การสัมภาษณ์และ Workshop ยืนยันผลการวิเคราะห์ผลกระทบทางธุรกิจ (BIA) | D8: Determine how long each critical service can be down, how much data it can lose, and which systems and suppliers it depends on. | E8: 1. Impact over time: 1 hour, 4 hours, 1 day, 3 days (safety, financial, legal, reputation) 2. Maximum tolerable downtime, Recovery Time Objective (RTO), and Recovery Point Objective (RPO) per service 3. Dependencies: systems, people, suppliers, facilities 4. Manual workarounds and how long they can run 5. Validation workshop: management confirms RTO and RPO and accepts the cost implications | F8: Business Continuity Management (BCM) Coordinator, System Owner, Chief Information Officer (CIO), Chief Financial Officer (CFO), Risk Owner | G8: Service list, asset inventory, incident history | H8: 1 to 2 hours per service, plus a 2 hour validation workshop | I8: Annual | J8: Specialist-required | K8: Business owners tend to say every service needs zero downtime. A facilitator experienced in ISO 22301 must challenge the numbers and show the cost of each RTO. | L8: ID-RPT-002, RC-PLN-001
A9: ACT-08 | B9: Risk Appetite Workshop | C9: Workshop ระดับความเสี่ยงที่ยอมรับได้ | D9: Have executives state how much cybersecurity risk the organization will accept, in measurable terms. | E9: 1. Recap of top business objectives and recent sector incidents 2. Appetite by risk area: service disruption, data breach, regulatory breach, fraud 3. Tolerance thresholds and Key Risk Indicators (KRI) that trigger escalation 4. Who may accept which level of risk 5. Approval route to the Board or its committee | F9: Chief Executive Officer (CEO), Chief Financial Officer (CFO), Chief Information Officer (CIO), Chief Risk Officer (CRO) or Enterprise Risk Manager, Chief Information Security Officer (CISO) or Security Manager, Board of Directors | G9: Enterprise risk framework, BIA results | H9: 2 hours | I9: Annual | J9: Specialist-required | K9: Executives rarely state appetite unprompted. Prepare scenario cards with impact in baht and hours of downtime, then ask which ones they would accept. | L9: GV-STM-001
A10: ACT-09 | B10: Risk Methodology Design and Calibration Session | C10: การออกแบบและปรับเทียบวิธีการประเมินความเสี่ยง | D10: Define the likelihood and impact scales, risk matrix, and treatment rules, aligned with enterprise risk management and NIST SP 800-30. | E10: 1. Align scales with the enterprise risk framework 2. Impact criteria: patient or customer safety, financial, legal, operational, reputation 3. Likelihood criteria tied to threat and control evidence 4. Treatment options and acceptance authority per risk level 5. Trial run on three known risks to calibrate scoring | F10: Chief Information Security Officer (CISO) or Security Manager, Chief Risk Officer (CRO) or Enterprise Risk Manager, Head of Internal Audit | G10: Enterprise risk framework, risk appetite statement | H10: Two 2 hour sessions | I10: One time, then annual review | J10: Specialist-required | K10: This is the most common place where IT-only teams go wrong: scales that do not match enterprise risk, or every risk scored High. Engage a specialist for the first cycle. | L10: GV-PRC-001
A11: ACT-10 | B11: Risk Assessment Workshops | C11: Workshop ประเมินความเสี่ยง | D11: Identify, analyze, and evaluate cybersecurity risks per critical service or system using the agreed methodology. | E11: 1. Threat scenarios relevant to the service (ransomware, data theft, vendor compromise, insider) 2. Existing controls and their evidence 3. Likelihood and impact scoring with justification 4. Risk owner confirmation 5. Initial treatment direction | F11: Chief Information Security Officer (CISO) or Security Manager, Risk Owner, System Owner, IT Infrastructure Manager | G11: Asset inventory, BIA, vulnerability results, threat intelligence | H11: 2 hours per service or system group | I11: Annual and on major change | J11: Specialist-required | K11: Threat scenarios and control effectiveness need security judgment. IT can supply facts, but a specialist should lead scoring in the first year. | L11: ID-REG-005, ID-PLN-001, ID-RPT-003
A12: ACT-11 | B12: Current State Assessment and CSF Profile Gap Analysis | C12: การประเมินสภาพปัจจุบันและวิเคราะห์ช่องว่างตาม CSF Profile | D12: Measure current practice against NIST CSF 2.0, set a Target Profile, and list the gaps that drive the roadmap. | E12: 1. Interviews and evidence review per CSF Category 2. Current Profile and Tier rating 3. Target Profile agreed with management, informed by risk appetite and legal duties 4. Gap list with priority and effort 5. Read-out to the steering committee | F12: Chief Information Security Officer (CISO) or Security Manager, Chief Information Officer (CIO), System Owner, Head of Internal Audit | G12: Existing policies, technical evidence, prior audit findings | H12: 3 to 6 weeks | I12: Annual | J12: Specialist-required | K12: An independent assessor gives a more credible baseline than self-assessment, and the result is easier to defend in a budget request. | L12: GV-STR-001, GV-REG-005, GV-REG-006, ID-RPT-003
... A30: ACT-29 | B30: Post-Incident and Lessons Learned Review | C30: การทบทวนหลังเหตุการณ์และบทเรียนที่ได้รับ | D30: Review an incident or exercise without blame, find root causes, and track improvements. | E30: 1. Timeline reconstruction 2. What worked and what did not 3. Root causes: people, process, technology 4. Improvement actions with owners and due dates 5. Updates needed to plans, playbooks, and the risk register | F30: Chief Information Security Officer (CISO) or Security Manager, IT Infrastructure Manager, System Owner, Business Continuity Management (BCM) Coordinator | G30: Incident record, exercise report | H30: 1 to 2 hours | I30: After each major incident or exercise | J30: Specialist-guided | K30: Hold the review within two weeks while memory is fresh, and feed actions into the corrective action register. | L30: ID-TPL-001

Sheet Process Flows
A1: Process Flow | B1: Step | C1: Step Label | D1: Document ID | E1: Title | F1: Flow Description
A2: Risk management cycle | B2: 1 | C2: Set appetite | D2: GV-STM-001 | E2: Risk Appetite and Tolerance Statement | F2: From appetite to Board reporting: how risk decisions are made and evidenced.
A3: Risk management cycle | B3: 2 | C3: Set rules | D3: GV-POL-002 | E3: Cybersecurity Risk Management Policy | F3: From appetite to Board reporting: how risk decisions are made and evidenced.
A4: Risk management cycle | B4: 3 | C4: Define method | D4: GV-PRC-001 | E4: Risk Assessment and Treatment Methodology | F4: From appetite to Board reporting: how risk decisions are made and evidenced.
A5: Risk management cycle | B5: 4 | C5: Record risks | D5: ID-REG-005 | E5: IT and Cybersecurity Risk Register | F5: From appetite to Board reporting: how risk decisions are made and evidenced.
A6: Risk management cycle | B6: 5 | C6: Report assessment | D6: ID-RPT-003 | E6: Cybersecurity Risk Assessment Report | F6: From appetite to Board reporting: how risk decisions are made and evidenced.
A7: Risk management cycle | B7: 6 | C7: Plan treatment | D7: ID-PLN-001 | E7: Risk Treatment Plan | F7: From appetite to Board reporting: how risk decisions are made and evidenced.
A8: Risk management cycle | B8: 7 | C8: Accept residual risk | D8: GV-FRM-001 | E8: Risk Acceptance Form | F8: From appetite to Board reporting: how risk decisions are made and evidenced.
A9: Risk management cycle | B9: 8 | C9: Measure | D9: GV-REG-008 | E9: Cybersecurity Metrics Catalog (KPI and KRI) | F9: From appetite to Board reporting: how risk decisions are made and evidenced.
A10: Risk management cycle | B10: 9 | C10: Report to Board | D10: GV-TPL-005 | E10: Board Cybersecurity Report Template | F10: From appetite to Board reporting: how risk decisions are made and evidenced.
A11: User access lifecycle | B11: 1 | C11: Set rules | D11: PR-POL-001 | E11: Access Control Policy | F11: Request, approve, provision, review, and remove access.
A12: User access lifecycle | B12: 2 | C12: Set authentication | D12: PR-STD-001 | E12: Identity and Authentication Standard | F12: Request, approve, provision, review, and remove access.
A13: User access lifecycle | B13: 3 | C13: Manage access | D13: PR-PRC-001 | E13: User Access Management Procedure | F13: Request, approve, provision, review, and remove access.
... A92: Policy lifecycle and exceptions | B92: 5 | C92: Register exception | D92: GV-REG-004 | E92: Policy Exception Register | F92: Write, approve, publish, and grant controlled exceptions.

Sheet CSF Traceability
A1: Subcategory | B1: Function | C1: Category | D1: Outcome (paraphrased) | E1: Outcome (TH, unofficial) | F1: Document Count | G1: T0 and T1 (Direction) | H1: T2 (Standards) | I1: T3 (Procedures and Plans) | J1: T4 (Evidence)
A2: GV.OC-01 | B2: Govern | C2: Organizational Context | D2: Organizational mission is understood and informs cybersecurity risk management | E2: เข้าใจพันธกิจขององค์กร และนำมาใช้กำหนดการบริหารความเสี่ยงด้านไซเบอร์ | F2: 3 | G2: GV-CHR-001, GV-STR-001 | J2: GV-RPT-001
A3: GV.OC-02 | B3: Govern | C3: Organizational Context | D3: Internal and external stakeholders and their cybersecurity expectations are understood | E3: เข้าใจผู้มีส่วนได้ส่วนเสียภายในและภายนอก และความคาดหวังด้านไซเบอร์ของแต่ละฝ่าย | F3: 2 | J3: GV-RPT-001, GV-REG-002
A4: GV.OC-03 | B4: Govern | C4: Organizational Context | D4: Legal, regulatory, and contractual cybersecurity requirements are understood and managed | E4: เข้าใจและบริหารข้อกำหนดด้านไซเบอร์ตามกฎหมาย กฎระเบียบ และสัญญา | F4: 10 | G4: GV-POL-005, GV-POL-004 | I4: GV-PRC-004, GV-PRC-005 | J4: GV-REG-001, GV-REG-006, GV-REG-007, GV-TPL-002, GV-FRM-005, GV-TPL-004
A5: GV.OC-04 | B5: Govern | C5: Organizational Context | D5: Critical objectives, capabilities, and services that external stakeholders depend on are understood | E5: เข้าใจวัตถุประสงค์ ขีดความสามารถ และบริการสำคัญที่ผู้มีส่วนได้ส่วนเสียภายนอกพึ่งพา | F5: 3 | G5: RC-POL-001 | J5: GV-RPT-001, ID-RPT-002
A6: GV.OC-05 | B6: Govern | C6: Organizational Context | D6: Outcomes, capabilities, and services that the organization depends on are understood | E6: เข้าใจผลลัพธ์ ขีดความสามารถ และบริการที่องค์กรต้องพึ่งพา | F6: 2 | J6: GV-RPT-001, ID-RPT-002
A7: GV.RM-01 | B7: Govern | C7: Risk Management Strategy | D7: Risk management objectives are established and agreed to by stakeholders | E7: กำหนดวัตถุประสงค์การบริหารความเสี่ยง และได้รับความเห็นชอบจากผู้มีส่วนได้ส่วนเสีย | F7: 3 | G7: GV-STR-001, GV-STM-001, GV-POL-002
A8: GV.RM-02 | B8: Govern | C8: Risk Management Strategy | D8: Risk appetite and risk tolerance statements are established, communicated, and maintained | E8: กำหนด สื่อสาร และดูแลเอกสารระดับความเสี่ยงที่ยอมรับได้และค่าความเบี่ยงเบนที่ยอมรับได้ | F8: 1 | G8: GV-STM-001
A9: GV.RM-03 | B9: Govern | C9: Risk Management Strategy | D9: Cybersecurity risk management is included in enterprise risk management processes | E9: รวมการบริหารความเสี่ยงด้านไซเบอร์ไว้ในกระบวนการบริหารความเสี่ยงองค์กร | F9: 2 | G9: GV-STM-001, GV-POL-002
A10: GV.RM-04 | B10: Govern | C10: Risk Management Strategy | D10: Strategic direction for appropriate risk response options is established and communicated | E10: กำหนดและสื่อสารทิศทางเชิงกลยุทธ์สำหรับทางเลือกในการจัดการความเสี่ยงที่เหมาะสม | F10: 2 | G10: GV-POL-002 | J10: GV-FRM-001
A11: GV.RM-05 | B11: Govern | C11: Risk Management Strategy | D11: Lines of communication for cybersecurity risks, including supplier risks, are established | E11: กำหนดช่องทางการสื่อสารความเสี่ยงด้านไซเบอร์ รวมถึงความเสี่ยงจากผู้ให้บริการ | F11: 1 | G11: GV-POL-002
A12: GV.RM-06 | B12: Govern | C12: Risk Management Strategy | D12: A standardized method for calculating, documenting, categorizing, and prioritizing risks is established | E12: กำหนดวิธีมาตรฐานในการคำนวณ บันทึก จัดหมวดหมู่ และจัดลำดับความสำคัญของความเสี่ยง | F12: 3 | I12: GV-PRC-001 | J12: GV-REG-005, ID-REG-005
A13: GV.RM-07 | B13: Govern | C13: Risk Management Strategy | D13: Strategic opportunities (positive risks) are characterized and included in discussions | E13: ระบุลักษณะของโอกาสเชิงกลยุทธ์ (ความเสี่ยงเชิงบวก) และนำเข้าสู่การพิจารณา | F13: 1 | G13: GV-POL-002
A14: GV.RR-01 | B14: Govern | C14: Roles, Responsibilities, and Authorities | D14: Leadership is responsible and accountable for cybersecurity risk and fosters a risk-aware culture | E14: ผู้นำองค์กรรับผิดชอบต่อความเสี่ยงด้านไซเบอร์ และส่งเสริมวัฒนธรรมที่ตระหนักถึงความเสี่ยง | F14: 3 | G14: GV-CHR-001, GV-CHR-002 | J14: GV-REG-003
A15: GV.RR-02 | B15: Govern | C15: Roles, Responsibilities, and Authorities | D15: Cybersecurity roles, responsibilities, and authorities are established, communicated, and enforced | E15: กำหนด สื่อสาร และบังคับใช้บทบาท ความรับผิดชอบ และอำนาจหน้าที่ด้านไซเบอร์ | F15: 2 | J15: GV-REG-003, GV-TPL-001
A16: GV.RR-03 | B16: Govern | C16: Roles, Responsibilities, and Authorities | D16: Adequate resources are allocated commensurate with risk strategy, roles, and policies | E16: จัดสรรทรัพยากรอย่างเพียงพอและสอดคล้องกับกลยุทธ์ความเสี่ยง บทบาท และนโยบาย | F16: 1 | I16: GV-PLN-001
A17: GV.RR-04 | B17: Govern | C17: Roles, Responsibilities, and Authorities | D17: Cybersecurity is included in human resources practices | E17: รวมเรื่องความมั่นคงปลอดภัยไซเบอร์ไว้ในการบริหารทรัพยากรบุคคล | F17: 5 | H17: GV-STD-001 | J17: GV-TPL-001, GV-FRM-002, GV-FRM-003, PR-REG-002
A18: GV.PO-01 | B18: Govern | C18: Policy | D18: Cybersecurity policy is established, communicated, and enforced based on context, strategy, and priorities | E18: กำหนด สื่อสาร และบังคับใช้นโยบายด้านไซเบอร์ตามบริบท กลยุทธ์ และลำดับความสำคัญ | F18: 6 | G18: GV-POL-001, GV-POL-003, GV-POL-005, GV-POL-004 | J18: GV-REG-005, GV-REG-006
A19: GV.PO-02 | B19: Govern | C19: Policy | D19: Cybersecurity policy is reviewed, updated, communicated, and enforced to reflect changes | E19: ทบทวน ปรับปรุง สื่อสาร และบังคับใช้นโยบายด้านไซเบอร์ให้สอดคล้องกับการเปลี่ยนแปลง | F19: 3 | G19: GV-POL-001 | I19: GV-PRC-002, GV-PRC-003
A20: GV.OV-01 | B20: Govern | C20: Oversight | D20: Risk management strategy outcomes are reviewed to inform and adjust strategy and direction | E20: ทบทวนผลลัพธ์ของกลยุทธ์การบริหารความเสี่ยง เพื่อใช้ปรับกลยุทธ์และทิศทาง | F20: 6 | G20: GV-CHR-001, GV-STR-001, GV-CHR-002 | I20: GV-PRC-006 | J20: GV-REC-001, GV-TPL-005
A21: GV.OV-02 | B21: Govern | C21: Oversight | D21: Risk management strategy is reviewed and adjusted to ensure coverage of requirements and risks | E21: ทบทวนและปรับกลยุทธ์การบริหารความเสี่ยงให้ครอบคลุมข้อกำหนดและความเสี่ยง | F21: 7 | G21: GV-CHR-002 | I21: GV-PRC-006, GV-PRC-007, GV-PLN-002 | J21: GV-REG-004, GV-REC-001, GV-TPL-006
A22: GV.OV-03 | B22: Govern | C22: Oversight | D22: Risk management performance is evaluated and reviewed for adjustments needed | E22: ประเมินและทบทวนผลการดำเนินงานด้านการบริหารความเสี่ยง เพื่อปรับปรุงตามความจำเป็น | F22: 3 | I22: GV-PRC-006 | J22: GV-REG-008, GV-TPL-005
A23: GV.SC-01 | B23: Govern | C23: Cybersecurity Supply Chain Risk Management | D23: A cybersecurity supply chain risk management program, strategy, objectives, policies, and processes are established | E23: กำหนดแผนงาน กลยุทธ์ วัตถุประสงค์ นโยบาย และกระบวนการบริหารความเสี่ยงห่วงโซ่อุปทานด้านไซเบอร์ | F23: 1 | G23: GV-POL-006
A24: GV.SC-02 | B24: Govern | C24: Cybersecurity Supply Chain Risk Management | D24: Cybersecurity roles for suppliers, customers, and partners are established and coordinated | E24: กำหนดและประสานบทบาทด้านไซเบอร์ของผู้ให้บริการ ลูกค้า และคู่ค้า | F24: 1 | G24: GV-POL-006
A25: GV.SC-03 | B25: Govern | C25: Cybersecurity Supply Chain Risk Management | D25: Supply chain risk management is integrated into cybersecurity and enterprise risk management | E25: บูรณาการการบริหารความเสี่ยงห่วงโซ่อุปทานเข้ากับการบริหารความเสี่ยงด้านไซเบอร์และความเสี่ยงองค์กร | F25: 2 | G25: GV-POL-002, GV-POL-006
A26: GV.SC-04 | B26: Govern | C26: Cybersecurity Supply Chain Risk Management | D26: Suppliers are known and prioritized by criticality | E26: รู้จักผู้ให้บริการทั้งหมดและจัดลำดับตามความสำคัญ | F26: 2 | I26: GV-PRC-008 | J26: GV-REG-009
A27: GV.SC-05 | B27: Govern | C27: Cybersecurity Supply Chain Risk Management | D27: Requirements to address supply chain risks are established, prioritized, and integrated into contracts | E27: กำหนดข้อกำหนดเพื่อจัดการความเสี่ยงห่วงโซ่อุปทาน จัดลำดับความสำคัญ และใส่ไว้ในสัญญา | F27: 5 | H27: GV-STD-002, PR-STD-014 | I27: DE-GDL-001 | J27: GV-FRM-002, GV-TPL-004
A28: GV.SC-06 | B28: Govern | C28: Cybersecurity Supply Chain Risk Management | D28: Planning and due diligence are performed to reduce risks before entering supplier relationships | E28: วางแผนและตรวจสอบรายละเอียดเพื่อลดความเสี่ยงก่อนเริ่มความสัมพันธ์กับผู้ให้บริการ | F28: 2 | I28: GV-PRC-008 | J28: GV-FRM-006
A29: GV.SC-07 | B29: Govern | C29: Cybersecurity Supply Chain Risk Management | D29: Supplier risks are understood, recorded, prioritized, assessed, responded to, and monitored | E29: เข้าใจ บันทึก จัดลำดับ ประเมิน จัดการ และติดตามความเสี่ยงจากผู้ให้บริการ | F29: 3 | I29: GV-PRC-008 | J29: GV-FRM-006, PR-FRM-003
A30: GV.SC-08 | B30: Govern | C30: Cybersecurity Supply Chain Risk Management | D30: Relevant suppliers are included in incident planning, response, and recovery activities | E30: ให้ผู้ให้บริการที่เกี่ยวข้องมีส่วนในการวางแผน ตอบสนอง และกู้คืนจากเหตุการณ์ | F30: 3 | H30: GV-STD-002 | I30: RS-PLN-001 | J30: RS-REG-002
A31: GV.SC-09 | B31: Govern | C31: Cybersecurity Supply Chain Risk Management | D31: Supply chain security practices are integrated and monitored throughout the technology product and service life cycle | E31: บูรณาการและติดตามแนวปฏิบัติด้านความมั่นคงปลอดภัยของห่วงโซ่อุปทานตลอดวงจรชีวิตของผลิตภัณฑ์และบริการเทคโนโลยี | F31: 1 | H31: GV-STD-003
A32: GV.SC-10 | B32: Govern | C32: Cybersecurity Supply Chain Risk Management | D32: Supply chain risk management plans include provisions for activities after a partnership or service ends | E32: แผนบริหารความเสี่ยงห่วงโซ่อุปทานครอบคลุมกิจกรรมหลังสิ้นสุดความร่วมมือหรือบริการ | F32: 2 | I32: GV-PRC-008 | J32: GV-FRM-007
A33: ID.AM-01 | B33: Identify | C33: Asset Management | D33: Inventories of hardware managed by the organization are maintained | E33: ดูแลทะเบียนฮาร์ดแวร์ที่องค์กรบริหารจัดการ | F33: 3 | H33: ID-STD-001 | J33: ID-REG-001, ID-REG-004
A34: ID.AM-02 | B34: Identify | C34: Asset Management | D34: Inventories of software, services, and systems managed by the organization are maintained | E34: ดูแลทะเบียนซอฟต์แวร์ บริการ และระบบที่องค์กรบริหารจัดการ | F34: 4 | H34: ID-STD-001 | J34: ID-REG-002, ID-REG-004, PR-REG-003
A35: ID.AM-03 | B35: Identify | C35: Asset Management | D35: Representations of authorized network communication and data flows are maintained | E35: ดูแลแผนภาพการสื่อสารผ่านเครือข่ายและการไหลของข้อมูลที่ได้รับอนุญาต | F35: 2 | J35: ID-REG-003, ID-RPT-001
A36: ID.AM-04 | B36: Identify | C36: Asset Management | D36: Inventories of services provided by suppliers are maintained | E36: ดูแลทะเบียนบริการที่ได้รับจากผู้ให้บริการ | F36: 3 | H36: ID-STD-001 | J36: GV-REG-009, ID-REG-002
A37: ID.AM-05 | B37: Identify | C37: Asset Management | D37: Assets are prioritized based on classification, criticality, resources, and impact on the mission | E37: จัดลำดับความสำคัญของทรัพย์สินตามชั้นข้อมูล ความสำคัญ ทรัพยากร และผลกระทบต่อพันธกิจ | F37: 5 | H37: ID-STD-001 | J37: ID-REG-001, ID-REG-002, ID-REG-004, ID-RPT-002
A38: ID.AM-07 | B38: Identify | C38: Asset Management | D38: Inventories of data and corresponding metadata for designated data types are maintained | E38: ดูแลทะเบียนข้อมูลและ metadata ของประเภทข้อมูลที่กำหนด | F38: 3 | H38: ID-STD-001 | J38: GV-REG-007, ID-REG-003
A39: ID.AM-08 | B39: Identify | C39: Asset Management | D39: Systems, hardware, software, services, and data are managed throughout their life cycles | E39: บริหารระบบ ฮาร์ดแวร์ ซอฟต์แวร์ บริการ และข้อมูลตลอดวงจรชีวิต | F39: 5 | H39: ID-STD-001, PR-STD-007 | I39: ID-PRC-001 | J39: GV-FRM-003, ID-FRM-001
A40: ID.RA-01 | B40: Identify | C40: Risk Assessment | D40: Vulnerabilities in assets are identified, validated, and recorded | E40: ระบุ ยืนยัน และบันทึกช่องโหว่ของทรัพย์สิน | F40: 6 | H40: ID-STD-002 | I40: ID-PRC-002, ID-PRC-003, PR-PRC-007 | J40: ID-REG-006, ID-FRM-002
A41: ID.RA-02 | B41: Identify | C41: Risk Assessment | D41: Cyber threat intelligence is received from information sharing forums and sources | E41: รับข้อมูลข่าวกรองภัยคุกคามไซเบอร์จากเวทีและแหล่งแลกเปลี่ยนข้อมูล | F41: 1 | I41: ID-PRC-004
A42: ID.RA-03 | B42: Identify | C42: Risk Assessment | D42: Internal and external threats to the organization are identified and recorded | E42: ระบุและบันทึกภัยคุกคามจากภายในและภายนอกองค์กร | F42: 3 | I42: GV-PRC-001, ID-PRC-004 | J42: ID-REG-005
A43: ID.RA-04 | B43: Identify | C43: Risk Assessment | D43: Potential impacts and likelihoods of threats exploiting vulnerabilities are identified and recorded | E43: ระบุและบันทึกผลกระทบและโอกาสที่ภัยคุกคามจะใช้ประโยชน์จากช่องโหว่ | F43: 5 | I43: GV-PRC-001, GV-PRC-004 | J43: GV-TPL-003, ID-REG-005, ID-RPT-003
A44: ID.RA-05 | B44: Identify | C44: Risk Assessment | D44: Threats, vulnerabilities, likelihoods, and impacts are used to understand inherent risk and inform prioritization | E44: ใช้ข้อมูลภัยคุกคาม ช่องโหว่ โอกาส และผลกระทบ เพื่อเข้าใจความเสี่ยงตั้งต้นและจัดลำดับความสำคัญ | F44: 3 | I44: GV-PRC-001 | J44: ID-REG-005, ID-RPT-003
A45: ID.RA-06 | B45: Identify | C45: Risk Assessment | D45: Risk responses are chosen, prioritized, planned, tracked, and communicated | E45: เลือก จัดลำดับ วางแผน ติดตาม และสื่อสารการจัดการความเสี่ยง | F45: 5 | I45: GV-PRC-001, ID-PLN-001 | J45: GV-FRM-001, ID-REG-005, ID-REG-006
A46: ID.RA-07 | B46: Identify | C46: Risk Assessment | D46: Changes and exceptions are managed, assessed for risk impact, recorded, and tracked | E46: บริหาร ประเมินผลกระทบด้านความเสี่ยง บันทึก และติดตามการเปลี่ยนแปลงและข้อยกเว้น | F46: 5 | I46: GV-PRC-003, PR-PRC-006 | J46: GV-FRM-004, GV-REG-004, PR-FRM-005
A47: ID.RA-08 | B47: Identify | C47: Risk Assessment | D47: Processes for receiving, analyzing, and responding to vulnerability disclosures are established | E47: กำหนดกระบวนการรับ วิเคราะห์ และตอบสนองต่อการแจ้งช่องโหว่ | F47: 2 | I47: ID-PRC-002, ID-PRC-005
A48: ID.RA-09 | B48: Identify | C48: Risk Assessment | D48: The authenticity and integrity of hardware and software are assessed prior to acquisition and use | E48: ประเมินความถูกต้องแท้จริงและความครบถ้วนของฮาร์ดแวร์และซอฟต์แวร์ก่อนจัดหาและใช้งาน | F48: 1 | H48: GV-STD-003
A49: ID.RA-10 | B49: Identify | C49: Risk Assessment | D49: Critical suppliers are assessed prior to acquisition | E49: ประเมินผู้ให้บริการสำคัญก่อนการจัดหา | F49: 3 | H49: GV-STD-003 | I49: GV-PRC-008 | J49: GV-FRM-006
A50: ID.IM-01 | B50: Identify | C50: Improvement | D50: Improvements are identified from evaluations | E50: ระบุสิ่งที่ต้องปรับปรุงจากการประเมิน | F50: 5 | I50: GV-PRC-007, ID-PRC-006 | J50: GV-REG-008, GV-TPL-006, ID-REG-007
A51: ID.IM-02 | B51: Identify | C51: Improvement | D51: Improvements are identified from security tests and exercises | E51: ระบุสิ่งที่ต้องปรับปรุงจากการทดสอบและการฝึกซ้อมด้านความมั่นคงปลอดภัย | F51: 5 | I51: ID-PRC-003, ID-PRC-006, ID-PLN-002 | J51: ID-REG-007, RC-REC-001
A52: ID.IM-03 | B52: Identify | C52: Improvement | D52: Improvements are identified from execution of operational processes, procedures, and activities | E52: ระบุสิ่งที่ต้องปรับปรุงจากการปฏิบัติตามกระบวนการ ระเบียบปฏิบัติ และกิจกรรมต่าง ๆ | F52: 3 | I52: ID-PRC-006 | J52: ID-REG-007, ID-TPL-001
A53: ID.IM-04 | B53: Identify | C53: Improvement | D53: Incident response plans and other cybersecurity plans that affect operations are established, communicated, maintained, and improved | E53: จัดทำ สื่อสาร ดูแล และปรับปรุงแผนรับมือเหตุการณ์และแผนด้านไซเบอร์อื่นที่กระทบการปฏิบัติงาน | F53: 5 | I53: ID-PRC-006, ID-PLN-002, RS-PLN-001 | J53: ID-REG-007, ID-TPL-001
A54: PR.AA-01 | B54: Protect | C54: Identity Management, Authentication, and Access Control | D54: Identities and credentials for authorized users, services, and hardware are managed | E54: บริหารตัวตนและข้อมูลยืนยันตัวตนของผู้ใช้ บริการ และฮาร์ดแวร์ที่ได้รับอนุญาต | F54: 6 | G54: PR-POL-001 | H54: PR-STD-001, PR-STD-002 | I54: PR-PRC-001 | J54: PR-FRM-001, PR-REG-001
A55: PR.AA-02 | B55: Protect | C55: Identity Management, Authentication, and Access Control | D55: Identities are proofed and bound to credentials based on the context of interactions | E55: พิสูจน์ตัวตนและผูกตัวตนกับข้อมูลยืนยันตัวตนตามบริบทของการใช้งาน | F55: 2 | G55: PR-POL-001 | H55: PR-STD-001
A56: PR.AA-03 | B56: Protect | C56: Identity Management, Authentication, and Access Control | D56: Users, services, and hardware are authenticated | E56: ยืนยันตัวตนของผู้ใช้ บริการ และฮาร์ดแวร์ | F56: 4 | G56: PR-POL-001 | H56: PR-STD-001, PR-STD-003, PR-STD-009
A57: PR.AA-04 | B57: Protect | C57: Identity Management, Authentication, and Access Control | D57: Identity assertions are protected, conveyed, and verified | E57: ปกป้อง ส่งต่อ และตรวจสอบการยืนยันตัวตน (identity assertion) | F57: 2 | G57: PR-POL-001 | H57: PR-STD-001
A58: PR.AA-05 | B58: Protect | C58: Identity Management, Authentication, and Access Control | D58: Access permissions, entitlements, and authorizations are defined, managed, enforced, and reviewed | E58: กำหนด บริหาร บังคับใช้ และทบทวนสิทธิ์การเข้าถึงและการอนุญาต | F58: 13 | G58: PR-POL-001 | H58: GV-STD-001, PR-STD-002, PR-STD-003, PR-STD-014 | I58: PR-PRC-001, PR-PRC-002 | J58: GV-FRM-003, PR-FRM-001, PR-FRM-002, PR-FRM-003, PR-REC-001, PR-REG-001
A59: PR.AA-06 | B59: Protect | C59: Identity Management, Authentication, and Access Control | D59: Physical access to assets is managed, monitored, and enforced commensurate with risk | E59: บริหาร เฝ้าระวัง และบังคับใช้การเข้าถึงทางกายภาพตามระดับความเสี่ยง | F59: 3 | G59: PR-POL-002 | I59: PR-PRC-003 | J59: PR-FRM-004
A60: PR.AT-01 | B60: Protect | C60: Awareness and Training | D60: Personnel are provided with awareness and training for general tasks with cybersecurity risks in mind | E60: จัดให้บุคลากรได้รับการสร้างความตระหนักรู้และการฝึกอบรมสำหรับงานทั่วไปโดยคำนึงถึงความเสี่ยงด้านไซเบอร์ | F60: 4 | G60: GV-POL-003 | I60: PR-PLN-001, PR-PRC-004 | J60: PR-REC-002
A61: PR.AT-02 | B61: Protect | C61: Awareness and Training | D61: Individuals in specialized roles are provided with awareness and training for those roles | E61: จัดให้ผู้ที่อยู่ในบทบาทเฉพาะทางได้รับการสร้างความตระหนักรู้และการฝึกอบรมสำหรับบทบาทนั้น | F61: 3 | I61: PR-PLN-001 | J61: PR-REG-002, PR-REC-002
A62: PR.DS-01 | B62: Protect | C62: Data Security | D62: The confidentiality, integrity, and availability of data-at-rest are protected | E62: ปกป้องความลับ ความถูกต้องครบถ้วน และความพร้อมใช้งานของข้อมูลที่จัดเก็บ | F62: 7 | G62: PR-POL-003 | H62: PR-STD-004, PR-STD-005, PR-STD-007, PR-STD-008, PR-STD-009 | J62: ID-FRM-001
A63: PR.DS-02 | B63: Protect | C63: Data Security | D63: The confidentiality, integrity, and availability of data-in-transit are protected | E63: ปกป้องความลับ ความถูกต้องครบถ้วน และความพร้อมใช้งานของข้อมูลระหว่างการรับส่ง | F63: 4 | G63: PR-POL-003 | H63: PR-STD-004, PR-STD-005, PR-STD-008
A64: PR.DS-10 | B64: Protect | C64: Data Security | D64: The confidentiality, integrity, and availability of data-in-use are protected | E64: ปกป้องความลับ ความถูกต้องครบถ้วน และความพร้อมใช้งานของข้อมูลระหว่างการใช้งาน | F64: 4 | G64: GV-POL-005, PR-POL-003 | H64: PR-STD-004, PR-STD-008
A65: PR.DS-11 | B65: Protect | C65: Data Security | D65: Backups of data are created, protected, maintained, and tested | E65: สร้าง ปกป้อง ดูแล และทดสอบข้อมูลสำรอง | F65: 3 | H65: PR-STD-006 | I65: PR-PRC-005 | J65: PR-REC-003
A66: PR.PS-01 | B66: Protect | C66: Platform Security | D66: Configuration management practices are established and applied | E66: กำหนดและใช้แนวปฏิบัติการบริหารการตั้งค่า | F66: 6 | H66: PR-STD-009, PR-STD-010, PR-STD-014, PR-STD-015 | I66: PR-PRC-006 | J66: PR-FRM-005
A67: PR.PS-02 | B67: Protect | C67: Platform Security | D67: Software is maintained, replaced, and removed commensurate with risk | E67: ดูแล เปลี่ยน และถอดถอนซอฟต์แวร์ตามระดับความเสี่ยง | F67: 4 | H67: ID-STD-002, PR-STD-015 | I67: ID-PRC-002, PR-PRC-007
A68: PR.PS-03 | B68: Protect | C68: Platform Security | D68: Hardware is maintained, replaced, and removed commensurate with risk | E68: ดูแล เปลี่ยน และถอดถอนฮาร์ดแวร์ตามระดับความเสี่ยง | F68: 2 | I68: ID-PRC-001, PR-PRC-007
A69: PR.PS-04 | B69: Protect | C69: Platform Security | D69: Log records are generated and made available for continuous monitoring | E69: สร้างบันทึก log และจัดให้พร้อมใช้สำหรับการเฝ้าระวังอย่างต่อเนื่อง | F69: 2 | H69: PR-STD-011 | J69: DE-REG-001
A70: PR.PS-05 | B70: Protect | C70: Platform Security | D70: Installation and execution of unauthorized software are prevented | E70: ป้องกันการติดตั้งและการเรียกใช้ซอฟต์แวร์ที่ไม่ได้รับอนุญาต | F70: 2 | H70: PR-STD-012 | J70: PR-REG-003
A71: PR.PS-06 | B71: Protect | C71: Platform Security | D71: Secure software development practices are integrated and their performance is monitored | E71: บูรณาการแนวปฏิบัติการพัฒนาซอฟต์แวร์อย่างปลอดภัย และติดตามผลการดำเนินงาน | F71: 1 | H71: PR-STD-013
A72: PR.IR-01 | B72: Protect | C72: Technology Infrastructure Resilience | D72: Networks and environments are protected from unauthorized logical access and usage | E72: ปกป้องเครือข่ายและสภาพแวดล้อมจากการเข้าถึงและการใช้งานทางตรรกะโดยไม่ได้รับอนุญาต | F72: 7 | H72: PR-STD-003, PR-STD-014, PR-STD-015, PR-STD-016 | I72: PR-PRC-008 | J72: ID-RPT-001, PR-FRM-006
A73: PR.IR-02 | B73: Protect | C73: Technology Infrastructure Resilience | D73: Technology assets are protected from environmental threats | E73: ปกป้องทรัพย์สินเทคโนโลยีจากภัยคุกคามด้านสภาพแวดล้อม | F73: 1 | G73: PR-POL-002
A74: PR.IR-03 | B74: Protect | C74: Technology Infrastructure Resilience | D74: Mechanisms are implemented to achieve resilience requirements in normal and adverse situations | E74: จัดให้มีกลไกที่ทำให้บรรลุข้อกำหนดด้านความยืดหยุ่นทั้งในสถานการณ์ปกติและไม่ปกติ | F74: 1 | H74: PR-STD-017
A75: PR.IR-04 | B75: Protect | C75: Technology Infrastructure Resilience | D75: Adequate resource capacity to ensure availability is maintained | E75: ดูแลให้มีขีดความสามารถของทรัพยากรเพียงพอต่อความพร้อมใช้งาน | F75: 1 | H75: PR-STD-017
A76: DE.CM-01 | B76: Detect | C76: Continuous Monitoring | D76: Networks and network services are monitored to find potentially adverse events | E76: เฝ้าระวังเครือข่ายและบริการเครือข่ายเพื่อค้นหาเหตุการณ์ที่อาจไม่พึงประสงค์ | F76: 5 | H76: PR-STD-011, DE-STD-001 | I76: DE-PRC-001 | J76: DE-REG-001, DE-REG-002
A77: DE.CM-02 | B77: Detect | C77: Continuous Monitoring | D77: The physical environment is monitored to find potentially adverse events | E77: เฝ้าระวังสภาพแวดล้อมทางกายภาพเพื่อค้นหาเหตุการณ์ที่อาจไม่พึงประสงค์ | F77: 3 | G77: PR-POL-002 | H77: DE-STD-001 | I77: PR-PRC-003
A78: DE.CM-03 | B78: Detect | C78: Continuous Monitoring | D78: Personnel activity and technology usage are monitored to find potentially adverse events | E78: เฝ้าระวังกิจกรรมของบุคลากรและการใช้เทคโนโลยีเพื่อค้นหาเหตุการณ์ที่อาจไม่พึงประสงค์ | F78: 3 | H78: PR-STD-011, DE-STD-001 | I78: DE-PRC-001
A79: DE.CM-06 | B79: Detect | C79: Continuous Monitoring | D79: External service provider activities and services are monitored to find potentially adverse events | E79: เฝ้าระวังกิจกรรมและบริการของผู้ให้บริการภายนอกเพื่อค้นหาเหตุการณ์ที่อาจไม่พึงประสงค์ | F79: 2 | H79: DE-STD-001 | I79: DE-GDL-001
A80: DE.CM-09 | B80: Detect | C80: Continuous Monitoring | D80: Computing hardware and software, runtime environments, and their data are monitored to find potentially adverse events | E80: เฝ้าระวังฮาร์ดแวร์ ซอฟต์แวร์ สภาพแวดล้อมการทำงาน และข้อมูล เพื่อค้นหาเหตุการณ์ที่อาจไม่พึงประสงค์ | F80: 6 | H80: PR-STD-011, PR-STD-012, DE-STD-001 | I80: DE-PRC-001 | J80: DE-REG-001, DE-REG-002
A81: DE.AE-02 | B81: Detect | C81: Adverse Event Analysis | D81: Potentially adverse events are analyzed to better understand associated activities | E81: วิเคราะห์เหตุการณ์ที่อาจไม่พึงประสงค์เพื่อเข้าใจกิจกรรมที่เกี่ยวข้อง | F81: 3 | I81: DE-PRC-002, DE-PRC-003 | J81: DE-REG-002
A82: DE.AE-03 | B82: Detect | C82: Adverse Event Analysis | D82: Information is correlated from multiple sources | E82: เชื่อมโยงข้อมูลจากหลายแหล่ง | F82: 2 | I82: DE-PRC-002, DE-PRC-003
A83: DE.AE-04 | B83: Detect | C83: Adverse Event Analysis | D83: The estimated impact and scope of adverse events are understood | E83: เข้าใจผลกระทบและขอบเขตโดยประมาณของเหตุการณ์ไม่พึงประสงค์ | F83: 2 | H83: DE-STD-002 | I83: DE-PRC-002
A84: DE.AE-06 | B84: Detect | C84: Adverse Event Analysis | D84: Information on adverse events is provided to authorized staff and tools | E84: ส่งข้อมูลเหตุการณ์ไม่พึงประสงค์ให้บุคลากรและเครื่องมือที่ได้รับอนุญาต | F84: 2 | I84: DE-PRC-001, DE-PRC-002
A85: DE.AE-07 | B85: Detect | C85: Adverse Event Analysis | D85: Cyber threat intelligence and other contextual information are integrated into the analysis | E85: นำข่าวกรองภัยคุกคามไซเบอร์และข้อมูลบริบทอื่นมาใช้ในการวิเคราะห์ | F85: 3 | I85: DE-PRC-002, DE-PRC-003 | J85: DE-REG-002
A86: DE.AE-08 | B86: Detect | C86: Adverse Event Analysis | D86: Incidents are declared when adverse events meet the defined incident criteria | E86: ประกาศเป็นเหตุการณ์ (incident) เมื่อเหตุการณ์ไม่พึงประสงค์เข้าเกณฑ์ที่กำหนด | F86: 1 | H86: DE-STD-002
A87: RS.MA-01 | B87: Respond | C87: Incident Management | D87: The incident response plan is executed in coordination with relevant third parties once an incident is declared | E87: ดำเนินการตามแผนรับมือเหตุการณ์ร่วมกับบุคคลภายนอกที่เกี่ยวข้องเมื่อมีการประกาศเหตุการณ์ | F87: 2 | I87: RS-PLN-001 | J87: RS-REG-002
A88: RS.MA-02 | B88: Respond | C88: Incident Management | D88: Incident reports are triaged and validated | E88: คัดกรองและยืนยันรายงานเหตุการณ์ | F88: 3 | I88: RS-PRC-001 | J88: RS-FRM-001, RS-REG-001
A89: RS.MA-03 | B89: Respond | C89: Incident Management | D89: Incidents are categorized and prioritized | E89: จัดหมวดหมู่และจัดลำดับความสำคัญของเหตุการณ์ | F89: 4 | H89: DE-STD-002 | I89: RS-PRC-001, RS-PLB-003 | J89: RS-REG-001
A90: RS.MA-04 | B90: Respond | C90: Incident Management | D90: Incidents are escalated or elevated as needed | E90: ยกระดับเหตุการณ์ตามความจำเป็น | F90: 3 | I90: RS-PLN-001, RS-PRC-001, RC-PLN-003
A91: RS.MA-05 | B91: Respond | C91: Incident Management | D91: The criteria for initiating incident recovery are applied | E91: ใช้เกณฑ์ที่กำหนดในการเริ่มกู้คืนจากเหตุการณ์ | F91: 2 | I91: RS-PLN-001, RS-PRC-001
A92: RS.AN-03 | B92: Respond | C92: Incident Analysis | D92: Analysis is performed to establish what has taken place during an incident and the root cause | E92: วิเคราะห์เพื่อระบุสิ่งที่เกิดขึ้นระหว่างเหตุการณ์และสาเหตุที่แท้จริง | F92: 5 | I92: RS-PLB-001, RS-PLB-002, RS-PRC-002 | J92: RS-REG-001, RS-TPL-001
A93: RS.AN-06 | B93: Respond | C93: Incident Analysis | D93: Actions performed during an investigation are recorded and the records' integrity and provenance are preserved | E93: บันทึกการดำเนินการระหว่างการสอบสวน และรักษาความถูกต้องครบถ้วนและที่มาของบันทึก | F93: 3 | I93: RS-PRC-002 | J93: RS-FRM-002, RS-TPL-001
A94: RS.AN-07 | B94: Respond | C94: Incident Analysis | D94: Incident data and metadata are collected, and their integrity and provenance are preserved | E94: เก็บรวบรวมข้อมูลและ metadata ของเหตุการณ์ และรักษาความถูกต้องครบถ้วนและที่มา | F94: 2 | I94: RS-PRC-002 | J94: RS-FRM-002
A95: RS.AN-08 | B95: Respond | C95: Incident Analysis | D95: An incident's magnitude is estimated and validated | E95: ประมาณและยืนยันขนาดของเหตุการณ์ | F95: 4 | I95: RS-PLB-003, RS-PRC-002 | J95: RS-REG-001, RS-TPL-001
A96: RS.CO-02 | B96: Respond | C96: Incident Response Reporting and Communication | D96: Internal and external stakeholders are notified of incidents | E96: แจ้งเหตุการณ์ต่อผู้มีส่วนได้ส่วนเสียภายในและภายนอก | F96: 5 | I96: RS-PLN-001, RS-PLB-003, RS-PRC-003 | J96: RS-REG-002, RS-TPL-002
A97: RS.CO-03 | B97: Respond | C97: Incident Response Reporting and Communication | D97: Information is shared with designated internal and external stakeholders | E97: แบ่งปันข้อมูลกับผู้มีส่วนได้ส่วนเสียภายในและภายนอกที่กำหนด | F97: 5 | I97: RS-PLN-001, RS-PLB-003, RS-PRC-003 | J97: RS-REG-002, RS-TPL-002
A98: RS.MI-01 | B98: Respond | C98: Incident Mitigation | D98: Incidents are contained | E98: ควบคุมการแพร่กระจายของเหตุการณ์ | F98: 4 | I98: RS-PRC-001, RS-PLB-001, RS-PLB-002, RS-PLB-004
A99: RS.MI-02 | B99: Respond | C99: Incident Mitigation | D99: Incidents are eradicated | E99: กำจัดต้นเหตุของเหตุการณ์ | F99: 4 | I99: RS-PRC-001, RS-PLB-001, RS-PLB-002, RS-PLB-004
A100: RC.RP-01 | B100: Recover | C100: Incident Recovery Plan Execution | D100: The recovery portion of the incident response plan is executed once initiated | E100: ดำเนินการส่วนการกู้คืนของแผนรับมือเหตุการณ์เมื่อเริ่มกระบวนการ | F100: 3 | G100: RC-POL-001 | I100: RC-PLN-001, RC-PLN-002
...

Sheet Hierarchy
A1: Parent ID | B1: Parent Title | C1: Parent Tier | D1: Child ID | E1: Child Title | F1: Child Tier
A2: GV-CHR-001 | B2: Cybersecurity Governance Charter | C2: T0 | D2: GV-STR-001 | E2: Cybersecurity Strategy and Roadmap | F2: T0
A3: GV-CHR-001 | B3: Cybersecurity Governance Charter | C3: T0 | D3: GV-RPT-001 | E3: Organizational Context and ISMS Scope Statement | F3: T4
A4: GV-RPT-001 | B4: Organizational Context and ISMS Scope Statement | C4: T4 | D4: GV-REG-001 | E4: Legal, Regulatory, and Contractual Requirements Register | F4: T4
A5: GV-RPT-001 | B5: Organizational Context and ISMS Scope Statement | C5: T4 | D5: GV-REG-002 | E5: Stakeholder Requirements Register | F5: T4
A6: GV-CHR-001 | B6: Cybersecurity Governance Charter | C6: T0 | D6: GV-STM-001 | E6: Risk Appetite and Tolerance Statement | F6: T0
A7: GV-POL-001 | B7: Information Security Policy | C7: T1 | D7: GV-POL-002 | E7: Cybersecurity Risk Management Policy | F7: T1
A8: GV-STM-001 | B8: Risk Appetite and Tolerance Statement | C8: T0 | D8: GV-POL-002 | E8: Cybersecurity Risk Management Policy | F8: T1
A9: GV-POL-002 | B9: Cybersecurity Risk Management Policy | C9: T1 | D9: GV-PRC-001 | E9: Risk Assessment and Treatment Methodology | F9: T3
A10: GV-PRC-001 | B10: Risk Assessment and Treatment Methodology | C10: T3 | D10: GV-FRM-001 | E10: Risk Acceptance Form | F10: T4
A11: GV-CHR-001 | B11: Cybersecurity Governance Charter | C11: T0 | D11: GV-CHR-002 | E11: Information Security Steering Committee Terms of Reference | F11: T0
A12: GV-CHR-001 | B12: Cybersecurity Governance Charter | C12: T0 | D12: GV-REG-003 | E12: Cybersecurity Roles, Responsibilities, and RACI Matrix | F12: T4
... A146: RC-PRC-002 | B146: Crisis Communication Procedure | C146: T3 | D146: RC-TPL-001 | E146: Public Statement and Stakeholder Update Templates | F146: T4

Sheet Verify List
A1: Document ID | B1: Title | C1: Items Marked [VERIFY] | D1: Basis
A2: DE-STD-002 | B2: Incident Classification and Severity Standard | C2: 3 | D2: CRC Notification on CII duties 2024 (incident reporting within 24 hours) [VERIFY]; ISO/IEC 27001:2022 Annex A 5.25
A3: GV-POL-004 | B3: Personal Data Protection Policy | C3: 3 | D3: PDPA s.37(1); PDPC Notification on Security Measures B.E. 2565
A4: GV-PRC-004 | B4: Data Protection Impact Assessment (DPIA) Procedure | C4: 1 | D4: Not explicitly mandated by the PDPA; supports the risk-based measures in PDPA s.37(1) [VERIFY current PDPC guidance]
A5: GV-PRC-007 | B5: Internal Audit Procedure | C5: 2 | D5: ISO/IEC 27001:2022 Clause 9.2; CSA s.54
A6: GV-REG-001 | B6: Legal, Regulatory, and Contractual Requirements Register | C6: 2 | D6: ISO/IEC 27001:2022 Annex A 5.31; PDPA; CSA
A7: GV-REG-006 | B7: CII Code of Practice Compliance Matrix | C7: 3 | D7: CSA s.44; NCSC Notification on Code of Practice and Standard Framework B.E. 2564; CRC Notification on CII duties 2024 [VERIFY]
A8: GV-REG-007 | B8: Record of Processing Activities (ROPA) | C8: 2 | D8: PDPA s.39 (controller) and s.40 (processor)
A9: GV-TPL-002 | B9: Privacy Notice Template | C9: 1 | D9: PDPA s.23
A10: ID-PLN-002 | B10: Cybersecurity Exercise and Testing Program | C10: 1 | D10: CSA s.56 (readiness tests); CRC Notification on CII duties 2024 (annual BCP exercise) [VERIFY]
A11: ID-RPT-002 | B11: Business Impact Analysis (BIA) | C11: 1 | D11: ISO 22301:2019 Clause 8.2.2; CRC Notification on CII duties 2024 (BCP criteria) [VERIFY]
A12: ID-RPT-003 | B12: Cybersecurity Risk Assessment Report | C12: 3 | D12: CSA s.54 (annual risk assessment; summary to NCSA within 30 days); CRC Notification on CII duties 2024 [VERIFY]
A13: PR-STD-007 | B13: Data Retention and Disposal Standard | C13: 10 | D13: PDPA s.37(3); ISO/IEC 27001:2022 Annex A 5.33 and 8.10
... A22: RS-TPL-002 | B22: Regulatory Notification Templates | C22: 4 | D22: PDPA s.37(4); CSA s.57
